Workbook

Sheet 全運通
K3: 日期 | L3: =NOW() -> 46083.416
A4: 員工出勤動態日報表
A5: 單位 | J5: 人數統計 | K5: 單位加總 | L5: 實到人數 | M5: 出勤率
A6: 全運通 | B6: 土城廠 | C6: 主管 | J6: =COUNTA(D6:I6) -> 0 | K6: =J6+J7+J9 -> 2 | L6: 2 | M6: =L6/K6 -> 1
C7: 土城行政助理 | D7: 陳泱瑄 | J7: =COUNTA(D7:I7) -> 1 | S7: =COUNTA(D7:R7) -> 2
B8: 中和廠 | C8: 主管 | J8: =COUNTA(D8:I8) -> 0 | S8: =COUNTA(D8:R8) -> 1
C9: 中和行政助理 | D9: 陳蓉穎 | J9: =COUNTA(D9:I9) -> 1 | S9: =COUNTA(D9:R9) -> 2 | T9: =SUM(S7:S9) -> 5 | V9: 總員編 | W9: 3 | Y9: 3 | Z9: 0 | AA9: 0 | AB9: =SUM(Y9:AA9) -> 3 | AC9: =T9 -> 5 | AD9: =IF(AB9<AC9,AC9-AB9,0) -> 2 | AE9: =IF(AB9>AC9,AB9-AC9,0) -> 0

Sheet Sheet2
A1: 室/站/專案
D2: 編制人數 | E2: 現有人數 | F2: 缺額 | G2: 41275 | H2: 41358 | I2: 1-3離職人數 | J2: 離職率
A3: 總經理室 | D3: 10 | E3: 7 | F3: =D3-E3 -> 3 | G3: 10 | H3: =E3 -> 7 | I3: 0 | J3: =I3/((G3+H3)/2) -> 0
A4: 資源循環研發中心 | D4: 4 | E4: 4 | F4: =D4-E4 -> 0 | G4: 4 | H4: =E4 -> 4 | I4: 0 | J4: =I4/((G4+H4)/2) -> 0
A5: 稽核室 | D5: 3 | E5: 4 | F5: =D5-E5 -> -1 | G5: 3 | H5: =E5 -> 4 | I5: 0 | J5: =I5/((G5+H5)/2) -> 0
A6: 副總 | D6: 1 | E6: 1 | F6: =D6-E6 -> 0 | G6: 1 | H6: =E6 -> 1 | I6: 0 | J6: =I6/((G6+H6)/2) -> 0
A7: 財務組 | E7: 3 | F7: =D7-E7 -> -3 | G7: 3 | H7: =E7 -> 3 | I7: 0 | J7: =I7/((G7+H7)/2) -> 0
A8: 會計組 | E8: 9 | F8: =D8-E8 -> -9 | G8: 9 | H8: =E8 -> 9 | I8: 1 | J8: =I8/((G8+H8)/2) -> 0.11111111
A9: 投資組 | E9: 3 | F9: =D9-E9 -> -3 | G9: 3 | H9: =E9 -> 3 | I9: 0 | J9: =I9/((G9+H9)/2) -> 0
A10: 策略管理處與行政暨物料管理組 | E10: 3 | F10: =D10-E10 -> -3 | G10: 3 | H10: =E10 -> 3 | I10: 0 | J10: =I10/((G10+H10)/2) -> 0
A11: 公關行銷組 | E11: 2 | F11: =D11-E11 -> -2 | G11: 2 | H11: =E11 -> 2 | I11: 0 | J11: =I11/((G11+H11)/2) -> 0
A12: 人資策略組 | E12: 5 | F12: =D12-E12 -> -5 | G12: 6 | H12: =E12 -> 5 | I12: 2 | J12: =I12/((G12+H12)/2) -> 0.36363636
A13: 法務環安組 | E13: 2 | F13: =D13-E13 -> -2 | G13: 2 | H13: =E13 -> 2 | I13: 0 | J13: =I13/((G13+H13)/2) -> 0
A14: 資訊策略組 | E14: 5 | F14: =D14-E14 -> -5 | G14: 5 | H14: =E14 -> 5 | I14: 0 | J14: =I14/((G14+H14)/2) -> 0
A15: 處主管 | E15: 1 | F15: =D15-E15 -> -1 | G15: 1 | H15: =E15 -> 1 | I15: 0 | J15: =I15/((G15+H15)/2) -> 0
A16: 行政室 | E16: 6 | F16: =D16-E16 -> -6 | G16: 6 | H16: =E16 -> 6 | I16: 0 | J16: =I16/((G16+H16)/2) -> 0
A17: 中區市場開發部 | E17: 3 | F17: =D17-E17 -> -3 | G17: 3 | H17: =E17 -> 3 | I17: 0 | J17: =I17/((G17+H17)/2) -> 0
A18: 中區-倉儲物流管理部 | B18: 主任 | E18: 1 | F18: =D18-E18 -> -1 | G18: 1 | H18: =E18 -> 1 | I18: 0 | J18: =I18/((G18+H18)/2) -> 0
B19: 副主任 | F19: =D19-E19 -> 0 | H19: =E19 -> 0 | I19: 0 | J19: 0
B20: 中部專案 | E20: 0 | F20: =D20-E20 -> 0 | H20: =E20 -> 0 | I20: 0 | J20: 0
C21: 中部倉儲管理 | E21: 11 | F21: =D21-E21 -> -11 | G21: 11 | H21: =E21 -> 11 | I21: 1 | J21: =I21/((G21+H21)/2) -> 0.090909091
C22: 中部資收 | E22: 6 | F22: =D22-E22 -> -6 | G22: 7 | H22: =E22 -> 6 | I22: 2 | J22: =I22/((G22+H22)/2) -> 0.30769231
B23: 文山專案 | C23: 文山專案 | E23: 22 | F23: =D23-E23 -> -22 | G23: 18 | H23: =E23 -> 22 | I23: 7 | J23: =I23/((G23+H23)/2) -> 0.35
C24: 人力仲介 | E24: 0 | F24: =D24-E24 -> 0 | G24: 0 | H24: =E24 -> 0 | I24: 0 | J24: 0
B25: 輔祥專案 | C25: 輔祥 | E25: 2 | F25: =D25-E25 -> -2 | G25: 2 | H25: =E25 -> 2 | I25: 0 | J25: =I25/((G25+H25)/2) -> 0
B26: 友達專案 | C26: 副主任 | E26: 2 | F26: =D26-E26 -> -2 | G26: 1 | H26: =E26 -> 2 | I26: 0 | J26: =I26/((G26+H26)/2) -> 0
C27: 友達-資收區(一、二期) | E27: 9 | F27: =D27-E27 -> -9 | G27: 9 | H27: =E27 -> 9 | I27: 0 | J27: =I27/((G27+H27)/2) -> 0
C28: 友達-資收區(三期) | E28: 8 | F28: =D28-E28 -> -8 | G28: 8 | H28: =E28 -> 8 | I28: 0 | J28: =I28/((G28+H28)/2) -> 0
C29: 友達-包材區 | E29: 12 | F29: =D29-E29 -> -12 | G29: 11 | H29: =E29 -> 12 | I29: 0 | J29: =I29/((G29+H29)/2) -> 0
C30: 友達-后里包材清潔區 | E30: 30 | F30: =D30-E30 -> -30 | G30: 32 | H30: =E30 -> 30 | I30: 2 | J30: =I30/((G30+H30)/2) -> 0.064516129
C31: 友達-后里包材清潔區(人力仲介) | E31: 5 | F31: =D31-E31 -> -5 | G31: 5 | H31: =E31 -> 5 | I31: 0 | J31: =I31/((G31+H31)/2) -> 0
C32: 友達-資收區(七星) | E32: 6 | F32: =D32-E32 -> -6 | G32: 6 | H32: =E32 -> 6 | I32: 0 | J32: =I32/((G32+H32)/2) -> 0
A33: 北區市場開發部 | E33: 2 | F33: =D33-E33 -> -2 | G33: 1 | H33: =E33 -> 2 | I33: 0 | J33: =I33/((G33+H33)/2) -> 0
A34: 北區-倉儲物流管理部 | B34: 北部資收 | C34: 蘆竹 | E34: 7 | F34: =D34-E34 -> -7 | G34: 10 | H34: =E34 -> 7 | I34: 4 | J34: =I34/((G34+H34)/2) -> 0.47058824
C35: 龍潭 | E35: 1 | F35: =D35-E35 -> -1 | G35: 4 | H35: =E35 -> 1 | I35: 3 | J35: =I35/((G35+H35)/2) -> 1.2
C36: 人力仲介 | E36: 0 | F36: =D36-E36 -> 0 | G36: 0 | H36: =E36 -> 0 | I36: 0 | J36: =I36/((G36+H36)/2) -> #DIV/0!
C37: 桃園 | E37: 1 | F37: =D37-E37 -> -1 | G37: 1 | H37: =E37 -> 1 | I37: 1 | J37: =I37/((G37+H37)/2) -> 1
A38: 南區市場開發部 | E38: 4 | F38: =D38-E38 -> -4 | G38: 3 | H38: =E38 -> 4 | I38: 1 | J38: =I38/((G38+H38)/2) -> 0.28571429
A39: 南區-倉儲物流管理部 | B39: 南部專案 | C39: 南科3m | E39: 33 | F39: =D39-E39 -> -33 | G39: 28 | H39: =E39 -> 33 | I39: 2 | J39: =I39/((G39+H39)/2) -> 0.06557377
C40: 中強 | E40: 1 | F40: =D40-E40 -> -1 | G40: 1 | H40: =E40 -> 1 | I40: 0 | J40: =I40/((G40+H40)/2) -> 0
C41: 聯電 | E41: 1 | F41: =D41-E41 -> -1 | G41: 1 | H41: =E41 -> 1 | I41: 0 | J41: =I41/((G41+H41)/2) -> 0
B42: 夢時代站 | C42: 夢時代統包 | E42: 5 | F42: =D42-E42 -> -5 | G42: 5 | H42: =E42 -> 5 | I42: 2 | J42: =I42/((G42+H42)/2) -> 0.4
B43: 高雄資收 | C43: 仁武倉庫 | E43: 4 | F43: =D43-E43 -> -4 | G43: 4 | H43: =E43 -> 4 | I43: 2 | J43: =I43/((G43+H43)/2) -> 0.5
A44: 營管處行政室&加盟室 | E44: 13 | F44: =D44-E44 -> -13 | G44: 10 | H44: =E44 -> 13 | I44: 1 | J44: =I44/((G44+H44)/2) -> 0.086956522
A45: 北區營運中心 | C45: 土城站 | E45: 7 | F45: =D45-E45 -> -7 | G45: 5 | H45: =E45 -> 7 | I45: 3 | J45: =I45/((G45+H45)/2) -> 0.5
C46: 桃園站 | E46: 8 | F46: =D46-E46 -> -8 | G46: 8 | H46: =E46 -> 8 | I46: 0 | J46: =I46/((G46+H46)/2) -> 0
C47: 新竹站 | E47: 6 | F47: =D47-E47 -> -6 | G47: 7 | H47: =E47 -> 6 | I47: 3 | J47: =I47/((G47+H47)/2) -> 0.46153846
A48: 中區營運中心 | C48: 彰興站 | E48: 15 | F48: =D48-E48 -> -15 | G48: 15 | H48: =E48 -> 15 | I48: 2 | J48: =I48/((G48+H48)/2) -> 0.13333333
C49: 草屯站 | E49: 6 | F49: =D49-E49 -> -6 | G49: 6 | H49: =E49 -> 6 | I49: 0 | J49: =I49/((G49+H49)/2) -> 0
C50: 神岡站 | E50: 7 | F50: =D50-E50 -> -7 | G50: 7 | H50: =E50 -> 7 | I50: 0 | J50: =I50/((G50+H50)/2) -> 0
C51: 金馬站 | E51: 4 | F51: =D51-E51 -> -4 | G51: 5 | H51: =E51 -> 4 | I51: 0 | J51: =I51/((G51+H51)/2) -> 0
C52: 和美站 | E52: 5 | F52: =D52-E52 -> -5 | G52: 5 | H52: =E52 -> 5 | I52: 0 | J52: =I52/((G52+H52)/2) -> 0
C53: 員林站 | E53: 11 | F53: =D53-E53 -> -11 | G53: 9 | H53: =E53 -> 11 | I53: 2 | J53: =I53/((G53+H53)/2) -> 0.2
C54: 員林三信站 | E54: 3 | F54: =D54-E54 -> -3 | G54: 0 | H54: =E54 -> 3 | I54: 2 | J54: =I54/((G54+H54)/2) -> 1.3333333
C55: 大明站 | E55: 2 | F55: =D55-E55 -> -2 | G55: 2 | H55: =E55 -> 2 | I55: 0 | J55: =I55/((G55+H55)/2) -> 0
C56: 大里站 | E56: 6 | F56: =D56-E56 -> -6 | G56: 8 | H56: =E56 -> 6 | I56: 0 | J56: =I56/((G56+H56)/2) -> 0
C57: 台中水湳站 | E57: 4 | F57: =D57-E57 -> -4 | G57: 0 | H57: =E57 -> 4 | I57: 0 | J57: =I57/((G57+H57)/2) -> 0
A58: 南區營運中心 | C58: 斗六保長站 | E58: 11 | F58: =D58-E58 -> -11 | G58: 11 | H58: =E58 -> 11 | I58: 0 | J58: =I58/((G58+H58)/2) -> 0
C59: 台南站 | E59: 7 | F59: =D59-E59 -> -7 | G59: 7 | H59: =E59 -> 7 | I59: 0 | J59: =I59/((G59+H59)/2) -> 0
A60: 國際事業處 | C60: 主管 | E60: 3 | F60: =D60-E60 -> -3 | H60: =E60 -> 3 | I60: 0 | J60: =I60/((G60+H60)/2) -> 0
C61: 行政室 | E61: 1 | F61: =D61-E61 -> -1 | H61: =E61 -> 1 | I61: 1 | J61: =I61/((G61+H61)/2) -> 2
C62: 銷售部 | E62: 2 | F62: =D62-E62 -> -2 | I62: 0 | J62: =I62/((G62+H62)/2) -> #DIV/0!
C63: 採購部 | E63: 1 | F63: =D63-E63 -> -1 | I63: 0 | J63: =I63/((G63+H63)/2) -> #DIV/0!
A64: 再生處理處 | C64: 行政室 | E64: 5 | F64: =D64-E64 -> -5 | H64: =E64 -> 5 | I64: 0 | J64: =I64/((G64+H64)/2) -> 0
C65: 研發中心 | E65: 4 | F65: =D65-E65 -> -4 | H65: =E65 -> 4 | I65: 0 | J65: =I65/((G65+H65)/2) -> 0
C66: 分選課 | E66: 20 | F66: =D66-E66 -> -20 | H66: =E66 -> 20 | I66: 2 | J66: =I66/((G66+H66)/2) -> 0.2
C67: 處理課 | E67: 17 | F67: =D67-E67 -> -17 | H67: =E67 -> 17 | I67: 1 | J67: =I67/((G67+H67)/2) -> 0.11764706
C68: 造粒課 | E68: 8 | F68: =D68-E68 -> -8 | H68: =E68 -> 8 | I68: 0 | J68: =I68/((G68+H68)/2) -> 0
C69: 喬翔分選課 | E69: 10 | F69: =D69-E69 -> -10 | H69: =E69 -> 10 | I69: 2 | J69: =I69/((G69+H69)/2) -> 0.4
A70: =#REF! -> #REF! | C70: 便利通店 | E70: 9 | F70: =D70-E70 -> -9 | H70: =E70 -> 9 | I70: 0 | J70: =I70/((G70+H70)/2) -> 0
E71: 420 | F71: =D71-E71 -> -420 | J71: =I71/((G71+H71)/2) -> #DIV/0!

Sheet 各站員工名單
A1: 各站單位人員 | D1: 各站單位人員 | J1: 主 管 | K1: 成員 | X1: 人數統計 | Y1: 單位加總
A2: 董事會 | D2: 董事會 | I2: 董事長 | J2: 林盟洲 | X2: =COUNTA(J2:W2) -> 1
I3: 副董事長 | J3: 洪勝裕 | X3: =COUNTA(J3:W3) -> 1 | Y3: =SUM(X2:X3) -> 2
A4: 總經理 | D4: 總經理室 | F4: 總經理室 | I4: 總經理 | J4: 林盟洲 | X4: =COUNTA(J4:W4) -> 1
I5: 顧問 | K5: 顏嘉賢 | X5: =COUNTA(K5:W5) -> 1
I6: 資深高級管理師 | K6: 林茹雯 | X6: =COUNTA(K6:W6) -> 1
I7: 管理師 | X7: =COUNTA(J7:W7) -> 0
I8: 實習生 | X8: =COUNTA(K8:W8) -> 0
I9: 儲備幹部(幹訓班) | X9: =COUNTA(J9:W9) -> 0 | Y9: =SUM(X4:X9) -> 3 | AA9: 總員編 | AB9: 4 | AE9: (原編3，增加顧問1名)
A10: 稽核室 | D10: 資源循環研發處 | F10: 主管 | I10: 經理 | J10: 李韶華 | X10: =COUNTA(J10:W10) -> 1 | Y10: 1 | Z10: 1
F11: 資源循環研發處 | I11: 主管(李韶華兼任) | X11: =COUNTA(J11:W11) -> 0
I12: 副管理師 | K12: 張福麟 | X12: =COUNTA(J12:W12) -> 1
I13: 實習生 | X13: =COUNTA(J13:W13) -> 0 | Y13: =SUM(X11:X13) -> 1 | Z13: 2
F14: 知識創新部 | I14: 襄理 | K14: 邱淑婷 | L14: 阮常新 | X14: =COUNTA(J14:W14) -> 2
I15: 資深高級管理師 | X15: =COUNTA(J15:W15) -> 0
I16: 高級管理師 | X16: =COUNTA(J16:W16) -> 0
I17: 事務員 | K17: 張雅涵 | X17: =COUNTA(J17:W17) -> 1 | Y17: =SUM(X14:X17) -> 3 | Z17: 3
F18: 研發部 | I18: 副理 | K18: 施承享 | X18: =COUNTA(J18:M18) -> 1
I19: 專員 | X19: =COUNTA(K19:W19) -> 0
I20: 高級管理師 | K20: 呂智偉 | X20: =COUNTA(K20:W20) -> 1
I21: 助理管理師 | K21: 曾炘宸 | X21: =COUNTA(K21:W21) -> 1 | Y21: =SUM(X18:X21) -> 3 | Z21: 3
F22: 環保顧問部 | I22: 高級管理師 | K22: 陳麗芳 | X22: =COUNTA(K22:W22) -> 1 | Y22: =SUM(X22:X23) -> 2
I23: 管理師 | K23: 陳信佳 | X23: =COUNTA(K23:W23) -> 1 | Y23: =Y22+Y21+Y17+Y13+Y10 -> 10 | Z23: 2 | AA23: 總員編 | AB23: 9
A24: 稽核室 | D24: 稽核室 | I24: 副理 | J24: 羅儷英 | X24: =COUNTA(J24:W24) -> 1
I25: 高級管理師 | X25: =COUNTA(J25:W25) -> 0
I26: 管理師 | X26: =COUNTA(J26:W26) -> 0
I27: 副管理師 | K27: 錢煥昇 | X27: =COUNTA(J27:W27) -> 1 | Y27: =SUM(X24:X27) -> 2 | AA27: 總員編 | AB27: 4
A28: 財務處 | C28: 副總經理 | D28: 財務部 | I28: 副理 | J28: 王雅祈 | X28: =COUNTA(J28:W28) -> 1 | Y28: =X28 -> 1 | Z28: 1
C29: 財務組 | F29: 財務課 | I29: 主任 | J29: 蔡佩君 | X29: =COUNTA(J29:W29) -> 1
I30: 主任 | X30: =COUNTA(J30:W30) -> 0
I31: 助理管理師 | X31: =COUNTA(J31:W31) -> 0
I32: 事務員 | K32: 吳宜蒨 | L32: 翁琳婷 | X32: =COUNTA(J32:W32) -> 2 | Y32: =SUM(X29:X32) -> 3 | Z32: 3
F33: 會計課 | I33: 主任 | J33: 莊宜陵 | X33: =COUNTA(J33:W33) -> 1
I34: 助理管理師 | K34: 吳佳純 | L34: 蕭秀玲 | M34: 黃意茗 | N34: 黃美萍 | O34: 劉靜文 | X34: =COUNTA(J34:W34) -> 5
I35: 事務員 | X35: =COUNTA(J35:W35) -> 0 | Y35: =SUM(X33:X35) -> 6 | Z35: 6
C36: 投資組 | F36: 投資課 | I36: 襄理 | X36: =COUNTA(J36:W36) -> 0
I37: 大陸投資 | K37: 巫志誠 | X37: =COUNTA(J37:W37) -> 1
I38: 專案經理 | X38: 0
I39: 助理管理師 | K39: 劉晏汝 | X39: =COUNTA(J39:W39) -> 1 | Y39: =SUM(X36:X39) -> 2 | Z39: 3
F40: 法務課 | I40: 高級管理師 | K40: 賴柏州 | X40: =COUNTA(J40:W40) -> 1 | Y40: =X40 -> 1 | Z40: 1
C41: 合計 | F41: 合計 | Y41: =Y40+Y39+Y35+Y32+Y28 -> 13 | AA41: 總員編 | AB41: 13
C42: 公關行銷組 | D42: 行銷部 | I42: 副理 | J42: 許家惠 | X42: =COUNTA(J42:W42) -> 1
I43: 管理師 | X43: =COUNTA(J43:W43) -> 0
F44: 數位行銷課 | I44: 主任 | J44: 陳澤洋 | X44: =COUNTA(J44:W44) -> 1
I45: 助理管理師 | K45: 張以均 | X45: =COUNTA(J45:W45) -> 1 | Y45: =SUM(X42:X45) -> 3 | AA45: 總員編 | AB45: 3
C46: 人資策略組 | D46: 人資部 | I46: 資深經理 | J46: 王靜美 | X46: =COUNTA(J46:W46) -> 1
I47: 清潔員 | X47: =COUNTA(J47:W47) -> 0
F48: 訓練暨薪酬課 | I48: 主任 | J48: 王婕誼 | X48: =COUNTA(J48:W48) -> 1
I49: 管理師 | K49: 卓怡伶 | X49: =COUNTA(J49:W49) -> 1
I50: 副管理師 | K50: 劉晏君 | X50: =COUNTA(J50:W50) -> 1
F51: 召募暨行政課 | I51: 主任 | J51: 洪榮宗 | X51: =COUNTA(J51:W51) -> 1
I52: 助理管理師 | K52: 謝佩伶 | L52: 鄧雅帆 | X52: =COUNTA(J52:W52) -> 2
I53: 清潔員 | K53: 蘇琬惠 | X53: =COUNTA(J53:W53) -> 1 | Y53: =SUM(X46:X53) -> 8 | AA53: 總員編 | AB53: 9
C54: 資訊策略組 | D54: 資訊部 | I54: 資深經理 | J54: 賴宏維 | X54: =COUNTA(J54:W54) -> 1
F55: 應用系統課 | I55: 主任 | K55: 郭保宏 | X55: =COUNTA(J55:W55) -> 1
I56: 資深及高級工程師 | K56: 游庭菊 | X56: =COUNTA(J56:W56) -> 1
I57: 高級工程師 | K57: 賴志信 | X57: =COUNTA(J57:W57) -> 1
I58: 副工程師 | K58: 許峻堯 | X58: =COUNTA(J58:W58) -> 1
F59: 網管課 | I59: 襄理 | K59: 劉邦鉦 | X59: =COUNTA(J59:W59) -> 1
I60: 高級工程師 | K60: 林逸平 | X60: =COUNTA(J60:W60) -> 1
I61: 事務員 | K61: 陳駿顥 | X61: =COUNTA(J61:W61) -> 1
F62: 專案管理課 | I62: 高級工程師 | K62: 廖欣怡 | X62: =COUNTA(J62:W62) -> 1 | Y62: =SUM(X54:X62) -> 9 | AA62: 總員編 | AB62: 9
B63: 行政室 | D63: 業務開發處 | E63: 處主管(行政一) | I63: 特助 | J63: 吳佩珊 | X63: =COUNTA(J63:W63) -> 1 | Y63: =SUM(X63) -> 1 | AA63: 總員編 | AB63: 1
E64: 行政課(行政二) | I64: 主任 | K64: 林衍如 | X64: =COUNTA(J64:W64) -> 1 | Y64: =SUM(X64) -> 1 | AA64: 總員編 | AB64: 1
E65: 電子商務部(行政一) | I65: 副管理師 | K65: 范惟彥 | X65: =COUNTA(J65:W65) -> 1
I66: 業務助理 | X66: =COUNTA(J66:W66) -> 0 | Y66: =SUM(X65:X66) -> 1 | AA66: 總員編 | AB66: 6
E67: 北區業務部 | F67: 北區業務課 | I67: 經理 | X67: =COUNTA(J67:W67) -> 0
I68: 專員 | X68: =COUNTA(J68:W68) -> 0 | Y68: =SUM(X67:X68) -> 0 | AA68: 總員編 | AB68: 1
F69: 北區物流作業課 | H69: 主管(費用京元電子) | I69: 主任 | J69: 李建葳 | X69: =COUNTA(J69:W69) -> 1 | Y69: =SUM(X69) -> 1 | AA69: 總員編 | AB69: 1
H70: 倉儲物流組 | I70: 專員 | X70: =COUNTA(J70:W70) -> 0
I71: 助管師(行政二) | K71: 魏淑婷 | X71: =COUNTA(J71:W71) -> 1 | Y71: =SUM(X70:X71) -> 1 | AA71: 總員編 | AB71: 0
H72: 業務-燿華電子 | I72: 主任 | J72: 張偉修 | X72: =COUNTA(J72:W72) -> 1
I73: 班長 | K73: 王鈞平 | X73: =COUNTA(J73:W73) -> 1
I74: 堆高機人員-宜蘭廠 | K74: 林炳宏 | X74: =COUNTA(J74:W74) -> 1
I75: 堆高機人員-土城廠 | K75: 周正忠 | L75: 胡家祥 | M75: 陳嘉漢 | X75: =COUNTA(J75:W75) -> 3
I76: 司機人員-土城廠 | K76: 王立翔 | X76: =COUNTA(J76:W76) -> 1 | Y76: =SUM(X72:X76) -> 7 | AA76: 總員編 | AB76: 7
H77: 京元電子 | I77: 主任 | X77: =COUNTA(J77:W77) -> 0
I78: 作業員 | K78: 李武憲 | L78: 吳魁 | X78: =COUNTA(J78:W78) -> 2 | Y78: =SUM(X77:X78) -> 2 | AA78: 總員編 | AB78: 1
E79: 中區業務部 | F79: 主管(費用業務-相如專案) | I79: 資深經理 | J79: 劉相如 | X79: =COUNTA(J79:W79) -> 1
F80: 中區業務課 | I80: 副管理師(業務-相如專案) | K80: 蔡佩娟 | L80: 王宣詠 | X80: =COUNTA(J80:W80) -> 2
I81: 助理管理師(業務-相如專案) | K81: 李美如 | X81: =COUNTA(J81:W81) -> 1
I82: 綜合服務專案 | K82: 朱巧妏 | X82: =COUNTA(J82:W82) -> 1
A83: 業務開發處 | B83: 經理 | I83: 業務-敏耀專案 | K83: 蘇敏耀 | X83: =COUNTA(J83:W83) -> 1
I84: 業務-献良專案 | K84: 張簡献良 | X84: =COUNTA(J84:W84) -> 1
I85: 廢棄物專案 | K85: 陳文欽 | X85: =COUNTA(J85:W85) -> 1 | Y85: =SUM(X79:X85) -> 8 | AA85: 總員編 | AB85: 4
F86: 中區物流作業一課 | G86: 主管(費用物流管理組) | J86: 周啟弘 | X86: =COUNTA(J86:W86) -> 1 | Y86: =SUM(X86) -> 1 | AA86: 總員編 | AB86: 1
G87: 物流管理組 | I87: 組長 | X87: =COUNTA(J87:W87) -> 0
I88: 壓縮車司機 | K88: 王博鋐 | L88: 李欣原 | M88: 秦洪政 | N88: 蔡承叡 | X88: =COUNTA(J88:W88) -> 4
I89: 35T 拖車司機 | K89: 葉震群 | L89: 恩波 | X89: =COUNTA(J89:W89) -> 2
I90: 26T大貨車 | K90: 邱明水 | X90: =COUNTA(J90:W90) -> 1
I91: 17T大貨車 | K91: 許國賓 | L91: 林倫揚 | M91: 陳品紘 | N91: 翁緯綸 | O91: 施政任 | X91: =COUNTA(J91:W91) -> 5
I92: 7.7T貨車 | K92: 楊財綜 | X92: =COUNTA(J92:W92) -> 1
I93: 7.4T司機 | X93: =COUNTA(J93:W93) -> 0
I94: 3.5噸司機 | X94: =COUNTA(J94:W94) -> 0
I95: 副管理師 | X95: =COUNTA(J95:W95) -> 0
I96: 助理管理師 | K96: 李朋鏸 | X96: =COUNTA(J96:W96) -> 1 | Y96: =SUM(X87:X96) -> 14 | AA96: 總員編 | AB96: 9
G97: 中部倉庫 | I97: 組長 | K97: 駱志明 | X97: =COUNTA(J97:W97) -> 1
I98: 作業員 | K98: 邱志強 | L98: 林慶華 | M98: 洪揚竣 | N98: 黃聖傑 | X98: =COUNTA(J98:W98) -> 4
I99: 堆高機作業員 | K99: 王偉萍 | X99: =COUNTA(J99:W99) -> 1 | Y99: =SUM(X97:X99) -> 6 | AA99: 總員編 | AB99: 9
F100: 中區物流作業二課 | G100: 主管(費用友達資收) | X100: =COUNTA(J100:W100) -> 0 | Y100: =SUM(X100) -> 0 | AA100: 總員編 | AB100: 1
...

Sheet 員工出勤日報表
A1: =TODAY() -> 46083
A2: 處/別 | B2: 室/站/專案 | F2: 員編
G3: 應到人數 | H3: 實到人數 | I3: 出勤率
A4: =各站員工名單!A2 -> 董事會 | B4: =A4 -> 董事會 | G4: =各站員工名單!Y3 -> 2 | H4: 2 | I4: =H4/G4 -> 1
A5: 總經理室 | B5: =A5 -> 總經理室 | G5: =各站員工名單!Y9 -> 3 | H5: 3 | I5: =H5/G5 -> 1
A6: 資源循環研發處 | B6: =A6 -> 資源循環研發處 | G6: =各站員工名單!Y10+各站員工名單!Y13 -> 2 | H6: 2 | I6: =H6/G6 -> 1
B7: 知識創新部 | G7: =各站員工名單!Y17 -> 3 | H7: 2 | I7: =H7/G7 -> 0.66666667 | J7: 出差1名(阮常新1200-1730)
B8: 研發部 | G8: =各站員工名單!Y21 -> 3 | H8: 3 | I8: =H8/G8 -> 1
B9: 環保顧問部 | G9: =各站員工名單!Y22 -> 2 | H9: 2 | I9: =H9/G9 -> 1
A10: 稽核室 | B10: =A10 -> 稽核室 | G10: =各站員工名單!Y27 -> 2 | H10: 2 | I10: =H10/G10 -> 1
A11: =各站員工名單!D28 -> 財務部 | B11: 副理 | G11: =各站員工名單!Y28 -> 1 | H11: 1 | I11: =H11/G11 -> 1
B12: 財務課 | G12: =各站員工名單!Y32 -> 3 | H12: 3 | I12: =H12/G12 -> 1
B13: 會計課 | G13: =各站員工名單!Y35 -> 6 | H13: 5 | I13: =H13/G13 -> 0.83333333 | J13: 特休1名(莊宜陵)
B14: 投資課 | G14: =各站員工名單!Y39 -> 2 | H14: 2 | I14: =H14/G14 -> 1
B15: 法務課 | G15: =各站員工名單!Y40 -> 1 | H15: 1 | I15: =H15/G15 -> 1 | J15: 事假1名(賴柏州1300-1730)
A16: =各站員工名單!D42 -> 行銷部 | B16: 行銷部 | G16: =各站員工名單!Y45 -> 3 | H16: 3 | I16: =H16/G16 -> 1 | J16: 特休1名(許家惠1330-1730)
A17: =各站員工名單!D46 -> 人資部 | B17: 人資部 | G17: =各站員工名單!Y53 -> 8 | H17: 8 | I17: =H17/G17 -> 1 | J17: 休假1名(卓怡伶1300-1730)
A18: =各站員工名單!D54 -> 資訊部 | B18: 資訊部 | G18: =各站員工名單!Y62 -> 9 | H18: 9 | I18: =H18/G18 -> 1
A19: 業務開發處 | B19: 處主管 | G19: =各站員工名單!Y63 -> 1 | H19: 1 | I19: =H19/G19 -> 1
B20: 業務處行政課 | G20: =各站員工名單!X64 -> 1 | H20: 1 | I20: =H20/G20 -> 1
B21: 電子商務部 | G21: =各站員工名單!Y66 -> 1 | H21: 1 | I21: =H21/G21 -> 1
B22: 北區業務部 | C22: 業務課 | G22: =各站員工名單!Y68 -> 0 | H22: 0 | I22: =H22/G22 -> #DIV/0!
C23: 物流作業課 | D23: 倉儲物流組 | G23: =各站員工名單!Y71 -> 1 | H23: 1 | I23: =H23/G23 -> 1
D24: 作業組 | E24: 業務-燿華電子 | G24: =各站員工名單!Y76 -> 7 | H24: 7 | I24: =H24/G24 -> 1
E25: 業務-京元電子 | G25: =各站員工名單!Y78 -> 2 | H25: 2 | I25: =H25/G25 -> 1
B26: 中區業務部 | C26: 業務課 | G26: =各站員工名單!Y85 -> 8 | H26: 8 | I26: 1
C27: 物流作業一課 | D27: 主管 | G27: =各站員工名單!Y86 -> 1 | H27: 1 | I27: =H27/G27 -> 1
D28: 倉儲物流組 | E28: 業務廢棄物專案 | G28: =各站員工名單!X85 -> 1 | H28: 1 | I28: =H28/G28 -> 1
E29: 物流管理組 | G29: =各站員工名單!Y96 -> 14 | H29: 14 | I29: =H29/G29 -> 1
D30: 作業組 | E30: 中部倉庫 | G30: =各站員工名單!Y99 -> 6 | H30: 6 | I30: =H30/G30 -> 1
C31: 物流作業二課 | D31: 主管 | G31: =各站員工名單!X100 -> 0 | H31: 0 | I31: =H31/G31 -> #DIV/0!
D32: 倉儲物流組 | G32: 0 | H32: 0 | I32: =H32/G32 -> #DIV/0!
D33: 作業組 | E33: 友達-七星 | G33: =各站員工名單!Y104 -> 7 | H33: 7 | I33: =H33/G33 -> 1
E34: 友達資收專案 | G34: =各站員工名單!Y112 -> 16 | H34: 16 | I34: =H34/G34 -> 1
E35: 友達包材 | G35: =各站員工名單!Y117 -> 9 | H35: 8 | I35: =H35/G35 -> 0.88888889 | J35: 病假1名(葉銘珠)
E36: 美光電子 | G36: =各站員工名單!Y119 -> 2 | H36: 2 | I36: =H36/G36 -> 1
C37: 物流作業三課 | D37: 主管 | G37: =各站員工名單!Y120 -> 1 | H37: 1 | I37: =H37/G37 -> 1
D38: 倉儲物流組 | G38: 0 | H38: 0 | I38: =H38/G38 -> #DIV/0!
D39: 作業組 | E39: 文山專案 | G39: =各站員工名單!Y130 -> 15 | H39: 15 | I39: =H39/G39 -> 1
B40: 南區業務部 | C40: 主管 | G40: =各站員工名單!Y131 -> 1 | H40: 1 | I40: =H40/G40 -> 1
C41: 業務課 | G41: =各站員工名單!Y131 -> 1 | H41: 1 | I41: =H41/G41 -> 1
C42: 物流作業課 | D42: 倉儲物流組 | E42: 南部物流管理組 | G42: =各站員工名單!Y138 -> 7 | H42: 7 | I42: =H42/G42 -> 1
D43: 作業組 | E43: 南部倉庫 | G43: =各站員工名單!Y142 -> 7 | H43: 6 | I43: =H43/G43 -> 0.85714286 | J43: 休假1名(邱光明)
E44: 中強 | G44: =各站員工名單!Y143 -> 1 | H44: 1 | I44: =H44/G44 -> 1
E45: 聯電 | G45: =各站員工名單!Y144 -> 1 | H45: 1 | I45: =H45/G45 -> 1
A46: 營運管理處 | B46: 處主管 | G46: =各站員工名單!Y155 -> 1 | H46: 1 | I46: =H46/G46 -> 1
B47: 行政課 | G47: =各站員工名單!Y148 -> 2 | H47: 2 | I47: =H47/G47 -> 1
B48: 電子商務部 | D48: 主管 | G48: =各站員工名單!Y149 -> 1 | H48: 1 | I48: =H48/G48 -> 1
D49: 家庭回收課 | G49: =各站員工名單!Y151 -> 1 | H49: 1 | I49: =H49/G49 -> 1
D50: 電商支援課 | G50: =各站員工名單!Y153 -> 1 | H50: 1 | I50: =H50/G50 -> 1
D51: 拆除工程課 | G51: =各站員工名單!Y155 -> 1 | H51: 1 | I51: =H51/G51 -> 1
D52: 便利通路課 | G52: =各站員工名單!Y157 -> 3 | H52: 1 | I52: =H52/G52 -> 0.33333333 | J52: 休假2名(賴蘇蘭、李姮萱)
B53: 營運部 | D53: 主管 | G53: =各站員工名單!Y158 -> 0 | H53: 0 | I53: =H53/G53 -> #DIV/0!
D54: 市場開發課 | G54: =各站員工名單!Y159 -> 1 | H54: 1 | I54: =H54/G54 -> 1
D55: 營運管理課 | E55: 彰興課 | G55: =各站員工名單!Y167 -> 13 | H55: 13 | I55: =H55/G55 -> 1
E56: 草屯課 | G56: =各站員工名單!Y172 -> 6 | H56: 6 | I56: =H56/G56 -> 1
E57: 神岡課 | G57: =各站員工名單!Y179 -> 8 | H57: 8 | I57: =H57/G57 -> 1
E58: 金馬組 | G58: =各站員工名單!Y185 -> 5 | H58: 5 | I58: =H58/G58 -> 1
E59: 和美組 | G59: =各站員工名單!Y190 -> 6 | H59: 6 | I59: =H59/G59 -> 1
E60: 員林課 | G60: =各站員工名單!Y199 -> 11 | H60: 11 | I60: =H60/G60 -> 1
E61: 員林三信組 | G61: =各站員工名單!Y205 -> 3 | H61: 3 | I61: =H61/G61 -> 1
E62: 大明組 | G62: =各站員工名單!Y210 -> 1 | H62: 1 | I62: =H62/G62 -> 1
E63: 斗六課 | G63: =各站員工名單!Y216 -> 10 | H63: 10 | I63: =H63/G63 -> 1
E64: 台南組 | G64: =各站員工名單!Y222 -> 7 | H64: 7 | I64: =H64/G64 -> 1
A65: =各站員工名單!D223 -> 新事業處 | B65: =各站員工名單!E223 -> 國際事業部 | G65: =各站員工名單!Y233 -> 3 | H65: 3 | I65: =H65/G65 -> 1
B66: =各站員工名單!E234 -> 機動車回收部 | D66: 主管 | G66: =各站員工名單!X234 -> 1 | H66: 1 | I66: =H66/G66 -> 1
D67: =各站員工名單!G235 -> 營運行銷課 | G67: =各站員工名單!X235+各站員工名單!X236 -> 2 | H67: 2 | I67: =H67/G67 -> 1
D68: 策略聯盟課 | G68: =各站員工名單!X241+各站員工名單!X242 -> 1 | H68: 0 | I68: =H68/G68 -> 0 | J68: 休假1名(楊豐瑋)
D69: 客服行銷課 | G69: =各站員工名單!X238+各站員工名單!X239 -> 4 | H69: 4 | I69: =H69/G69 -> 1
D70: 拆解觀光課 | G70: =各站員工名單!X240 -> 0 | H70: 0 | I70: =H70/G70 -> #DIV/0!
A71: 再生處理處 | B71: 再生處理處 | D71: 處主管 | G71: =各站員工名單!Y243 -> 1 | H71: 1 | I71: =H71/G71 -> 1
D72: 再生-行政室 | G72: =各站員工名單!Y245 -> 6 | H72: 6 | I72: =H72/G72 -> 1
D73: 處理二課 | G73: =各站員工名單!Y250 -> 13 | H73: 13 | I73: =H73/G73 -> 1
D74: 處理一課 | G74: =各站員工名單!Y259 -> 18 | H74: 17 | I74: =H74/G74 -> 0.94444444 | J74: 公傷假1名(梁玉美)
D75: 造粒課 | G75: =各站員工名單!Y263 -> 17 | H75: 14 | I75: =H75/G75 -> 0.82352941 | J75: 休假3名(彼查、阿日、萬多)
D76: 宏偉廠 | G76: =各站員工名單!Y269 -> 14 | H76: 14 | I76: =H76/G76 -> 1
A77: 綠遠公司 | B77: 綠遠公司 | D77: 執行長 | G77: =各站員工名單!X270 -> 1 | H77: 1 | I77: =H77/G77 -> 1
D78: 人資部 | G78: =各站員工名單!X271 -> 0 | H78: 0 | I78: =H78/G78 -> #DIV/0!
A79: 合計 | G79: =SUM(G5:G78) -> 321 | H79: =SUM(H5:H78) -> 310 | I79: =H79/G79 -> 0.96573209
M80: 製表者：Bella
G302: 特休1名(賴碧怜)

Sheet 業務開發處
C1: 日期 | D1: =員工出勤日報表!A1 -> 46083 | J1: 備註
C2: 成本中心 | D2: 職務 | E2: 員編 | F2: 實際人數 | G2: 缺額 | H2: 新進人員 | I2: 離職人員
C3: 業務行政費用一 | D3: 處主管 | E3: 1 | F3: =各站員工名單!X63 -> 1 | G3: =E3-F3 -> 0 | L3: 吳佩珊
D4: 合計 | E4: =SUM(E3) -> 1 | F4: =SUM(F3) -> 1 | G4: =E4-F4 -> 0
C5: 業務行政費用二 | D5: 主任 | E5: 1 | F5: =各站員工名單!X64 -> 1 | G5: =E5-F5 -> 0 | L5: 林衍如
D6: 副管理師 | E6: 2 | F6: =各站員工名單!X80 -> 2 | G6: =E6-F6 -> 0 | L6: 蔡佩娟 | M6: 王宣詠
D7: 助理管理師 | E7: 2 | F7: =各站員工名單!X71+各站員工名單!X81 -> 2 | G7: =E7-F7 -> 0 | L7: 魏淑婷 | M7: 李美如
D8: 合計 | E8: =SUM(E5:E7) -> 5 | F8: =SUM(F5:F7) -> 5 | G8: =E8-F8 -> 0
C9: 電子商務部 | D9: 副管理師 | E9: 1 | F9: =各站員工名單!X65 -> 1 | G9: =E9-F9 -> 0 | L9: 范惟彥
D10: 合計 | E10: =SUM(E26:E26) -> 1 | F10: =SUM(F9) -> 1 | G10: =E10-F10 -> 0
C11: 北區業務部 | D11: 經理 | E11: 1 | F11: =各站員工名單!X67 -> 0 | G11: =E11-F11 -> 1 | L11: 張煜欣
D12: 業務專員 | E12: 0 | F12: =各站員工名單!X68 -> 0 | G12: =E12-F12 -> 0
D13: 合計 | E13: =SUM(E11:E12) -> 1 | F13: =SUM(F11:F12) -> 0 | G13: =E13-F13 -> 1
C14: 北區物流作業課 | D14: 主任 | E14: 1 | F14: =各站員工名單!X69 -> 1 | G14: =E14-F14 -> 0 | L14: 李建葳
D15: 合計 | E15: =E14 -> 1 | F15: =F14 -> 1 | G15: =E15-F15 -> 0
C16: 業務-燿華電子 | D16: 主任 | E16: 1 | F16: =各站員工名單!X72 -> 1 | G16: =E16-F16 -> 0 | L16: 張偉修
D17: 班長 | E17: 1 | F17: =各站員工名單!X73 -> 1 | G17: =E17-F17 -> 0 | L17: 王鈞平
D18: 堆高機人員(宜蘭廠) | E18: 1 | F18: =各站員工名單!X74 -> 1 | G18: =E18-F18 -> 0 | L18: 林炳宏
D19: 堆高機人員(土城廠) | E19: 3 | F19: =各站員工名單!X75 -> 3 | G19: =E19-F19 -> 0 | L19: 周正忠 | M19: 胡家祥 | N19: 陳嘉漢
D20: 司機人員 | E20: 1 | F20: =各站員工名單!X76 -> 1 | G20: =E20-F20 -> 0 | L20: 王立翔
D21: 合計 | E21: =SUM(E16:E20) -> 7 | F21: =SUM(F16:F20) -> 7 | G21: =E21-F21 -> 0
C22: 京元電子 | D22: 主任 | E22: 1 | F22: =各站員工名單!X77 -> 0 | G22: =E22-F22 -> 1
D23: 作業員 | E23: 1 | F23: =各站員工名單!X78 -> 2 | G23: =E23-F23 -> -1 | L23: 李武憲
D24: 合計 | E24: =SUM(E22:E23) -> 2 | F24: =SUM(F22:F23) -> 2 | G24: =E24-F24 -> 0
C25: 中區業務課 | D25: 業務-相如專案 | E25: 1 | F25: =各站員工名單!X79 -> 1 | G25: =E25-F25 -> 0 | L25: 劉相如
D26: 業務-献良專案 | E26: 1 | F26: =各站員工名單!X84 -> 1 | G26: =E26-F26 -> 0 | L26: 張簡献良
D27: 業務-敏耀專案 | E27: 1 | F27: =各站員工名單!X83 -> 1 | G27: =E27-F27 -> 0 | L27: 蘇敏耀
D28: 綜合服務專案 | E28: 1 | F28: =各站員工名單!X82 -> 1 | G28: =E28-F28 -> 0 | L28: 朱巧妏
D29: 業務廢棄物專案 | E29: 1 | F29: =各站員工名單!X85 -> 1 | G29: =E29-F29 -> 0 | L29: 陳文欽
D30: 合計 | E30: =SUM(E25:E29) -> 5 | F30: =SUM(F25:F29) -> 5 | G30: =E30-F30 -> 0
C31: 中區物流作業一課 | D31: 主管 | E31: 1 | F31: =各站員工名單!X86 -> 1 | G31: =E31-F31 -> 0 | L31: 周啟弘
D32: 合計 | E32: =E31 -> 1 | F32: =F31 -> 1 | G32: =E32-F32 -> 0
C33: 物流管理組 | D33: 組長 | E33: 0 | F33: =各站員工名單!X87 -> 0 | G33: =E33-F33 -> 0
D34: 壓縮車司機 | E34: 3 | F34: =各站員工名單!X88 -> 4 | G34: =E34-F34 -> -1 | L34: 李欣原 | M34: 王博鋐
D35: 35T 拖車司機 | E35: 2 | F35: =各站員工名單!X89 -> 2 | G35: =E35-F35 -> 0 | L35: 恩波
D36: 26T大貨車 | E36: 1 | F36: =各站員工名單!X90 -> 1 | G36: =E36-F36 -> 0 | L36: 邱明水
D37: 17T車司機 | E37: 6 | F37: =各站員工名單!X91 -> 5 | G37: =E37-F37 -> 1 | L37: 許國賓 | M37: 林倫揚 | N37: 陳品紘 | O37: 梁國晉
D38: 7.7及7.4貨車 | E38: 2 | F38: =各站員工名單!X92+各站員工名單!X93 -> 1 | G38: =E38-F38 -> 1 | L38: 楊財綜
D39: 3.5噸司機 | E39: 0 | F39: =各站員工名單!X94 -> 0 | G39: =E39-F39 -> 0
D40: 副管理師 | E40: 1 | F40: =各站員工名單!X95 -> 0 | G40: =E40-F40 -> 1
D41: 助理管理師 | E41: 1 | F41: =各站員工名單!X96 -> 1 | G41: =E41-F41 -> 0 | L41: 李朋鏸
D42: 合計 | E42: =SUM(E33:E41) -> 16 | F42: =SUM(F33:F41) -> 14 | G42: =E42-F42 -> 2
C43: 中部倉庫 | D43: 作業員 | E43: 5 | F43: =各站員工名單!X98 -> 4 | G43: =E43-F43 -> 1 | L43: 邱志強 | M43: 林慶華
D44: 合計 | E44: =SUM(E43:E43) -> 5 | F44: =SUM(F43:F43) -> 4 | G44: =E44-F44 -> 1
C45: 業務-包材清潔 | D45: 主任 | E45: 1 | F45: =各站員工名單!#REF! -> #REF! | G45: =E45-F45 -> #REF!
D46: 組長 | E46: 1 | F46: =各站員工名單!#REF! -> #REF! | G46: =E46-F46 -> #REF!
D47: 班長 | E47: 2 | F47: =各站員工名單!#REF! -> #REF! | G47: =E47-F47 -> #REF! | L47: 張瑋鑫
D48: 堆高機人員 | E48: 2 | F48: =各站員工名單!#REF! -> #REF! | G48: =E48-F48 -> #REF! | L48: 羅震浩
D49: QC人員 | E49: 7 | F49: =各站員工名單!#REF! -> #REF! | G49: =E49-F49 -> #REF!
D50: 作業員-早班 | E50: 14 | F50: =各站員工名單!#REF!+各站員工名單!#REF! -> #REF! | G50: =E50-F50 -> #REF!
D51: 合計 | E51: =SUM(E45:E50) -> 27 | F51: =SUM(F45:F50) -> #REF! | G51: =E51-F51 -> #REF!
C52: 中區物流作業二課 | D52: 主管 | E52: 1 | F52: =各站員工名單!X100 -> 0 | G52: =E52-F52 -> 1 | L52: 王智鵬
D53: 合計 | E53: =E52 -> 1 | F53: =F52 -> 0 | G53: =E53-F53 -> 1
C54: 友達資收 專案 | D54: 主管 | E54: 1 | F54: =各站員工名單!X105 -> 0 | G54: =E54-F54 -> 1 | L54: 詹文仲
D55: 助理會計 | E55: 1 | F55: =各站員工名單!X106 -> 0 | G55: =E55-F55 -> 1 | L55: 劉思吟
D56: 班長 | E56: 1 | F56: =各站員工名單!X108 -> 1 | G56: =E56-F56 -> 0 | L56: 陳木柱
D57: 3.5噸司機 | E57: 1 | F57: =各站員工名單!X110 -> 0 | G57: =E57-F57 -> 1
D58: 堆高機人員 | E58: 2 | F58: =各站員工名單!X109 -> 3 | G58: =E58-F58 -> -1 | L58: 林金地 | M58: 陳金進
D59: 作業員 | E59: 10 | F59: =各站員工名單!X111+各站員工名單!X112 -> 12 | G59: =E59-F59 -> -2 | L59: 李苡丞 | M59: 梁綠 | N59: 吳金信 | O59: 許淑芬 | P59: 陳麗花 | Q59: 趙昆總 | R59: 簡瑞枝 | S59: 沈紅 | T59: 趙昭娟 | U59: 趙彩鑾 | V59: 黃瑩鶯 | W59: 鍾玲利 | X59: 孫維章
D60: 合計 | E60: =SUM(E54:E59) -> 16 | F60: =SUM(F54:F59) -> 16 | G60: =E60-F60 -> 0
C61: 友達包材 | D61: 主任 | E61: 0 | F61: =各站員工名單!X113 -> 0 | G61: =E61-F61 -> 0
D62: 3.5T司機 | E62: 1 | F62: =各站員工名單!X114 -> 2 | G62: =E62-F62 -> -1 | L62: 葉育憲
D63: 堆高機人員 | E63: 3 | F63: =各站員工名單!X115 -> 2 | G63: =E63-F63 -> 1 | L63: 翁文穎 | M63: 陳智鴻 | N63: 王仲和
D64: 作業員-早 | E64: 6 | F64: =各站員工名單!X116 -> 4 | G64: =E64-F64 -> 2 | L64: 林桂花 | M64: 林玉貴 | N64: 葉銘珠 | O64: 范翠姮 | P64: 李秀芬
D65: 作業員-夜 | E65: 1 | F65: =各站員工名單!X117 -> 1 | G65: =E65-F65 -> 0 | L65: 王淑燕
D66: 合計 | E66: =SUM(E61:E65) -> 11 | F66: =SUM(F61:F65) -> 9 | G66: =E66-F66 -> 2
C67: 友達七星 | D67: 主任 | E67: 0 | F67: =各站員工名單!X101 -> 0 | G67: =E67-F67 -> 0
D68: 班長 | E68: 1 | F68: =各站員工名單!X102 -> 1 | G68: =E68-F68 -> 0 | L68: 吳侯進
D69: 堆高機人員 | E69: 1 | F69: =各站員工名單!X103 -> 1 | G69: =E69-F69 -> 0 | L69: 李肇祥
D70: 作業員 | E70: 5 | F70: =各站員工名單!X104 -> 5 | G70: =E70-F70 -> 0 | L70: 阮氏金成 | M70: 林新惠 | N70: 黎玉婷 | O70: 張燕麟 | P70: 周文蘭 | Q70: 楊榮玉 | R70: 馮玉英
D71: 合計 | E71: =SUM(E67:E70) -> 7 | F71: =SUM(F67:F70) -> 7 | G71: =E71-F71 -> 0
C72: 業務-美光電子 | D72: 作業員 | E72: 1 | F72: 0 | G72: =E72-F72 -> 1
D73: 合計 | E73: =SUM(E72) -> 1 | F73: =SUM(F72) -> 0 | G73: =E73-F73 -> 1
C74: 中區物流作業三課 | D74: 主管 | E74: 1 | F74: =各站員工名單!X120 -> 1 | G74: =E74-F74 -> 0 | L74: 李志仁
D75: 合計 | E75: =E74 -> 1 | F75: =F74 -> 1 | G75: =E75-F75 -> 0
C76: 文山專案 | D76: 組長 | E76: 1 | F76: =各站員工名單!X121 -> 1 | G76: =E76-F76 -> 0 | L76: 王喻模
D77: 助理管理師 | E77: 0 | F77: =各站員工名單!X122 -> 0 | G77: =E77-F77 -> 0
D78: 堆高機人員-早 | E78: 2 | F78: =各站員工名單!X127 -> 2 | G78: =E78-F78 -> 0 | L78: 徐基銀 | M78: 吳世輝
D79: 堆高機人員-晚 | E79: 1 | F79: =各站員工名單!X128 -> 1 | G79: =E79-F79 -> 0 | L79: 廖本湧 | M79: 鄭台麟
D80: 作業員-早 | E80: 11 | F80: =各站員工名單!X125 -> 8 | G80: =E80-F80 -> 3 | L80: 林惠卿 | M80: 陳啟崙 | N80: 蔡孟彥 | O80: 徐麗嫦 | P80: 婁小苗 | Q80: 詹書軒 | R80: 温壽昌 | S80: 蘇宥瑋 | T80: 徐姝雯 | U80: 王露瑟
D81: 助理會計 | E81: 1 | F81: =各站員工名單!X123 -> 1 | G81: =E81-F81 -> 0 | L81: 郭曜瑋
D82: 計時-工讀生(晚班) | E82: 2 | F82: =各站員工名單!X124 -> 1 | G82: =E82-F82 -> 1 | L82: 張世緯 | M82: 陳亭㚬
D83: 合計 | E83: =SUM(E76:E82) -> 18 | F83: =SUM(F76:F82) -> 14 | G83: =E83-F83 -> 4
C84: 南區業務課 | D84: 主管 | E84: 1 | F84: =各站員工名單!X131 -> 1 | G84: =E84-F84 -> 0 | L84: 鍾侑宏
D85: 業務-南區專案二 | E85: 1 | F85: =各站員工名單!X133 -> 1 | G85: =E85-F85 -> 0 | L85: 黃子忠
D86: 合計 | E86: =SUM(E84:E85) -> 2 | F86: =SUM(F84:F85) -> 2 | G86: =E86-F86 -> 0
C87: 南部物流管理組 | D87: 主任 | E87: 1 | F87: =各站員工名單!X134 -> 1 | G87: =E87-F87 -> 0 | L87: 劉明修
D88: 夾子車司機 | E88: 3 | F88: =各站員工名單!X136 -> 3 | G88: =E88-F88 -> 0 | L88: 楊宗霖 | M88: 邱毅貴 | N88: 楊泰輝
D89: 3.5噸司機 | E89: 2 | F89: =各站員工名單!X138 -> 2 | G89: =E89-F89 -> 0 | L89: 邱啟賓 | M89: 戴文祥
D90: 合計 | E90: =SUM(E87:E89) -> 6 | F90: =SUM(F87:F89) -> 6 | G90: =E90-F90 -> 0
C91: 南部倉庫 | D91: 主任 | E91: 1 | F91: =各站員工名單!X139 -> 0 | G91: =E91-F91 -> 1
D92: 助理會計 | E92: 1 | F92: =各站員工名單!X141 -> 1 | G92: =E92-F92 -> 0 | L92: 林佩鈺
D93: 作業員 | E93: 5 | F93: =各站員工名單!X142 -> 6 | G93: =E93-F93 -> -1 | L93: 劉俊宏 | M93: 邱光明 | N93: 詹萬郡 | O93: 陳文福 | P93: 蘇春安 | Q93: 張寶原
D94: 合計 | E94: =SUM(E91:E93) -> 7 | F94: =SUM(F91:F93) -> 7 | G94: =E94-F94 -> 0
C95: 中強專案 | D95: 作業員 | E95: 2 | F95: =各站員工名單!X143 -> 1 | G95: =E95-F95 -> 1 | L95: 黃明輝
D96: 合計 | E96: =SUM(E95) -> 2 | F96: =SUM(F95) -> 1 | G96: =E96-F96 -> 1
C97: 聯電 | D97: 作業員 | E97: 1 | F97: =各站員工名單!X144 -> 1 | G97: =E97-F97 -> 0 | L97: 邱旭廷
D98: 合計 | E98: =SUM(E97) -> 1 | F98: =SUM(F97) -> 1 | G98: =E98-F98 -> 0
C99: 業務開發處總計 | E99: =E4+E8+E10+E30+E32+E71+E21+E24+E51+E73+E75+E42+E44+E60+E66+E83+E86+E94+E96+E98+E90+E13+E15+E53 -> 145 | F99: =F4+F8+F10+F30+F32+F71+F21+F24+F73+F75+F42+F44+F60+F66+F83+F86+F94+F96+F98+F90+F13+F15+F51+F53 -> #REF! | G99: =G4+G8+G10+G30+G31+G71+G21+G24+G51+G74+G75+G42+G44+G60+G66+G83+G84+G94+G96+G98+G90 -> #REF! | H99: =SUM(H3:H96) -> 0 | I99: =SUM(I3:I96) -> 0

Sheet 資料
G1: 到職 | I1: 離職
A2: 通知日 | B2: 事業處 | C2: 部門 | D2: 職位(務) | E2: 工號 | F2: 姓名 | G2: 年份 | H2: 月份 | I2: 年份 | J2: 月份 | K2: 到職日 | L2: 離職日 | M2: 在職天數 | O2: 未滿90天
A3: 41244 | B3: 業務開發處 | C3: 文山專案 | D3: 作業員 | E3: 無 | F3: 高振駸 | G3: =IF(K3="",0,YEAR(K3)) -> 2012 | H3: =IF(K3="",0,MONTH(K3)) -> 12 | I3: =IF(L3="",0,YEAR(K3)) -> 2012 | J3: =IF(L3="",0,MONTH(L3)) -> 12 | K3: 41244 | L3: 41244 | M3: =IF(L3="",0,L3-K3+1) -> 1 | O3: =IF(M3<91,"V","") -> V
B4: 營運管理處 | C4: 營運管理處 | D4: 儲備幹部 | E4: 02204 | F4: 廖柏鈞 | G4: =IF(K4="",0,YEAR(K4)) -> 2012 | H4: =IF(K4="",0,MONTH(K4)) -> 12 | I4: =IF(L4="",0,YEAR(K4)) -> 0 | J4: =IF(L4="",0,MONTH(L4)) -> 0 | K4: 41246 | M4: =IF(L4="",0,L4-K4+1) -> 0 | O4: =IF(M4<91,"V","") -> V
B5: 再生處理處 | C5: 喬翔分選課 | D5: 計時作業員 | F5: 廖玉梅 | G5: =IF(K5="",0,YEAR(K5)) -> 2012 | H5: =IF(K5="",0,MONTH(K5)) -> 12 | I5: =IF(L5="",0,YEAR(K5)) -> 0 | J5: =IF(L5="",0,MONTH(L5)) -> 0 | K5: 41250 | M5: =IF(L5="",0,L5-K5+1) -> 0 | O5: =IF(M5<91,"V","") -> V
A6: 41244 | B6: 業務開發處 | C6: 文山專案 | D6: 作業員 | E6: 無 | F6: 江志隆 | G6: =IF(K6="",0,YEAR(K6)) -> 2012 | H6: =IF(K6="",0,MONTH(K6)) -> 12 | I6: =IF(L6="",0,YEAR(K6)) -> 2012 | J6: =IF(L6="",0,MONTH(L6)) -> 12 | K6: 41254 | L6: 41254 | M6: =IF(L6="",0,L6-K6+1) -> 1 | O6: =IF(M6<91,"V","") -> V
B7: 業務開發處 | C7: 友達-資收區(七星) | D7: 作業員 | E7: 01880 | F7: 周氏善 | G7: =IF(K7="",0,YEAR(K7)) -> 2011 | H7: =IF(K7="",0,MONTH(K7)) -> 9 | I7: =IF(L7="",0,YEAR(K7)) -> 2011 | J7: =IF(L7="",0,MONTH(L7)) -> 12 | K7: 40787 | L7: 41244 | M7: =IF(L7="",0,L7-K7+1) -> 458 | O7: =IF(M7<91,"V","")
B8: 業務開發處 | C8: 友達-后里包材清潔區 | D8: 作業員 | E8: 02008 | F8: 邵紫廷 | G8: =IF(K8="",0,YEAR(K8)) -> 2012 | H8: =IF(K8="",0,MONTH(K8)) -> 3 | I8: =IF(L8="",0,YEAR(K8)) -> 2012 | J8: =IF(L8="",0,MONTH(L8)) -> 12 | K8: 40969 | L8: 41253 | M8: =IF(L8="",0,L8-K8+1) -> 285 | O8: =IF(M8<91,"V","")
B9: 再生處理處 | C9: 處理課 | D9: 外場人員 | E9: 01598 | F9: 李元夆 | G9: =IF(K9="",0,YEAR(K9)) -> 2010 | H9: =IF(K9="",0,MONTH(K9)) -> 7 | I9: =IF(L9="",0,YEAR(K9)) -> 2010 | J9: =IF(L9="",0,MONTH(L9)) -> 12 | K9: 40364 | L9: 41251 | M9: =IF(L9="",0,L9-K9+1) -> 888 | O9: =IF(M9<91,"V","")
B10: 再生處理處 | C10: 分選課 | D10: 外勞 | E10: 01676 | F10: 查那猜 | G10: =IF(K10="",0,YEAR(K10)) -> 2010 | H10: =IF(K10="",0,MONTH(K10)) -> 9 | I10: =IF(L10="",0,YEAR(K10)) -> 2010 | J10: =IF(L10="",0,MONTH(L10)) -> 12 | K10: 40449 | L10: 41253 | M10: =IF(L10="",0,L10-K10+1) -> 805 | O10: =IF(M10<91,"V","")
A11: 40909 | B11: 營運管理處 | C11: 新竹站 | D11: 外場人員 | E11: 02189 | F11: 潘青宏 | G11: =IF(K11="",0,YEAR(K11)) -> 2012 | H11: =IF(K11="",0,MONTH(K11)) -> 10 | I11: =IF(L11="",0,YEAR(K11)) -> 2012 | J11: =IF(L11="",0,MONTH(L11)) -> 1 | K11: 41193 | L11: 41277 | M11: =IF(L11="",0,L11-K11+1) -> 85 | O11: =IF(M11<91,"V","") -> V
B12: 策略管理處 | C12: 人資策略組 | D12: 工讀生 | E12: 02195 | F12: 蘇若綺 | G12: =IF(K12="",0,YEAR(K12)) -> 2012 | H12: =IF(K12="",0,MONTH(K12)) -> 11 | I12: =IF(L12="",0,YEAR(K12)) -> 2012 | J12: =IF(L12="",0,MONTH(L12)) -> 1 | K12: 41214 | L12: 41276 | M12: =IF(L12="",0,L12-K12+1) -> 63 | O12: =IF(M12<91,"V","") -> V
B13: 營運管理處 | C13: 員林新站 | D13: 外場人員 | E13: X | F13: 陳志佳 | G13: =IF(K13="",0,YEAR(K13)) -> 2012 | H13: =IF(K13="",0,MONTH(K13)) -> 1 | I13: =IF(L13="",0,YEAR(K13)) -> 2012 | J13: =IF(L13="",0,MONTH(L13)) -> 1 | K13: 40912 | L13: 40912 | M13: =IF(L13="",0,L13-K13+1) -> 1 | O13: =IF(M13<91,"V","") -> V
B14: 業務開發處 | C14: 文山專案 | D14: 作業員 | E14: 02054 | F14: 溫壽昌 | G14: =IF(K14="",0,YEAR(K14)) -> 2011 | H14: =IF(K14="",0,MONTH(K14)) -> 3 | I14: =IF(L14="",0,YEAR(K14)) -> 2011 | J14: =IF(L14="",0,MONTH(L14)) -> 1 | K14: 40609 | L14: 41281 | M14: =IF(L14="",0,L14-K14+1) -> 673 | O14: =IF(M14<91,"V","")
B15: 業務開發處 | C15: 夢時代統包 | D15: 外場人員 | E15: 02197 | F15: 鍾宏儒 | G15: =IF(K15="",0,YEAR(K15)) -> 2012 | H15: =IF(K15="",0,MONTH(K15)) -> 11 | I15: =IF(L15="",0,YEAR(K15)) -> 2012 | J15: =IF(L15="",0,MONTH(L15)) -> 1 | K15: 41215 | L15: 41284 | M15: =IF(L15="",0,L15-K15+1) -> 70 | O15: =IF(M15<91,"V","") -> V
B16: 國際事業處 | C16: 國際事業處 | D16: 副理 | E16: 00062 | F16: 宋祈全 | G16: =IF(K16="",0,YEAR(K16)) -> 2004 | H16: =IF(K16="",0,MONTH(K16)) -> 8 | I16: =IF(L16="",0,YEAR(K16)) -> 2004 | J16: =IF(L16="",0,MONTH(L16)) -> 1 | K16: 38222 | L16: 41295 | M16: =IF(L16="",0,L16-K16+1) -> 3074 | O16: =IF(M16<91,"V","")
B17: 營運管理處 | C17: 彰興站 | D17: 夾子車司機 | E17: 02199 | F17: 蔡渙凱 | G17: =IF(K17="",0,YEAR(K17)) -> 2012 | H17: =IF(K17="",0,MONTH(K17)) -> 11 | I17: =IF(L17="",0,YEAR(K17)) -> 2012 | J17: =IF(L17="",0,MONTH(L17)) -> 1 | K17: 41234 | L17: 41297 | M17: =IF(L17="",0,L17-K17+1) -> 64 | O17: =IF(M17<91,"V","") -> V
B18: 業務開發處 | C18: 文山專案 | D18: 短期作業員 | E18: X | F18: 梁云佳 | G18: =IF(K18="",0,YEAR(K18)) -> 2013 | H18: =IF(K18="",0,MONTH(K18)) -> 1 | I18: =IF(L18="",0,YEAR(K18)) -> 2013 | J18: =IF(L18="",0,MONTH(L18)) -> 1 | K18: 41298 | L18: 41298 | M18: =IF(L18="",0,L18-K18+1) -> 1 | O18: =IF(M18<91,"V","") -> V
B19: 業務開發處 | C19: 文山專案 | D19: 作業員 | E19: 02228 | F19: 武祥麟 | G19: =IF(K19="",0,YEAR(K19)) -> 2013 | H19: =IF(K19="",0,MONTH(K19)) -> 1 | I19: =IF(L19="",0,YEAR(K19)) -> 2013 | J19: =IF(L19="",0,MONTH(L19)) -> 1 | K19: 41299 | L19: 41302 | M19: =IF(L19="",0,L19-K19+1) -> 4 | O19: =IF(M19<91,"V","") -> V
B20: 營運管理處 | C20: 員林三信站 | D20: 外場人員 | E20: X | F20: 黃偉銘 | G20: =IF(K20="",0,YEAR(K20)) -> 2013 | H20: =IF(K20="",0,MONTH(K20)) -> 1 | I20: =IF(L20="",0,YEAR(K20)) -> 2013 | J20: =IF(L20="",0,MONTH(L20)) -> 1 | K20: 41302 | L20: 41302 | M20: =IF(L20="",0,L20-K20+1) -> 1 | O20: =IF(M20<91,"V","") -> V
B21: 業務開發處 | C21: 文山專案 | D21: 短期作業員 | E21: 02227 | F21: 白雨晨 | G21: =IF(K21="",0,YEAR(K21)) -> 2013 | H21: =IF(K21="",0,MONTH(K21)) -> 1 | I21: =IF(L21="",0,YEAR(K21)) -> 2013 | J21: =IF(L21="",0,MONTH(L21)) -> 1 | K21: 41298 | L21: 41305 | M21: =IF(L21="",0,L21-K21+1) -> 8 | O21: =IF(M21<91,"V","") -> V
B22: 營運管理處 | C22: 新竹站 | D22: 外場人員 | F22: 黃守仁 | G22: =IF(K22="",0,YEAR(K22)) -> 2012 | H22: =IF(K22="",0,MONTH(K22)) -> 8 | I22: =IF(L22="",0,YEAR(K22)) -> 2012 | J22: =IF(L22="",0,MONTH(L22)) -> 2 | K22: 41122 | L22: 41306 | M22: =IF(L22="",0,L22-K22+1) -> 185 | O22: =IF(M22<91,"V","")
B23: 業務開發處 | C23: 文山專案 | D23: 堆高機 | E23: 02211 | F23: 陳盈昌 | G23: =IF(K23="",0,YEAR(K23)) -> 2012 | H23: =IF(K23="",0,MONTH(K23)) -> 12 | I23: =IF(L23="",0,YEAR(K23)) -> 2012 | J23: =IF(L23="",0,MONTH(L23)) -> 2 | K23: 41270 | L23: 41311 | M23: =IF(L23="",0,L23-K23+1) -> 42 | O23: =IF(M23<91,"V","") -> V
B24: 營運管理處 | C24: 土城站 | D24: 外場人員 | F24: 邱子豪 | G24: =IF(K24="",0,YEAR(K24)) -> 2010 | H24: =IF(K24="",0,MONTH(K24)) -> 10 | I24: =IF(L24="",0,YEAR(K24)) -> 2010 | J24: =IF(L24="",0,MONTH(L24)) -> 2 | K24: 40458 | L24: 41320 | M24: =IF(L24="",0,L24-K24+1) -> 863 | O24: =IF(M24<91,"V","")
B25: 業務開發處 | C25: 夢時代統包 | D25: 外場人員 | F25: 吳秉達 | G25: =IF(K25="",0,YEAR(K25)) -> 2013 | H25: =IF(K25="",0,MONTH(K25)) -> 1 | I25: =IF(L25="",0,YEAR(K25)) -> 2013 | J25: =IF(L25="",0,MONTH(L25)) -> 2 | K25: 41285 | L25: 41313 | M25: =IF(L25="",0,L25-K25+1) -> 29 | O25: =IF(M25<91,"V","") -> V
B26: 營運管理處 | C26: 新竹站 | D26: 3/5T司機 | E26: X | F26: 薛建誠 | G26: =IF(K26="",0,YEAR(K26)) -> 2013 | H26: =IF(K26="",0,MONTH(K26)) -> 2 | I26: =IF(L26="",0,YEAR(K26)) -> 2013 | J26: =IF(L26="",0,MONTH(L26)) -> 2 | K26: 41323 | L26: 41323 | M26: =IF(L26="",0,L26-K26+1) -> 1 | O26: =IF(M26<91,"V","") -> V
B27: 業務開發處 | C27: 明基北部專案(龍潭) | D27: 外場人員 | F27: 徐清富 | G27: =IF(K27="",0,YEAR(K27)) -> 2012 | H27: =IF(K27="",0,MONTH(K27)) -> 7 | I27: =IF(L27="",0,YEAR(K27)) -> 2012 | J27: =IF(L27="",0,MONTH(L27)) -> 2 | K27: 41106 | L27: 41320 | M27: =IF(L27="",0,L27-K27+1) -> 215 | O27: =IF(M27<91,"V","")
B28: 業務開發處 | C28: 明基北部專案(龍潭) | D28: 外場人員 | F28: 張文山 | G28: =IF(K28="",0,YEAR(K28)) -> 2012 | H28: =IF(K28="",0,MONTH(K28)) -> 7 | I28: =IF(L28="",0,YEAR(K28)) -> 2012 | J28: =IF(L28="",0,MONTH(L28)) -> 2 | K28: 41107 | L28: 41320 | M28: =IF(L28="",0,L28-K28+1) -> 214 | O28: =IF(M28<91,"V","")
B29: 業務開發處 | C29: 文山專案 | D29: 晚班堆高機 | E29: 02157 | F29: 巫信融 | G29: =IF(K29="",0,YEAR(K29)) -> 2012 | H29: =IF(K29="",0,MONTH(K29)) -> 8 | I29: =IF(L29="",0,YEAR(K29)) -> 2012 | J29: =IF(L29="",0,MONTH(L29)) -> 2 | K29: 41122 | L29: 41325 | M29: =IF(L29="",0,L29-K29+1) -> 204 | O29: =IF(M29<91,"V","")
B30: 業務開發處 | C30: 中部資收 | D30: 外場人員 | F30: 許明河 | G30: =IF(K30="",0,YEAR(K30)) -> 2012 | H30: =IF(K30="",0,MONTH(K30)) -> 2 | I30: =IF(L30="",0,YEAR(K30)) -> 2012 | J30: =IF(L30="",0,MONTH(L30)) -> 2 | K30: 40940 | L30: 41327 | M30: =IF(L30="",0,L30-K30+1) -> 388 | O30: =IF(M30<91,"V","")
B31: 業務開發處 | C31: 安定倉庫 | D31: 助理會計 | E31: 02232 | F31: 鄭怡婷 | G31: =IF(K31="",0,YEAR(K31)) -> 2013 | H31: =IF(K31="",0,MONTH(K31)) -> 2 | I31: =IF(L31="",0,YEAR(K31)) -> 2013 | J31: =IF(L31="",0,MONTH(L31)) -> 2 | K31: 41323 | L31: 41327 | M31: =IF(L31="",0,L31-K31+1) -> 5 | O31: =IF(M31<91,"V","") -> V
B32: 業務開發處 | C32: 明基北部(龍潭) | D32: 外場人員 | F32: 朱逸仙 | G32: =IF(K32="",0,YEAR(K32)) -> 2012 | H32: =IF(K32="",0,MONTH(K32)) -> 7 | I32: =IF(L32="",0,YEAR(K32)) -> 2012 | J32: =IF(L32="",0,MONTH(L32)) -> 2 | K32: 41114 | L32: 41328 | M32: =IF(L32="",0,L32-K32+1) -> 215 | O32: =IF(M32<91,"V","")
B33: 業務開發處 | C33: 友達-后里包材清潔區 | D33: 助理會計 | F33: 吳采融 | G33: =IF(K33="",0,YEAR(K33)) -> 2011 | H33: =IF(K33="",0,MONTH(K33)) -> 1 | I33: =IF(L33="",0,YEAR(K33)) -> 2011 | J33: =IF(L33="",0,MONTH(L33)) -> 2 | K33: 40561 | L33: 41330 | M33: =IF(L33="",0,L33-K33+1) -> 770 | O33: =IF(M33<91,"V","")
B34: 業務開發處 | C34: 中部倉庫 | D34: 作業員 | F34: 黃永騰 | G34: =IF(K34="",0,YEAR(K34)) -> 2013 | H34: =IF(K34="",0,MONTH(K34)) -> 2 | I34: =IF(L34="",0,YEAR(K34)) -> 2013 | J34: =IF(L34="",0,MONTH(L34)) -> 2 | K34: 41327 | L34: 41328 | M34: =IF(L34="",0,L34-K34+1) -> 2 | O34: =IF(M34<91,"V","") -> V
B35: 業務開發處 | C35: 高雄仁武倉庫 | D35: 外場人員 | E35: 02084 | F35: 林欣宏 | G35: =IF(K35="",0,YEAR(K35)) -> 2012 | H35: =IF(K35="",0,MONTH(K35)) -> 5 | I35: =IF(L35="",0,YEAR(K35)) -> 2012 | J35: =IF(L35="",0,MONTH(L35)) -> 2 | K35: 41045 | L35: 41333 | M35: =IF(L35="",0,L35-K35+1) -> 289 | O35: =IF(M35<91,"V","")
B36: 國際事業處 | C36: 國際事業處 | D36: 副課長 | E36: 01313 | F36: 賴娜慧 | G36: =IF(K36="",0,YEAR(K36)) -> 2009 | H36: =IF(K36="",0,MONTH(K36)) -> 8 | I36: =IF(L36="",0,YEAR(K36)) -> 2009 | J36: =IF(L36="",0,MONTH(L36)) -> 2 | K36: 40028 | L36: 41333 | M36: =IF(L36="",0,L36-K36+1) -> 1306 | O36: =IF(M36<91,"V","")
B37: 再生處理處 | C37: 喬翔分選 | D37: 作業員 | E37: 01846 | F37: 鄭秀蘭 | G37: =IF(K37="",0,YEAR(K37)) -> 2011 | H37: =IF(K37="",0,MONTH(K37)) -> 7 | I37: =IF(L37="",0,YEAR(K37)) -> 2011 | J37: =IF(L37="",0,MONTH(L37)) -> 2 | K37: 40730 | L37: 41333 | M37: =IF(L37="",0,L37-K37+1) -> 604 | O37: =IF(M37<91,"V","")
B38: 再生處理處 | C38: 全興處理課 | D38: 外場人員 | E38: 01419 | F38: 李建盛 | G38: =IF(K38="",0,YEAR(K38)) -> 2009 | H38: =IF(K38="",0,MONTH(K38)) -> 12 | I38: =IF(L38="",0,YEAR(K38)) -> 2009 | J38: =IF(L38="",0,MONTH(L38)) -> 2 | K38: 40164 | L38: 41333 | M38: =IF(L38="",0,L38-K38+1) -> 1170 | O38: =IF(M38<91,"V","")
B39: 再生處理處 | C39: 全興分選課 | D39: 作業員 | E39: 02166 | F39: 替瓦 | G39: =IF(K39="",0,YEAR(K39)) -> 2012 | H39: =IF(K39="",0,MONTH(K39)) -> 8 | I39: =IF(L39="",0,YEAR(K39)) -> 2012 | J39: =IF(L39="",0,MONTH(L39)) -> 2 | K39: 41144 | L39: 41333 | M39: =IF(L39="",0,L39-K39+1) -> 190 | O39: =IF(M39<91,"V","")
B40: 業務開發處 | C40: 安定倉庫 | D40: 助理會計 | F40: 郭怡婷 | G40: =IF(K40="",0,YEAR(K40)) -> 2010 | H40: =IF(K40="",0,MONTH(K40)) -> 3 | I40: =IF(L40="",0,YEAR(K40)) -> 2010 | J40: =IF(L40="",0,MONTH(L40)) -> 2 | K40: 40264 | L40: 41315 | M40: =IF(L40="",0,L40-K40+1) -> 1052 | O40: =IF(M40<91,"V","")
B41: 營運管理處 | C41: 員林站 | D41: 平板車司機 | E41: X | F41: 蔡政利 | G41: =IF(K41="",0,YEAR(K41)) -> 2013 | H41: =IF(K41="",0,MONTH(K41)) -> 3 | I41: =IF(L41="",0,YEAR(K41)) -> 2013 | J41: =IF(L41="",0,MONTH(L41)) -> 3 | K41: 41334 | L41: 41334 | M41: =IF(L41="",0,L41-K41+1) -> 1 | O41: =IF(M41<91,"V","") -> V
B42: 業務開發處 | C42: 明基北部(蘆竹) | D42: 外場人員 | F42: 陳愛玲 | G42: =IF(K42="",0,YEAR(K42)) -> 2012 | H42: =IF(K42="",0,MONTH(K42)) -> 3 | I42: =IF(L42="",0,YEAR(K42)) -> 2012 | J42: =IF(L42="",0,MONTH(L42)) -> 3 | K42: 40994 | L42: 41335 | M42: =IF(L42="",0,L42-K42+1) -> 342 | O42: =IF(M42<91,"V","")
B43: 業務開發處 | C43: 明基北部(蘆竹) | D43: 外場人員 | F43: 藍瓈鳳 | G43: =IF(K43="",0,YEAR(K43)) -> 2012 | H43: =IF(K43="",0,MONTH(K43)) -> 3 | I43: =IF(L43="",0,YEAR(K43)) -> 2012 | J43: =IF(L43="",0,MONTH(L43)) -> 3 | K43: 40994 | L43: 41335 | M43: =IF(L43="",0,L43-K43+1) -> 342 | O43: =IF(M43<91,"V","")
B44: 業務開發處 | C44: 明基北部(蘆竹) | D44: 外場人員 | F44: 林泓文 | G44: =IF(K44="",0,YEAR(K44)) -> 2012 | H44: =IF(K44="",0,MONTH(K44)) -> 3 | I44: =IF(L44="",0,YEAR(K44)) -> 2012 | J44: =IF(L44="",0,MONTH(L44)) -> 3 | K44: 40996 | L44: 41335 | M44: =IF(L44="",0,L44-K44+1) -> 340 | O44: =IF(M44<91,"V","")
B45: 營運管理處 | C45: 員林三信站 | D45: 3/5T司機 | F45: 曹志豪 | G45: =IF(K45="",0,YEAR(K45)) -> 2013 | H45: =IF(K45="",0,MONTH(K45)) -> 1 | I45: =IF(L45="",0,YEAR(K45)) -> 2013 | J45: =IF(L45="",0,MONTH(L45)) -> 3 | K45: 41278 | L45: 41338 | M45: =IF(L45="",0,L45-K45+1) -> 61 | O45: =IF(M45<91,"V","") -> V
B46: 營運管理處 | C46: 員林站 | D46: 3/5T司機 | F46: 陳孟銓 | G46: =IF(K46="",0,YEAR(K46)) -> 2012 | H46: =IF(K46="",0,MONTH(K46)) -> 5 | I46: =IF(L46="",0,YEAR(K46)) -> 2012 | J46: =IF(L46="",0,MONTH(L46)) -> 3 | K46: 41054 | L46: 41339 | M46: =IF(L46="",0,L46-K46+1) -> 286 | O46: =IF(M46<91,"V","")
B47: 再生處理處 | C47: 全興廠分選課 | D47: 作業員 | E47: 01711 | F47: 沙陸 | G47: =IF(K47="",0,YEAR(K47)) -> 2010 | H47: =IF(K47="",0,MONTH(K47)) -> 12 | I47: =IF(L47="",0,YEAR(K47)) -> 2010 | J47: =IF(L47="",0,MONTH(L47)) -> 3 | K47: 40515 | L47: 41337 | M47: =IF(L47="",0,L47-K47+1) -> 823 | O47: =IF(M47<91,"V","")
B48: 營運管理處 | C48: 營運管理處-主任班 | D48: 儲備幹部 | F48: 李建毅 | G48: =IF(K48="",0,YEAR(K48)) -> 2013 | H48: =IF(K48="",0,MONTH(K48)) -> 1 | I48: =IF(L48="",0,YEAR(K48)) -> 2013 | J48: =IF(L48="",0,MONTH(L48)) -> 3 | K48: 41281 | L48: 41342 | M48: =IF(L48="",0,L48-K48+1) -> 62 | O48: =IF(M48<91,"V","") -> V
B49: 財務處 | C49: 財務處-會計組 | D49: 助理管理師 | E49: 02182 | F49: 蔡淑婷 | G49: =IF(K49="",0,YEAR(K49)) -> 2012 | H49: =IF(K49="",0,MONTH(K49)) -> 10 | I49: =IF(L49="",0,YEAR(K49)) -> 2012 | J49: =IF(L49="",0,MONTH(L49)) -> 3 | K49: 41197 | L49: 41341 | M49: =IF(L49="",0,L49-K49+1) -> 145 | O49: =IF(M49<91,"V","")
B50: 營運管理處 | C50: 彰興站 | D50: 3/5T司機 | F50: 陶錫民 | G50: =IF(K50="",0,YEAR(K50)) -> 2012 | H50: =IF(K50="",0,MONTH(K50)) -> 6 | I50: =IF(L50="",0,YEAR(K50)) -> 2012 | J50: =IF(L50="",0,MONTH(L50)) -> 3 | K50: 41064 | L50: 41342 | M50: =IF(L50="",0,L50-K50+1) -> 279 | O50: =IF(M50<91,"V","")
B51: 再生處理處 | C51: 喬翔分選 | D51: 計時作業員 | F51: 廖玉梅 | G51: =IF(K51="",0,YEAR(K51)) -> 2012 | H51: =IF(K51="",0,MONTH(K51)) -> 12 | I51: =IF(L51="",0,YEAR(K51)) -> 2012 | J51: =IF(L51="",0,MONTH(L51)) -> 3 | K51: 41250 | L51: 41342 | M51: =IF(L51="",0,L51-K51+1) -> 93 | O51: =IF(M51<91,"V","")
B52: 業務開發處 | C52: 友達-后里包材清潔區 | D52: 作業員 | F52: 陳怡如 | G52: =IF(K52="",0,YEAR(K52)) -> 2011 | H52: =IF(K52="",0,MONTH(K52)) -> 12 | I52: =IF(L52="",0,YEAR(K52)) -> 2011 | J52: =IF(L52="",0,MONTH(L52)) -> 3 | K52: 40904 | L52: 41345 | M52: =IF(L52="",0,L52-K52+1) -> 442 | O52: =IF(M52<91,"V","")
B53: 策略管理處 | C53: 人資策略組 | D53: 管理師 | E53: 02215 | F53: 紀友文 | G53: =IF(K53="",0,YEAR(K53)) -> 2013 | H53: =IF(K53="",0,MONTH(K53)) -> 1 | I53: =IF(L53="",0,YEAR(K53)) -> 2013 | J53: =IF(L53="",0,MONTH(L53)) -> 3 | K53: 41288 | L53: 41346 | M53: =IF(L53="",0,L53-K53+1) -> 59 | O53: =IF(M53<91,"V","") -> V
B54: 業務開發處 | C54: 文山專案 | D54: 助理會計 | E54: C00032 | F54: 魏妙華 | G54: =IF(K54="",0,YEAR(K54)) -> 2013 | H54: =IF(K54="",0,MONTH(K54)) -> 3 | I54: =IF(L54="",0,YEAR(K54)) -> 2013 | J54: =IF(L54="",0,MONTH(L54)) -> 3 | K54: 41345 | L54: 41347 | M54: =IF(L54="",0,L54-K54+1) -> 3 | O54: =IF(M54<91,"V","") -> V
B55: 業務開發處 | C55: 高雄資收(仁武) | D55: 外場人員 | E55: 02066 | F55: 陳清波 | G55: =IF(K55="",0,YEAR(K55)) -> 2012 | H55: =IF(K55="",0,MONTH(K55)) -> 5 | I55: =IF(L55="",0,YEAR(K55)) -> 2012 | J55: =IF(L55="",0,MONTH(L55)) -> 3 | K55: 41031 | L55: 41347 | M55: =IF(L55="",0,L55-K55+1) -> 317 | O55: =IF(M55<91,"V","")
B56: 營運管理處 | C56: 土城站 | D56: 外場人員 | E56: C00034 | F56: 劉得鑅 | G56: =IF(K56="",0,YEAR(K56)) -> 2013 | H56: =IF(K56="",0,MONTH(K56)) -> 3 | I56: =IF(L56="",0,YEAR(K56)) -> 2013 | J56: =IF(L56="",0,MONTH(L56)) -> 3 | K56: 41349 | L56: 41351 | M56: =IF(L56="",0,L56-K56+1) -> 3 | O56: =IF(M56<91,"V","") -> V
B57: 業務開發處 | C57: 物流管理組 | D57: 司機 | E57: C00035 | F57: 陳東煒 | G57: =IF(K57="",0,YEAR(K57)) -> 2013 | H57: =IF(K57="",0,MONTH(K57)) -> 3 | I57: =IF(L57="",0,YEAR(K57)) -> 2013 | J57: =IF(L57="",0,MONTH(L57)) -> 3 | K57: 41349 | L57: 41351 | M57: =IF(L57="",0,L57-K57+1) -> 3 | O57: =IF(M57<91,"V","") -> V
B58: 業務開發處 | C58: 友達包材 | D58: 作業員 | E58: C00033 | F58: 曾苑婷 | G58: =IF(K58="",0,YEAR(K58)) -> 2013 | H58: =IF(K58="",0,MONTH(K58)) -> 3 | I58: =IF(L58="",0,YEAR(K58)) -> 2013 | J58: =IF(L58="",0,MONTH(L58)) -> 3 | K58: 41346 | L58: 41352 | M58: =IF(L58="",0,L58-K58+1) -> 7 | O58: =IF(M58<91,"V","") -> V
B59: 業務開發處 | C59: 業務開發處-南區市場開發部 | D59: 業務專員 | E59: 02230 | F59: 涂志偉 | G59: =IF(K59="",0,YEAR(K59)) -> 2013 | H59: =IF(K59="",0,MONTH(K59)) -> 3 | I59: =IF(L59="",0,YEAR(K59)) -> 2013 | J59: =IF(L59="",0,MONTH(L59)) -> 3 | K59: 41344 | L59: 41348 | M59: =IF(L59="",0,L59-K59+1) -> 5 | O59: =IF(M59<91,"V","") -> V
B60: 營運管理處 | C60: 土城站(新站) | D60: 外場人員 | F60: 曾裕勝 | G60: =IF(K60="",0,YEAR(K60)) -> 2013 | H60: =IF(K60="",0,MONTH(K60)) -> 3 | I60: =IF(L60="",0,YEAR(K60)) -> 2013 | J60: =IF(L60="",0,MONTH(L60)) -> 3 | K60: 41354 | L60: 41355 | M60: =IF(L60="",0,L60-K60+1) -> 2 | O60: =IF(M60<91,"V","") -> V
B61: 業務開發處 | C61: 業務開發處-南區物流倉儲部 | D61: 主任 | E61: 02221 | F61: 藍友智 | G61: =IF(K61="",0,YEAR(K61)) -> 2013 | H61: =IF(K61="",0,MONTH(K61)) -> 1 | I61: =IF(L61="",0,YEAR(K61)) -> 2013 | J61: =IF(L61="",0,MONTH(L61)) -> 3 | K61: 41295 | L61: 41355 | M61: =IF(L61="",0,L61-K61+1) -> 61 | O61: =IF(M61<91,"V","") -> V
B62: 業務開發處 | C62: 明基北部專案(蘆竹) | D62: 外場人員 | E62: 02145 | F62: 蕭國輝 | G62: =IF(K62="",0,YEAR(K62)) -> 2012 | H62: =IF(K62="",0,MONTH(K62)) -> 7 | I62: =IF(L62="",0,YEAR(K62)) -> 2012 | J62: =IF(L62="",0,MONTH(L62)) -> 3 | K62: 41110 | L62: 41358 | M62: =IF(L62="",0,L62-K62+1) -> 249 | O62: =IF(M62<91,"V","")
B63: 營運管理處 | C63: 北部(新站) | D63: 窗口會計 | E63: X | F63: 徐金蓮 | G63: =IF(K63="",0,YEAR(K63)) -> 2013 | H63: =IF(K63="",0,MONTH(K63)) -> 3 | I63: =IF(L63="",0,YEAR(K63)) -> 2013 | J63: =IF(L63="",0,MONTH(L63)) -> 3 | K63: =VLOOKUP(F63,'到職(舊)'!$D$2:$G$12806,4,) -> 41359 | L63: 41359 | M63: =IF(L63="",0,L63-K63+1) -> 1 | O63: =IF(M63<91,"V","") -> V
B64: 營運管理處 | C64: 台中水湳站 | D64: 外場人員 | E64: 02226 | F64: 莊庭鋒 | G64: =IF(K64="",0,YEAR(K64)) -> 2013 | H64: =IF(K64="",0,MONTH(K64)) -> 1 | I64: =IF(L64="",0,YEAR(K64)) -> 2013 | J64: =IF(L64="",0,MONTH(L64)) -> 3 | K64: 41296 | L64: 41360 | M64: =IF(L64="",0,L64-K64+1) -> 65 | O64: =IF(M64<91,"V","") -> V
B65: 業務開發處 | C65: 夢時代統包 | D65: 外場人員 | E65: 02231 | F65: 張紘維 | G65: =IF(K65="",0,YEAR(K65)) -> 2013 | H65: =IF(K65="",0,MONTH(K65)) -> 2 | I65: =IF(L65="",0,YEAR(K65)) -> 2013 | J65: =IF(L65="",0,MONTH(L65)) -> 3 | K65: =VLOOKUP(F65,'到職(舊)'!$D$2:$G$12806,4,) -> 41314 | L65: 41356 | M65: =IF(L65="",0,L65-K65+1) -> 43 | O65: =IF(M65<91,"V","") -> V
B66: 再生處理處 | C66: 研發中心 | D66: 管理師 | E66: 01828 | F66: 李德偉 | G66: =IF(K66="",0,YEAR(K66)) -> 2011 | H66: =IF(K66="",0,MONTH(K66)) -> 6 | I66: =IF(L66="",0,YEAR(K66)) -> 2011 | J66: =IF(L66="",0,MONTH(L66)) -> 3 | K66: =VLOOKUP(F66,'到職(舊)'!$D$2:$G$12806,4,) -> 40708 | L66: 41361 | M66: =IF(L66="",0,L66-K66+1) -> 654 | O66: =IF(M66<91,"V","")
B67: 業務開發處 | C67: 南科3M | D67: 作業員 | E67: 00564 | F67: 王國斌 | G67: =IF(K67="",0,YEAR(K67)) -> 2007 | H67: =IF(K67="",0,MONTH(K67)) -> 8 | I67: =IF(L67="",0,YEAR(K67)) -> 2007 | J67: =IF(L67="",0,MONTH(L67)) -> 3 | K67: =VLOOKUP(F67,'到職(舊)'!$D$2:$G$12806,4,) -> 39307 | L67: 41364 | M67: =IF(L67="",0,L67-K67+1) -> 2058 | O67: =IF(M67<91,"V","")
B68: 再生處理處 | C68: 造粒課 | D68: 外勞 | E68: 01783 | F68: 邦亞 | G68: =IF(K68="",0,YEAR(K68)) -> 2011 | H68: =IF(K68="",0,MONTH(K68)) -> 4 | I68: =IF(L68="",0,YEAR(K68)) -> 2011 | J68: =IF(L68="",0,MONTH(L68)) -> 3 | K68: =VLOOKUP(F68,'到職(舊)'!$D$2:$G$12806,4,) -> 40640 | L68: 41364 | M68: =IF(L68="",0,L68-K68+1) -> 725 | O68: =IF(M68<91,"V","")
B69: 業務開發處 | C69: 文山專案 | D69: 窗口會計 | E69: 01576 | F69: 黃毓如 | G69: =IF(K69="",0,YEAR(K69)) -> 2010 | H69: =IF(K69="",0,MONTH(K69)) -> 6 | I69: =IF(L69="",0,YEAR(K69)) -> 2010 | J69: =IF(L69="",0,MONTH(L69)) -> 3 | K69: =VLOOKUP(F69,'到職(舊)'!$D$2:$G$12806,4,) -> 40339 | L69: 41364 | M69: =IF(L69="",0,L69-K69+1) -> 1026 | O69: =IF(M69<91,"V","")
B70: 再生處理處 | C70: 喬翔分選課 | D70: 作業員 | E70: 01861 | F70: 蔡憶如 | G70: =IF(K70="",0,YEAR(K70)) -> 2011 | H70: =IF(K70="",0,MONTH(K70)) -> 8 | I70: =IF(L70="",0,YEAR(K70)) -> 2011 | J70: =IF(L70="",0,MONTH(L70)) -> 3 | K70: =VLOOKUP(F70,'到職(舊)'!$D$2:$G$12806,4,) -> 40757 | L70: 41364 | M70: =IF(L70="",0,L70-K70+1) -> 608 | O70: =IF(M70<91,"V","")
B71: 業務開發處 | C71: 明基北部專案(蘆竹) | D71: 外場人員 | E71: 02137 | F71: 江惠芬 | G71: =IF(K71="",0,YEAR(K71)) -> 2012 | H71: =IF(K71="",0,MONTH(K71)) -> 7 | I71: =IF(L71="",0,YEAR(K71)) -> 2012 | J71: =IF(L71="",0,MONTH(L71)) -> 3 | K71: =VLOOKUP(F71,'到職(舊)'!$D$2:$G$12806,4,) -> 41103 | L71: 41364 | M71: =IF(L71="",0,L71-K71+1) -> 262 | O71: =IF(M71<91,"V","")
B72: 業務開發處 | C72: 明基北部專案(蘆竹) | D72: 外場人員 | E72: 02136 | F72: 田奇旺 | G72: =IF(K72="",0,YEAR(K72)) -> 2012 | H72: =IF(K72="",0,MONTH(K72)) -> 7 | I72: =IF(L72="",0,YEAR(K72)) -> 2012 | J72: =IF(L72="",0,MONTH(L72)) -> 3 | K72: =VLOOKUP(F72,'到職(舊)'!$D$2:$G$12806,4,) -> 41102 | L72: 41364 | M72: =IF(L72="",0,L72-K72+1) -> 263 | O72: =IF(M72<91,"V","")
B73: 業務開發處 | C73: 友達-后里包材清潔區 | D73: 作業員 | E73: 01943 | F73: 紀如萍 | G73: =IF(K73="",0,YEAR(K73)) -> 2011 | H73: =IF(K73="",0,MONTH(K73)) -> 12 | I73: =IF(L73="",0,YEAR(K73)) -> 2011 | J73: =IF(L73="",0,MONTH(L73)) -> 3 | K73: =VLOOKUP(F73,'到職(舊)'!$D$2:$G$12806,4,) -> 40904 | L73: 41364 | M73: =IF(L73="",0,L73-K73+1) -> 461 | O73: =IF(M73<91,"V","")
B74: 業務開發處 | C74: 友達-后里包材清潔區 | D74: 作業員 | E74: 01953 | F74: 謝紫欣 | G74: =IF(K74="",0,YEAR(K74)) -> 2011 | H74: =IF(K74="",0,MONTH(K74)) -> 12 | I74: =IF(L74="",0,YEAR(K74)) -> 2011 | J74: =IF(L74="",0,MONTH(L74)) -> 3 | K74: =VLOOKUP(F74,'到職(舊)'!$D$2:$G$12806,4,) -> 40904 | L74: 41364 | M74: =IF(L74="",0,L74-K74+1) -> 461 | O74: =IF(M74<91,"V","")
B75: 業務開發處 | C75: 業務開發處-北區市場開發部 | D75: 業務專員 | E75: 02220 | F75: 余靜怡 | G75: =IF(K75="",0,YEAR(K75)) -> 2013 | H75: =IF(K75="",0,MONTH(K75)) -> 1 | I75: =IF(L75="",0,YEAR(K75)) -> 2013 | J75: =IF(L75="",0,MONTH(L75)) -> 3 | K75: =VLOOKUP(F75,'到職(舊)'!$D$2:$G$12806,4,) -> 41295 | L75: 41364 | M75: =IF(L75="",0,L75-K75+1) -> 70 | O75: =IF(M75<91,"V","") -> V
B76: 營運管理處 | C76: 土城中華站 | D76: 3.5T司機 | E76: 02267 | F76: 呂議閎 | G76: =IF(K76="",0,YEAR(K76)) -> 2013 | H76: =IF(K76="",0,MONTH(K76)) -> 3 | I76: =IF(L76="",0,YEAR(K76)) -> 2013 | J76: =IF(L76="",0,MONTH(L76)) -> 4 | K76: =VLOOKUP(F76,'到職(舊)'!$D$2:$G$12806,4,) -> 41358 | L76: 41367 | M76: =IF(L76="",0,L76-K76+1) -> 10 | O76: =IF(M76<91,"V","") -> V
B77: 再生處理處 | C77: 喬翔分選課 | D77: 作業員 | F77: 彭國智 | G77: =IF(K77="",0,YEAR(K77)) -> 2010 | H77: =IF(K77="",0,MONTH(K77)) -> 6 | I77: =IF(L77="",0,YEAR(K77)) -> 2010 | J77: =IF(L77="",0,MONTH(L77)) -> 4 | K77: =VLOOKUP(F77,'到職(舊)'!$D$2:$G$12806,4,) -> 40350 | L77: 41370 | M77: =IF(L77="",0,L77-K77+1) -> 1021 | O77: =IF(M77<91,"V","")
B78: 業務開發處 | C78: 南科3m | D78: 臨時工 | F78: 張郡勻 | G78: =IF(K78="",0,YEAR(K78)) -> 2013 | H78: =IF(K78="",0,MONTH(K78)) -> 2 | I78: =IF(L78="",0,YEAR(K78)) -> 2013 | J78: =IF(L78="",0,MONTH(L78)) -> 4 | K78: =VLOOKUP(F78,'到職(舊)'!$D$2:$G$12806,4,) -> 41323 | L78: 41370 | M78: =IF(L78="",0,L78-K78+1) -> 48 | O78: =IF(M78<91,"V","") -> V
B79: 業務開發處 | C79: 南科3m | D79: 臨時工 | F79: 方雅欣 | G79: =IF(K79="",0,YEAR(K79)) -> 2013 | H79: =IF(K79="",0,MONTH(K79)) -> 2 | I79: =IF(L79="",0,YEAR(K79)) -> 2013 | J79: =IF(L79="",0,MONTH(L79)) -> 4 | K79: =VLOOKUP(F79,'到職(舊)'!$D$2:$G$12806,4,) -> 41324 | L79: 41370 | M79: =IF(L79="",0,L79-K79+1) -> 47 | O79: =IF(M79<91,"V","") -> V
B80: 業務開發處 | C80: 南科3m | D80: 臨時工 | F80: 王俊銘 | G80: =IF(K80="",0,YEAR(K80)) -> 2013 | H80: =IF(K80="",0,MONTH(K80)) -> 3 | I80: =IF(L80="",0,YEAR(K80)) -> 2013 | J80: =IF(L80="",0,MONTH(L80)) -> 4 | K80: =VLOOKUP(F80,'到職(舊)'!$D$2:$G$12806,4,) -> 41340 | L80: 41370 | M80: =IF(L80="",0,L80-K80+1) -> 31 | O80: =IF(M80<91,"V","") -> V
B81: 業務開發處 | C81: 南科3m | D81: 臨時工 | F81: 王振崑 | G81: =IF(K81="",0,YEAR(K81)) -> 2013 | H81: =IF(K81="",0,MONTH(K81)) -> 3 | I81: =IF(L81="",0,YEAR(K81)) -> 2013 | J81: =IF(L81="",0,MONTH(L81)) -> 4 | K81: =VLOOKUP(F81,'到職(舊)'!$D$2:$G$12806,4,) -> 41340 | L81: 41370 | M81: =IF(L81="",0,L81-K81+1) -> 31 | O81: =IF(M81<91,"V","") -> V
B82: 業務開發處 | C82: 南科3m | D82: 臨時工 | F82: 王政煌 | G82: =IF(K82="",0,YEAR(K82)) -> 2013 | H82: =IF(K82="",0,MONTH(K82)) -> 3 | I82: =IF(L82="",0,YEAR(K82)) -> 2013 | J82: =IF(L82="",0,MONTH(L82)) -> 4 | K82: =VLOOKUP(F82,'到職(舊)'!$D$2:$G$12806,4,) -> 41340 | L82: 41370 | M82: =IF(L82="",0,L82-K82+1) -> 31 | O82: =IF(M82<91,"V","") -> V
B83: 業務開發處 | C83: 友達-后里包材清潔區 | D83: 人力仲介 | E83: X | F83: 葉奇讓 | G83: =IF(K83="",0,YEAR(K83)) -> 2012 | H83: =IF(K83="",0,MONTH(K83)) -> 10 | I83: =IF(L83="",0,YEAR(K83)) -> 2012 | J83: =IF(L83="",0,MONTH(L83)) -> 4 | K83: =VLOOKUP(F83,'到職(舊)'!$D$2:$G$12806,4,) -> 41212 | L83: 41367 | M83: =IF(L83="",0,L83-K83+1) -> 156 | O83: =IF(M83<91,"V","")
B84: 業務開發處 | C84: 南科3m | D84: 作業員 | E84: 02266 | F84: 林湧振 | G84: =IF(K84="",0,YEAR(K84)) -> 2013 | H84: =IF(K84="",0,MONTH(K84)) -> 3 | I84: =IF(L84="",0,YEAR(K84)) -> 2013 | J84: =IF(L84="",0,MONTH(L84)) -> 4 | K84: =VLOOKUP(F84,'到職(舊)'!$D$2:$G$12806,4,) -> 41358 | L84: 41376 | M84: =IF(L84="",0,L84-K84+1) -> 19 | O84: =IF(M84<91,"V","") -> V
B85: 營運管理處 | C85: 中和中山站 | D85: 3.5T司機 | E85: 02263 | F85: 李志華 | G85: =IF(K85="",0,YEAR(K85)) -> 2013 | H85: =IF(K85="",0,MONTH(K85)) -> 3 | I85: =IF(L85="",0,YEAR(K85)) -> 2013 | J85: =IF(L85="",0,MONTH(L85)) -> 4 | K85: =VLOOKUP(F85,'到職(舊)'!$D$2:$G$12806,4,) -> 41354 | L85: 41379 | M85: =IF(L85="",0,L85-K85+1) -> 26 | O85: =IF(M85<91,"V","") -> V
B86: 營運管理處 | C86: 營管處行政室&加盟室 | D86: 儲備主管 | F86: 吳翊帆 | G86: =IF(K86="",0,YEAR(K86)) -> 2013 | H86: =IF(K86="",0,MONTH(K86)) -> 3 | I86: =IF(L86="",0,YEAR(K86)) -> 2013 | J86: =IF(L86="",0,MONTH(L86)) -> 4 | K86: =VLOOKUP(F86,'到職(舊)'!$D$2:$G$12806,4,) -> 41334 | L86: 41377 | M86: =IF(L86="",0,L86-K86+1) -> 44 | O86: =IF(M86<91,"V","") -> V
B87: 再生處理處 | C87: 喬翔分選課 | D87: 作業員 | E87: 02280 | F87: 鍾炎賜 | G87: =IF(K87="",0,YEAR(K87)) -> 2013 | H87: =IF(K87="",0,MONTH(K87)) -> 4 | I87: =IF(L87="",0,YEAR(K87)) -> 2013 | J87: =IF(L87="",0,MONTH(L87)) -> 4 | K87: =VLOOKUP(F87,'到職(舊)'!$D$2:$G$12806,4,) -> 41372 | L87: =VLOOKUP(F87,'離職(舊)'!$D$46:$G$12509,4,) -> 41381 | M87: =IF(L87="",0,L87-K87+1) -> 10 | O87: =IF(M87<91,"V","") -> V
B88: 業務開發處 | C88: 北部資收(蘆竹) | D88: 外場人員 | E88: 02090 | F88: 馬德樑 | G88: =IF(K88="",0,YEAR(K88)) -> 2012 | H88: =IF(K88="",0,MONTH(K88)) -> 5 | I88: =IF(L88="",0,YEAR(K88)) -> 2012 | J88: =IF(L88="",0,MONTH(L88)) -> 4 | K88: =VLOOKUP(F88,'到職(舊)'!$D$2:$G$12806,4,) -> 41051 | L88: 41382 | M88: =IF(L88="",0,L88-K88+1) -> 332 | O88: =IF(M88<91,"V","")
B89: 再生處理處 | C89: 喬翔分選課 | D89: 作業員 | E89: X | F89: 黃美紅 | G89: =IF(K89="",0,YEAR(K89)) -> 2013 | H89: =IF(K89="",0,MONTH(K89)) -> 4 | I89: =IF(L89="",0,YEAR(K89)) -> 2013 | J89: =IF(L89="",0,MONTH(L89)) -> 4 | K89: =VLOOKUP(F89,'到職(舊)'!$D$2:$G$12806,4,) -> 41382 | L89: 41382 | M89: =IF(L89="",0,L89-K89+1) -> 1 | O89: =IF(M89<91,"V","") -> V
B90: 再生處理處 | C90: 喬翔分選課 | D90: 作業員 | E90: X | F90: 黃月香 | G90: =IF(K90="",0,YEAR(K90)) -> 2013 | H90: =IF(K90="",0,MONTH(K90)) -> 4 | I90: =IF(L90="",0,YEAR(K90)) -> 2013 | J90: =IF(L90="",0,MONTH(L90)) -> 4 | K90: =VLOOKUP(F90,'到職(舊)'!$D$2:$G$12806,4,) -> 41382 | L90: 41383 | M90: =IF(L90="",0,L90-K90+1) -> 2 | O90: =IF(M90<91,"V","") -> V
B91: 營運管理處 | C91: 土城中華站 | D91: 3.5T司機 | E91: X | F91: 洪祺賢 | G91: =IF(K91="",0,YEAR(K91)) -> 2013 | H91: =IF(K91="",0,MONTH(K91)) -> 4 | I91: =IF(L91="",0,YEAR(K91)) -> 2013 | J91: =IF(L91="",0,MONTH(L91)) -> 4 | K91: =VLOOKUP(F91,'到職(舊)'!$D$2:$G$12806,4,) -> 41381 | L91: 41383 | M91: =IF(L91="",0,L91-K91+1) -> 3 | O91: =IF(M91<91,"V","") -> V
B92: 營運管理處 | C92: 彰興站 | D92: 外場人員 | E92: 00057 | F92: 張維祺 | G92: =IF(K92="",0,YEAR(K92)) -> 2004 | H92: =IF(K92="",0,MONTH(K92)) -> 6 | I92: =IF(L92="",0,YEAR(K92)) -> 2004 | J92: =IF(L92="",0,MONTH(L92)) -> 4 | K92: 38161 | L92: 41387 | M92: =IF(L92="",0,L92-K92+1) -> 3227 | O92: =IF(M92<91,"V","")
B93: 業務開發處 | C93: 南科3m | D93: 作業員 | E93: 02248 | F93: 陳復志 | G93: =IF(K93="",0,YEAR(K93)) -> 2013 | H93: =IF(K93="",0,MONTH(K93)) -> 3 | I93: =IF(L93="",0,YEAR(K93)) -> 2013 | J93: =IF(L93="",0,MONTH(L93)) -> 4 | K93: =VLOOKUP(F93,'到職(舊)'!$D$2:$G$12806,4,) -> 41339 | L93: 41389 | M93: =IF(L93="",0,L93-K93+1) -> 51 | O93: =IF(M93<91,"V","") -> V
B94: 營運管理處 | C94: 台南站 | D94: 助理會計 | E94: 02291 | F94: 黃佩如 | G94: =IF(K94="",0,YEAR(K94)) -> 2013 | H94: =IF(K94="",0,MONTH(K94)) -> 4 | I94: =IF(L94="",0,YEAR(K94)) -> 2013 | J94: =IF(L94="",0,MONTH(L94)) -> 4 | K94: =VLOOKUP(F94,'到職(舊)'!$D$2:$G$12806,4,) -> 41387 | L94: 41389 | M94: =IF(L94="",0,L94-K94+1) -> 3 | O94: =IF(M94<91,"V","") -> V
B95: 營運管理處 | C95: 彰興站 | D95: 夾子車司機 | E95: 02276 | F95: 吳晉嘉 | G95: =IF(K95="",0,YEAR(K95)) -> 2013 | H95: =IF(K95="",0,MONTH(K95)) -> 4 | I95: =IF(L95="",0,YEAR(K95)) -> 2013 | J95: =IF(L95="",0,MONTH(L95)) -> 4 | K95: =VLOOKUP(F95,'到職(舊)'!$D$2:$G$12806,4,) -> 41372 | L95: 41393 | M95: =IF(L95="",0,L95-K95+1) -> 22 | O95: =IF(M95<91,"V","") -> V
B96: 業務開發處 | C96: 業務開發處(南區市場開發部) | D96: 業務專員 | E96: 02169 | F96: 王美乃 | G96: =IF(K96="",0,YEAR(K96)) -> 2012 | H96: =IF(K96="",0,MONTH(K96)) -> 9 | I96: =IF(L96="",0,YEAR(K96)) -> 2012 | J96: =IF(L96="",0,MONTH(L96)) -> 4 | K96: =VLOOKUP(F96,'到職(舊)'!$D$2:$G$12806,4,) -> 41155 | L96: 41394 | M96: =IF(L96="",0,L96-K96+1) -> 240 | O96: =IF(M96<91,"V","")
B97: 營運管理處 | C97: 台南站 | D97: 助理會計 | E97: 01839 | F97: 鄭乃嘉 | G97: =IF(K97="",0,YEAR(K97)) -> 2011 | H97: =IF(K97="",0,MONTH(K97)) -> 7 | I97: =IF(L97="",0,YEAR(K97)) -> 2011 | J97: =IF(L97="",0,MONTH(L97)) -> 4 | K97: =VLOOKUP(F97,'到職(舊)'!$D$2:$G$12806,4,) -> 40725 | L97: 41394 | M97: =IF(L97="",0,L97-K97+1) -> 670 | O97: =IF(M97<91,"V","")
B98: 營運管理處 | C98: 員林三信站 | D98: 助理會計 | E98: 02044 | F98: 邱瓊珠 | G98: =IF(K98="",0,YEAR(K98)) -> 2012 | H98: =IF(K98="",0,MONTH(K98)) -> 4 | I98: =IF(L98="",0,YEAR(K98)) -> 2012 | J98: =IF(L98="",0,MONTH(L98)) -> 4 | K98: =VLOOKUP(F98,'到職(舊)'!$D$2:$G$12806,4,) -> 41008 | L98: 41394 | M98: =IF(L98="",0,L98-K98+1) -> 387 | O98: =IF(M98<91,"V","")
B99: 業務開發處 | C99: 文山專案 | D99: 作業員 | E99: 02258 | F99: 溫壽昌 | G99: =IF(K99="",0,YEAR(K99)) -> 2011 | H99: =IF(K99="",0,MONTH(K99)) -> 3 | I99: =IF(L99="",0,YEAR(K99)) -> 2011 | J99: =IF(L99="",0,MONTH(L99)) -> 4 | K99: =VLOOKUP(F99,'到職(舊)'!$D$2:$G$12806,4,) -> 40609 | L99: 41394 | M99: =IF(L99="",0,L99-K99+1) -> 786 | O99: =IF(M99<91,"V","")
B100: 業務開發處 | C100: 北部資收(蘆竹) | D100: 外場人員 | E100: 02209 | F100: 劉昌旺 | G100: =IF(K100="",0,YEAR(K100)) -> 2012 | H100: =IF(K100="",0,MONTH(K100)) -> 12 | I100: =IF(L100="",0,YEAR(K100)) -> 2012 | J100: =IF(L100="",0,MONTH(L100)) -> 4 | K100: =VLOOKUP(F100,'到職(舊)'!$D$2:$G$12806,4,) -> 41257 | L100: 41394 | M100: =IF(L100="",0,L100-K100+1) -> 138 | O100: =IF(M100<91,"V","")
...

Sheet 單位離職率統計
J1: 4
A2: 事業處 | B2: 室/站/專案 | E2: =YEAR(E3)&-MONTH(E3) -> 2013-4
E3: 41365 | F3: 41394 | G3: 當月 | H3: 當月 | J3: 當月 | L3: 當月 | N3: 當月 流動率
E4: 單位總人數 | F4: 單位總人數 | G4: 新進人員人數 | H4: 人員調動 | J4: 離職人數 | L4: 離職率
H5: 增加 | I5: 減少 | J5: 未滿90天 | K5: 全部 | L5: 未滿90天 | M5: 全部
A6: =B6 -> #REF! | B6: =#REF! -> #REF! | E6: 7 | F6: 7 | G6: =COUNTIFS(資料!$C:$C,B6,資料!$G:$G,"2013",資料!$H:$H,"4") -> 0 | H6: 0 | I6: 0 | J6: =COUNTIFS(資料!$C:$C,B6,資料!$I:$I,"2013",資料!$J:$J,"4",資料!$O:$O,"V") -> 0 | K6: =COUNTIFS(資料!$C:$C,B6,資料!$I:$I,"2013",資料!$J:$J,"4") -> 0 | L6: =J6/AVERAGE(E6,F6) -> 0 | M6: =K6/AVERAGE(E6,F6) -> 0 | N6: =(G6+K6)/AVERAGE(E6,F6) -> 0
A7: =B7 -> #REF! | B7: =#REF! -> #REF! | E7: 4 | F7: 5 | G7: =COUNTIFS(資料!$C:$C,B7,資料!$G:$G,"2013",資料!$H:$H,"4") -> 0 | H7: 0 | I7: 0 | J7: =COUNTIFS(資料!$C:$C,B7,資料!$I:$I,"2013",資料!$J:$J,"4",資料!$O:$O,"V") -> 0 | K7: =COUNTIFS(資料!$C:$C,B7,資料!$I:$I,"2013",資料!$J:$J,"4") -> 0 | L7: =J7/AVERAGE(E7,F7) -> 0 | M7: =K7/AVERAGE(E7,F7) -> 0 | N7: =(G7+K7)/AVERAGE(E7,F7) -> 0
A8: =B8 -> #REF! | B8: =#REF! -> #REF! | E8: 4 | F8: 4 | G8: =COUNTIFS(資料!$C:$C,B8,資料!$G:$G,"2013",資料!$H:$H,"4") -> 0 | H8: 0 | I8: 0 | J8: =COUNTIFS(資料!$C:$C,B8,資料!$I:$I,"2013",資料!$J:$J,"4",資料!$O:$O,"V") -> 0 | K8: =COUNTIFS(資料!$C:$C,B8,資料!$I:$I,"2013",資料!$J:$J,"4") -> 0 | L8: =J8/AVERAGE(E8,F8) -> 0 | M8: =K8/AVERAGE(E8,F8) -> 0 | N8: =(G8+K8)/AVERAGE(E8,F8) -> 0
A9: 財務處 | B9: =#REF! -> #REF! | E9: 1 | F9: 1 | G9: =COUNTIFS(資料!$C:$C,A9,資料!$G:$G,"2013",資料!$H:$H,"4") -> 0 | H9: 0 | I9: 0 | J9: =COUNTIFS(資料!$C:$C,B9,資料!$I:$I,"2013",資料!$J:$J,"4",資料!$O:$O,"V") -> 0 | K9: =COUNTIFS(資料!$C:$C,B9,資料!$I:$I,"2013",資料!$J:$J,"4") -> 0 | L9: =J9/AVERAGE(E9,F9) -> 0 | M9: =K9/AVERAGE(E9,F9) -> 0 | N9: =(G9+K9)/AVERAGE(E9,F9) -> 0
B10: =#REF! -> #REF! | E10: 3 | F10: 3 | J10: =COUNTIFS(資料!$C:$C,B10,資料!$I:$I,"2013",資料!$J:$J,"4",資料!$O:$O,"V") -> 0 | K10: =COUNTIFS(資料!$C:$C,B10,資料!$I:$I,"2013",資料!$J:$J,"4") -> 0 | L10: =J10/AVERAGE(E10,F10) -> 0 | M10: =K10/AVERAGE(E10,F10) -> 0 | N10: =(G10+K10)/AVERAGE(E10,F10) -> 0
B11: =#REF! -> #REF! | E11: 9 | F11: 9 | J11: =COUNTIFS(資料!$C:$C,B11,資料!$I:$I,"2013",資料!$J:$J,"4",資料!$O:$O,"V") -> 0 | K11: =COUNTIFS(資料!$C:$C,B11,資料!$I:$I,"2013",資料!$J:$J,"4") -> 0 | L11: =J11/AVERAGE(E11,F11) -> 0 | M11: =K11/AVERAGE(E11,F11) -> 0 | N11: =(G11+K11)/AVERAGE(E11,F11) -> 0
B12: =#REF! -> #REF! | E12: 3 | F12: 3 | J12: =COUNTIFS(資料!$C:$C,B12,資料!$I:$I,"2013",資料!$J:$J,"4",資料!$O:$O,"V") -> 0 | K12: =COUNTIFS(資料!$C:$C,B12,資料!$I:$I,"2013",資料!$J:$J,"4") -> 0 | L12: =J12/AVERAGE(E12,F12) -> 0 | M12: =K12/AVERAGE(E12,F12) -> 0 | N12: =(G12+K12)/AVERAGE(E12,F12) -> 0
A13: 策略管理處 | B13: =#REF! -> #REF! | E13: 3 | F13: 3 | G13: =COUNTIFS(資料!$C:$C,B13,資料!$G:$G,"2013",資料!$H:$H,"4") -> 0 | H13: 0 | I13: 0 | J13: =COUNTIFS(資料!$C:$C,B13,資料!$I:$I,"2013",資料!$J:$J,"4",資料!$O:$O,"V") -> 0 | K13: =COUNTIFS(資料!$C:$C,B13,資料!$I:$I,"2013",資料!$J:$J,"4") -> 0 | L13: =J13/AVERAGE(E13,F13) -> 0 | M13: =K13/AVERAGE(E13,F13) -> 0 | N13: =(G13+K13)/AVERAGE(E13,F13) -> 0
B14: =#REF! -> #REF! | E14: 2 | F14: 2 | G14: =COUNTIFS(資料!$C:$C,B14,資料!$G:$G,"2013",資料!$H:$H,"4") -> 0 | H14: 0 | I14: 0 | J14: =COUNTIFS(資料!$C:$C,B14,資料!$I:$I,"2013",資料!$J:$J,"4",資料!$O:$O,"V") -> 0 | K14: =COUNTIFS(資料!$C:$C,B14,資料!$I:$I,"2013",資料!$J:$J,"4") -> 0 | L14: =J14/AVERAGE(E14,F14) -> 0 | M14: =K14/AVERAGE(E14,F14) -> 0 | N14: =(G14+K14)/AVERAGE(E14,F14) -> 0
B15: =#REF! -> #REF! | E15: 5 | F15: 6 | G15: =COUNTIFS(資料!$C:$C,B15,資料!$G:$G,"2013",資料!$H:$H,"4") -> 0 | H15: 0 | I15: 0 | J15: =COUNTIFS(資料!$C:$C,B15,資料!$I:$I,"2013",資料!$J:$J,"4",資料!$O:$O,"V") -> 0 | K15: =COUNTIFS(資料!$C:$C,B15,資料!$I:$I,"2013",資料!$J:$J,"4") -> 0 | L15: =J15/AVERAGE(E15,F15) -> 0 | M15: =K15/AVERAGE(E15,F15) -> 0 | N15: =(G15+K15)/AVERAGE(E15,F15) -> 0
B16: =#REF! -> #REF! | E16: 2 | F16: 2 | G16: =COUNTIFS(資料!$C:$C,B16,資料!$G:$G,"2013",資料!$H:$H,"4") -> 0 | H16: 0 | I16: 0 | J16: =COUNTIFS(資料!$C:$C,B16,資料!$I:$I,"2013",資料!$J:$J,"4",資料!$O:$O,"V") -> 0 | K16: =COUNTIFS(資料!$C:$C,B16,資料!$I:$I,"2013",資料!$J:$J,"4") -> 0 | L16: =J16/AVERAGE(E16,F16) -> 0 | M16: =K16/AVERAGE(E16,F16) -> 0 | N16: =(G16+K16)/AVERAGE(E16,F16) -> 0
B17: =#REF! -> #REF! | E17: 5 | F17: 5 | G17: =COUNTIFS(資料!$C:$C,B17,資料!$G:$G,"2013",資料!$H:$H,"4") -> 0 | H17: 0 | I17: 0 | J17: =COUNTIFS(資料!$C:$C,B17,資料!$I:$I,"2013",資料!$J:$J,"4",資料!$O:$O,"V") -> 0 | K17: =COUNTIFS(資料!$C:$C,B17,資料!$I:$I,"2013",資料!$J:$J,"4") -> 0 | L17: =J17/AVERAGE(E17,F17) -> 0 | M17: =K17/AVERAGE(E17,F17) -> 0 | N17: =(G17+K17)/AVERAGE(E17,F17) -> 0
A18: 業務開發處 | B18: 處主管 | E18: 1 | F18: 1 | G18: =COUNTIFS(資料!$C:$C,B18,資料!$G:$G,"2013",資料!$H:$H,"4") -> 0 | H18: 0 | I18: 0 | J18: =COUNTIFS(資料!$C:$C,B18,資料!$I:$I,"2013",資料!$J:$J,"4",資料!$O:$O,"V") -> 0 | K18: =COUNTIFS(資料!$C:$C,B18,資料!$I:$I,"2013",資料!$J:$J,"4") -> 0 | L18: =J18/AVERAGE(E18,F18) -> 0 | M18: =K18/AVERAGE(E18,F18) -> 0 | N18: =(G18+K18)/AVERAGE(E18,F18) -> 0
B19: 業務處行政室 | E19: 6 | F19: 6 | G19: =COUNTIFS(資料!$C:$C,B19,資料!$G:$G,"2013",資料!$H:$H,"4") -> 0 | H19: 0 | I19: 0 | J19: =COUNTIFS(資料!$C:$C,B19,資料!$I:$I,"2013",資料!$J:$J,"4",資料!$O:$O,"V") -> 0 | K19: =COUNTIFS(資料!$C:$C,B19,資料!$I:$I,"2013",資料!$J:$J,"4") -> 0 | L19: =J19/AVERAGE(E19,F19) -> 0 | M19: =K19/AVERAGE(E19,F19) -> 0 | N19: =(G19+K19)/AVERAGE(E19,F19) -> 0
B20: 中區市場開發部 | E20: 3 | F20: 3 | G20: =COUNTIFS(資料!$C:$C,B20,資料!$G:$G,"2013",資料!$H:$H,"4") -> 0 | H20: 0 | I20: 0 | J20: =COUNTIFS(資料!$C:$C,B20,資料!$I:$I,"2013",資料!$J:$J,"4",資料!$O:$O,"V") -> 0 | K20: =COUNTIFS(資料!$C:$C,B20,資料!$I:$I,"2013",資料!$J:$J,"4") -> 0 | L20: =J20/AVERAGE(E20,F20) -> 0 | M20: =K20/AVERAGE(E20,F20) -> 0 | N20: =(G20+K20)/AVERAGE(E20,F20) -> 0
B21: 中區-倉儲物流管理部 | C21: 主任 | E21: 1 | F21: 1 | G21: =COUNTIFS(資料!$C:$C,B21,資料!$G:$G,"2013",資料!$H:$H,"4") -> 0 | H21: 0 | I21: 0 | J21: =COUNTIFS(資料!$C:$C,B21,資料!$I:$I,"2013",資料!$J:$J,"4",資料!$O:$O,"V") -> 0 | K21: =COUNTIFS(資料!$C:$C,C21,資料!$I:$I,"2013",資料!$J:$J,"4") -> 0 | L21: =J21/AVERAGE(E21,F21) -> 0 | M21: =K21/AVERAGE(E21,F21) -> 0 | N21: =(G21+K21)/AVERAGE(E21,F21) -> 0
D22: 中部物流管理組 | E22: 11 | F22: 11 | G22: =COUNTIFS(資料!$C:$C,D22,資料!$G:$G,"2013",資料!$H:$H,"4") -> 0 | H22: 0 | I22: 0 | J22: =COUNTIFS(資料!$C:$C,B22,資料!$I:$I,"2013",資料!$J:$J,"4",資料!$O:$O,"V") -> 0 | K22: =COUNTIFS(資料!$C:$C,D22,資料!$I:$I,"2013",資料!$J:$J,"4") -> 0 | L22: =J22/AVERAGE(E22,F22) -> 0 | M22: =K22/AVERAGE(E22,F22) -> 0 | N22: =(G22+K22)/AVERAGE(E22,F22) -> 0
D23: 中部倉庫 | E23: 6 | F23: 8 | G23: =COUNTIFS(資料!$C:$C,D23,資料!$G:$G,"2013",資料!$H:$H,"4") -> 1 | H23: 1 | I23: 0 | J23: =COUNTIFS(資料!$C:$C,D23,資料!$I:$I,"2013",資料!$J:$J,"4",資料!$O:$O,"V") -> 0 | K23: =COUNTIFS(資料!$C:$C,D23,資料!$I:$I,"2013",資料!$J:$J,"4") -> 0 | L23: =J23/AVERAGE(E23,F23) -> 0 | M23: =K23/AVERAGE(E23,F23) -> 0 | N23: =(G23+K23)/AVERAGE(E23,F23) -> 0.14285714
C24: 文山專案 | D24: 文山專案 | E24: 21 | F24: 20 | G24: =COUNTIFS(資料!$C:$C,D24,資料!$G:$G,"2013",資料!$H:$H,"4") -> 0 | H24: 0 | I24: 1 | J24: =COUNTIFS(資料!$C:$C,D24,資料!$I:$I,"2013",資料!$J:$J,"4",資料!$O:$O,"V") -> 0 | K24: =COUNTIFS(資料!$C:$C,D24,資料!$I:$I,"2013",資料!$J:$J,"4") -> 0 | L24: =J24/AVERAGE(E24,F24) -> 0 | M24: =K24/AVERAGE(E24,F24) -> 0 | N24: =(G24+K24)/AVERAGE(E24,F24) -> 0
D25: 人力仲介 | E25: 0 | F25: 0 | G25: =COUNTIFS(資料!$C:$C,D25,資料!$G:$G,"2013",資料!$H:$H,"4") -> 0 | H25: 0 | I25: 0 | J25: =COUNTIFS(資料!$C:$C,D25,資料!$I:$I,"2013",資料!$J:$J,"4",資料!$O:$O,"V") -> 0 | K25: =COUNTIFS(資料!$C:$C,D25,資料!$I:$I,"2013",資料!$J:$J,"4") -> 0 | L25: 0 | M25: 0 | N25: 0
C26: 輔祥專案 | D26: 輔祥專案 | E26: 2 | F26: 2 | G26: =COUNTIFS(資料!$C:$C,D26,資料!$G:$G,"2013",資料!$H:$H,"4") -> 0 | H26: 0 | I26: 0 | J26: =COUNTIFS(資料!$C:$C,D26,資料!$I:$I,"2013",資料!$J:$J,"4",資料!$O:$O,"V") -> 0 | K26: =COUNTIFS(資料!$C:$C,D26,資料!$I:$I,"2013",資料!$J:$J,"4") -> 0 | L26: =J26/AVERAGE(E26,F26) -> 0 | M26: =K26/AVERAGE(E26,F26) -> 0 | N26: =(G26+K26)/AVERAGE(E26,F26) -> 0
C27: 友達專案 | D27: 副主任 | E27: 2 | F27: 2 | G27: =COUNTIFS(資料!$C:$C,D27,資料!$G:$G,"2013",資料!$H:$H,"4") -> 0 | H27: 0 | I27: 0 | J27: =COUNTIFS(資料!$C:$C,D27,資料!$I:$I,"2013",資料!$J:$J,"4",資料!$O:$O,"V") -> 0 | K27: =COUNTIFS(資料!$C:$C,D27,資料!$I:$I,"2013",資料!$J:$J,"4") -> 0 | L27: =J27/AVERAGE(E27,F27) -> 0 | M27: =K27/AVERAGE(E27,F27) -> 0 | N27: =(G27+K27)/AVERAGE(E27,F27) -> 0
D28: 友達-資收區(一、二期) | E28: 9 | F28: 9 | G28: =COUNTIFS(資料!$C:$C,D28,資料!$G:$G,"2013",資料!$H:$H,"4") -> 0 | H28: 0 | I28: 0 | J28: =COUNTIFS(資料!$C:$C,D28,資料!$I:$I,"2013",資料!$J:$J,"4",資料!$O:$O,"V") -> 0 | K28: =COUNTIFS(資料!$C:$C,D28,資料!$I:$I,"2013",資料!$J:$J,"4") -> 0 | L28: =J28/AVERAGE(E28,F28) -> 0 | M28: =K28/AVERAGE(E28,F28) -> 0 | N28: =(G28+K28)/AVERAGE(E28,F28) -> 0
D29: 友達-資收區(三期) | E29: 8 | F29: 8 | G29: =COUNTIFS(資料!$C:$C,D29,資料!$G:$G,"2013",資料!$H:$H,"4") -> 0 | H29: 0 | I29: 0 | J29: =COUNTIFS(資料!$C:$C,D29,資料!$I:$I,"2013",資料!$J:$J,"4",資料!$O:$O,"V") -> 0 | K29: =COUNTIFS(資料!$C:$C,D29,資料!$I:$I,"2013",資料!$J:$J,"4") -> 0 | L29: =J29/AVERAGE(E29,F29) -> 0 | M29: =K29/AVERAGE(E29,F29) -> 0 | N29: =(G29+K29)/AVERAGE(E29,F29) -> 0
D30: 友達-包材區 | E30: 11 | F30: 11 | G30: =COUNTIFS(資料!$C:$C,D30,資料!$G:$G,"2013",資料!$H:$H,"4") -> 0 | H30: 0 | I30: 0 | J30: =COUNTIFS(資料!$C:$C,D30,資料!$I:$I,"2013",資料!$J:$J,"4",資料!$O:$O,"V") -> 0 | K30: =COUNTIFS(資料!$C:$C,D30,資料!$I:$I,"2013",資料!$J:$J,"4") -> 0 | L30: =J30/AVERAGE(E30,F30) -> 0 | M30: =K30/AVERAGE(E30,F30) -> 0 | N30: =(G30+K30)/AVERAGE(E30,F30) -> 0
D31: 友達-后里包材清潔區 | E31: 29 | F31: 31 | G31: =COUNTIFS(資料!$C:$C,D31,資料!$G:$G,"2013",資料!$H:$H,"4") -> 2 | H31: 0 | I31: 0 | J31: =COUNTIFS(資料!$C:$C,D31,資料!$I:$I,"2013",資料!$J:$J,"4",資料!$O:$O,"V") -> 0 | K31: =COUNTIFS(資料!$C:$C,D31,資料!$I:$I,"2013",資料!$J:$J,"4") -> 0 | L31: =J31/AVERAGE(E31,F31) -> 0 | M31: =K31/AVERAGE(E31,F31) -> 0 | N31: =(G31+K31)/AVERAGE(E31,F31) -> 0.066666667
D32: 友達-后里包材清潔區(人力仲介) | E32: 5 | F32: 3 | G32: =COUNTIFS(資料!$C:$C,D32,資料!$G:$G,"2013",資料!$H:$H,"4") -> 0 | H32: 0 | I32: 0 | J32: =COUNTIFS(資料!$C:$C,D32,資料!$I:$I,"2013",資料!$J:$J,"4",資料!$O:$O,"V") -> 0 | K32: 2 | L32: =J32/AVERAGE(E32,F32) -> 0 | M32: =K32/AVERAGE(E32,F32) -> 0.5 | N32: =(G32+K32)/AVERAGE(E32,F32) -> 0.5
D33: 友達-資收區(七星) | E33: 6 | F33: 6 | G33: =COUNTIFS(資料!$C:$C,D33,資料!$G:$G,"2013",資料!$H:$H,"4") -> 0 | J33: =COUNTIFS(資料!$C:$C,D33,資料!$I:$I,"2013",資料!$J:$J,"4",資料!$O:$O,"V") -> 0 | K33: =COUNTIFS(資料!$C:$C,D33,資料!$I:$I,"2013",資料!$J:$J,"4") -> 0 | L33: =J33/AVERAGE(E33,F33) -> 0 | M33: =K33/AVERAGE(E33,F33) -> 0 | N33: =(G33+K33)/AVERAGE(E33,F33) -> 0
B34: 北區市場開發部 | E34: 1 | F34: 2 | G34: =COUNTIFS(資料!$C:$C,B34,資料!$G:$G,"2013",資料!$H:$H,"4") -> 1 | H34: 0 | I34: 0 | J34: =COUNTIFS(資料!$C:$C,B34,資料!$I:$I,"2013",資料!$J:$J,"4",資料!$O:$O,"V") -> 0 | K34: =COUNTIFS(資料!$C:$C,D34,資料!$I:$I,"2013",資料!$J:$J,"4") -> 0 | L34: =J34/AVERAGE(E34,F34) -> 0 | M34: =K34/AVERAGE(E34,F34) -> 0 | N34: =(G34+K34)/AVERAGE(E34,F34) -> 0.66666667
B35: 北區-倉儲物流管理部 | C35: 北部資收 | D35: 蘆竹 | E35: 5 | F35: 5 | G35: =COUNTIFS(資料!$C:$C,C35,資料!$G:$G,"2013",資料!$H:$H,"4") -> 0 | J35: =COUNTIFS(資料!$C:$C,B34,資料!$I:$I,"2013",資料!$J:$J,"4",資料!$O:$O,"V") -> 0 | K35: =COUNTIFS(資料!$C:$C,C35,資料!$I:$I,"2013",資料!$J:$J,"4") -> 0 | L35: =J35/AVERAGE(E35,F35) -> 0 | M35: =K35/AVERAGE(E35,F35) -> 0 | N35: =(G35+K35)/AVERAGE(E35,F35) -> 0
D36: 龍潭
D37: 桃園
B38: 南區市場開發部 | E38: 4 | F38: 4 | G38: =COUNTIFS(資料!$C:$C,B38,資料!$G:$G,"2013",資料!$H:$H,"4") -> 0 | J38: =COUNTIFS(資料!$C:$C,B38,資料!$I:$I,"2013",資料!$J:$J,"4",資料!$O:$O,"V") -> 0 | K38: =COUNTIFS(資料!$C:$C,B38,資料!$I:$I,"2013",資料!$J:$J,"4") -> 0 | L38: =J38/AVERAGE(E38,F38) -> 0 | M38: =K38/AVERAGE(E38,F38) -> 0 | N38: =(G38+K38)/AVERAGE(E38,F38) -> 0
B39: 南區-倉儲物流管理部 | C39: 南部專案 | D39: 南科3m | E39: 33 | F39: 26 | G39: =COUNTIFS(資料!$C:$C,D39,資料!$G:$G,"2013",資料!$H:$H,"4") -> 0 | J39: =COUNTIFS(資料!$C:$C,D39,資料!$I:$I,"2013",資料!$J:$J,"4",資料!$O:$O,"V") -> 7 | K39: =COUNTIFS(資料!$C:$C,D39,資料!$I:$I,"2013",資料!$J:$J,"4") -> 7 | L39: =J39/AVERAGE(E39,F39) -> 0.23728814 | M39: =K39/AVERAGE(E39,F39) -> 0.23728814 | N39: =(G39+K39)/AVERAGE(E39,F39) -> 0.23728814
D40: 中強 | E40: 1 | F40: 1 | G40: =COUNTIFS(資料!$C:$C,D40,資料!$G:$G,"2013",資料!$H:$H,"4") -> 0 | J40: =COUNTIFS(資料!$C:$C,D40,資料!$I:$I,"2013",資料!$J:$J,"4",資料!$O:$O,"V") -> 0 | K40: =COUNTIFS(資料!$C:$C,D40,資料!$I:$I,"2013",資料!$J:$J,"4") -> 0 | L40: =J40/AVERAGE(E40,F40) -> 0 | M40: =K40/AVERAGE(E40,F40) -> 0 | N40: =(G40+K40)/AVERAGE(E40,F40) -> 0
D41: 聯電 | E41: 1 | F41: 1 | G41: =COUNTIFS(資料!$C:$C,D41,資料!$G:$G,"2013",資料!$H:$H,"4") -> 0 | J41: =COUNTIFS(資料!$C:$C,D41,資料!$I:$I,"2013",資料!$J:$J,"4",資料!$O:$O,"V") -> 0 | K41: =COUNTIFS(資料!$C:$C,D41,資料!$I:$I,"2013",資料!$J:$J,"4") -> 0 | L41: =J41/AVERAGE(E41,F41) -> 0 | M41: =K41/AVERAGE(E41,F41) -> 0 | N41: =(G41+K41)/AVERAGE(E41,F41) -> 0
C42: 夢時代站 | D42: 夢時代統包 | E42: 4 | F42: 4 | G42: =COUNTIFS(資料!$C:$C,D42,資料!$G:$G,"2013",資料!$H:$H,"4") -> 0 | J42: =COUNTIFS(資料!$C:$C,D42,資料!$I:$I,"2013",資料!$J:$J,"4",資料!$O:$O,"V") -> 0 | K42: =COUNTIFS(資料!$C:$C,D42,資料!$I:$I,"2013",資料!$J:$J,"4") -> 0 | L42: =J42/AVERAGE(E42,F42) -> 0 | M42: =K42/AVERAGE(E42,F42) -> 0 | N42: =(G42+K42)/AVERAGE(E42,F42) -> 0
C43: 高雄資收 | D43: 仁武倉庫 | E43: 4 | F43: 4 | G43: =COUNTIFS(資料!$C:$C,D43,資料!$G:$G,"2013",資料!$H:$H,"4") -> 0 | J43: =COUNTIFS(資料!$C:$C,D43,資料!$I:$I,"2013",資料!$J:$J,"4",資料!$O:$O,"V") -> 0 | K43: =COUNTIFS(資料!$C:$C,D43,資料!$I:$I,"2013",資料!$J:$J,"4") -> 0 | L43: =J43/AVERAGE(E43,F43) -> 0 | M43: =K43/AVERAGE(E43,F43) -> 0 | N43: =(G43+K43)/AVERAGE(E43,F43) -> 0
A44: 營運管理處 | B44: 營管處行政室&加盟室 | E44: 13 | F44: 14 | G44: =COUNTIFS(資料!$C:$C,B44,資料!$G:$G,"2013",資料!$H:$H,"4") -> 2 | J44: =COUNTIFS(資料!$C:$C,B44,資料!$I:$I,"2013",資料!$J:$J,"4",資料!$O:$O,"V") -> 1 | K44: =COUNTIFS(資料!$C:$C,B44,資料!$I:$I,"2013",資料!$J:$J,"4") -> 1 | L44: =J44/AVERAGE(E44,F44) -> 0.074074074 | M44: =K44/AVERAGE(E44,F44) -> 0.074074074 | N44: =(G44+K44)/AVERAGE(E44,F44) -> 0.22222222
B45: 北區營運中心 | D45: 土城站 | E45: 6 | F45: 7 | G45: =COUNTIFS(資料!$C:$C,D45,資料!$G:$G,"2013",資料!$H:$H,"4") -> 1 | J45: =COUNTIFS(資料!$C:$C,D45,資料!$I:$I,"2013",資料!$J:$J,"4",資料!$O:$O,"V") -> 0 | K45: =COUNTIFS(資料!$C:$C,D45,資料!$I:$I,"2013",資料!$J:$J,"4") -> 0 | L45: =J45/AVERAGE(E45,F45) -> 0 | M45: =K45/AVERAGE(E45,F45) -> 0 | N45: =(G45+K45)/AVERAGE(E45,F45) -> 0.15384615
D46: 土城中華站 | E46: 0 | F46: 3 | G46: 5 | J46: =COUNTIFS(資料!$C:$C,D46,資料!$I:$I,"2013",資料!$J:$J,"4",資料!$O:$O,"V") -> 2 | K46: =COUNTIFS(資料!$C:$C,D46,資料!$I:$I,"2013",資料!$J:$J,"4") -> 2 | L46: =J46/AVERAGE(E46,F46) -> 1.3333333 | M46: =K46/AVERAGE(E46,F46) -> 1.3333333 | N46: =(G46+K46)/AVERAGE(E46,F46) -> 4.6666667
D47: 中和中山站 | E47: 0 | F47: 2 | G47: 3 | J47: =COUNTIFS(資料!$C:$C,D47,資料!$I:$I,"2013",資料!$J:$J,"4",資料!$O:$O,"V") -> 1 | K47: =COUNTIFS(資料!$C:$C,D47,資料!$I:$I,"2013",資料!$J:$J,"4") -> 1 | L47: =J47/AVERAGE(E47,F47) -> 1 | M47: =K47/AVERAGE(E47,F47) -> 1 | N47: =(G47+K47)/AVERAGE(E47,F47) -> 4
D48: 桃園站 | E48: 8 | F48: 8 | G48: =COUNTIFS(資料!$C:$C,D48,資料!$G:$G,"2013",資料!$H:$H,"4") -> 0 | J48: =COUNTIFS(資料!$C:$C,D48,資料!$I:$I,"2013",資料!$J:$J,"4",資料!$O:$O,"V") -> 0 | K48: =COUNTIFS(資料!$C:$C,D48,資料!$I:$I,"2013",資料!$J:$J,"4") -> 0 | L48: =J48/AVERAGE(E48,F48) -> 0 | M48: =K48/AVERAGE(E48,F48) -> 0 | N48: =(G48+K48)/AVERAGE(E48,F48) -> 0
D49: 新竹站 | E49: 6 | F49: 6 | G49: =COUNTIFS(資料!$C:$C,D49,資料!$G:$G,"2013",資料!$H:$H,"4") -> 0 | J49: =COUNTIFS(資料!$C:$C,D49,資料!$I:$I,"2013",資料!$J:$J,"4",資料!$O:$O,"V") -> 0 | K49: =COUNTIFS(資料!$C:$C,D49,資料!$I:$I,"2013",資料!$J:$J,"4") -> 0 | L49: =J49/AVERAGE(E49,F49) -> 0 | M49: =K49/AVERAGE(E49,F49) -> 0 | N49: =(G49+K49)/AVERAGE(E49,F49) -> 0
B50: 中區營運中心 | D50: 彰興站 | E50: 15 | F50: 16 | G50: =COUNTIFS(資料!$C:$C,D50,資料!$G:$G,"2013",資料!$H:$H,"4") -> 2 | J50: =COUNTIFS(資料!$C:$C,D50,資料!$I:$I,"2013",資料!$J:$J,"4",資料!$O:$O,"V") -> 1 | K50: =COUNTIFS(資料!$C:$C,D50,資料!$I:$I,"2013",資料!$J:$J,"4") -> 1 | L50: =J50/AVERAGE(E50,F50) -> 0.064516129 | M50: =K50/AVERAGE(E50,F50) -> 0.064516129 | N50: =(G50+K50)/AVERAGE(E50,F50) -> 0.19354839
D51: 草屯站 | E51: 6 | F51: 6 | G51: =COUNTIFS(資料!$C:$C,D51,資料!$G:$G,"2013",資料!$H:$H,"4") -> 0 | J51: =COUNTIFS(資料!$C:$C,D51,資料!$I:$I,"2013",資料!$J:$J,"4",資料!$O:$O,"V") -> 0 | K51: =COUNTIFS(資料!$C:$C,D51,資料!$I:$I,"2013",資料!$J:$J,"4") -> 0 | L51: =J51/AVERAGE(E51,F51) -> 0 | M51: =K51/AVERAGE(E51,F51) -> 0 | N51: =(G51+K51)/AVERAGE(E51,F51) -> 0
D52: 神岡站 | E52: 7 | F52: 7 | G52: =COUNTIFS(資料!$C:$C,D52,資料!$G:$G,"2013",資料!$H:$H,"4") -> 0 | J52: =COUNTIFS(資料!$C:$C,D52,資料!$I:$I,"2013",資料!$J:$J,"4",資料!$O:$O,"V") -> 0 | K52: =COUNTIFS(資料!$C:$C,D52,資料!$I:$I,"2013",資料!$J:$J,"4") -> 0 | L52: =J52/AVERAGE(E52,F52) -> 0 | M52: =K52/AVERAGE(E52,F52) -> 0 | N52: =(G52+K52)/AVERAGE(E52,F52) -> 0
D53: 金馬站 | E53: 4 | F53: 4 | G53: =COUNTIFS(資料!$C:$C,D53,資料!$G:$G,"2013",資料!$H:$H,"4") -> 0 | J53: =COUNTIFS(資料!$C:$C,D53,資料!$I:$I,"2013",資料!$J:$J,"4",資料!$O:$O,"V") -> 0 | K53: =COUNTIFS(資料!$C:$C,D53,資料!$I:$I,"2013",資料!$J:$J,"4") -> 0 | L53: =J53/AVERAGE(E53,F53) -> 0 | M53: =K53/AVERAGE(E53,F53) -> 0 | N53: =(G53+K53)/AVERAGE(E53,F53) -> 0
D54: 和美站 | E54: 5 | F54: 5 | G54: =COUNTIFS(資料!$C:$C,D54,資料!$G:$G,"2013",資料!$H:$H,"4") -> 0 | J54: =COUNTIFS(資料!$C:$C,D54,資料!$I:$I,"2013",資料!$J:$J,"4",資料!$O:$O,"V") -> 0 | K54: =COUNTIFS(資料!$C:$C,D54,資料!$I:$I,"2013",資料!$J:$J,"4") -> 0 | L54: =J54/AVERAGE(E54,F54) -> 0 | M54: =K54/AVERAGE(E54,F54) -> 0 | N54: =(G54+K54)/AVERAGE(E54,F54) -> 0
D55: 員林站 | E55: 11 | F55: 10 | G55: =COUNTIFS(資料!$C:$C,D55,資料!$G:$G,"2013",資料!$H:$H,"4") -> 0 | J55: =COUNTIFS(資料!$C:$C,D55,資料!$I:$I,"2013",資料!$J:$J,"4",資料!$O:$O,"V") -> 0 | K55: 1 | L55: =J55/AVERAGE(E55,F55) -> 0 | M55: =K55/AVERAGE(E55,F55) -> 0.095238095 | N55: =(G55+K55)/AVERAGE(E55,F55) -> 0.095238095
D56: 員林三信站 | E56: 4 | F56: 5 | G56: =COUNTIFS(資料!$C:$C,D56,資料!$G:$G,"2013",資料!$H:$H,"4") -> 1 | J56: =COUNTIFS(資料!$C:$C,D56,資料!$I:$I,"2013",資料!$J:$J,"4",資料!$O:$O,"V") -> 0 | K56: 0 | L56: =J56/AVERAGE(E56,F56) -> 0 | M56: =K56/AVERAGE(E56,F56) -> 0 | N56: =(G56+K56)/AVERAGE(E56,F56) -> 0.22222222
D57: 大明站 | E57: 2 | F57: 2 | G57: =COUNTIFS(資料!$C:$C,D57,資料!$G:$G,"2013",資料!$H:$H,"4") -> 0 | J57: =COUNTIFS(資料!$C:$C,D57,資料!$I:$I,"2013",資料!$J:$J,"4",資料!$O:$O,"V") -> 0 | K57: =COUNTIFS(資料!$C:$C,D57,資料!$I:$I,"2013",資料!$J:$J,"4") -> 0 | L57: =J57/AVERAGE(E57,F57) -> 0 | M57: =K57/AVERAGE(E57,F57) -> 0 | N57: =(G57+K57)/AVERAGE(E57,F57) -> 0
D58: 大里站 | E58: 5 | F58: 5 | G58: =COUNTIFS(資料!$C:$C,D58,資料!$G:$G,"2013",資料!$H:$H,"4") -> 0 | J58: =COUNTIFS(資料!$C:$C,D58,資料!$I:$I,"2013",資料!$J:$J,"4",資料!$O:$O,"V") -> 0 | K58: =COUNTIFS(資料!$C:$C,D58,資料!$I:$I,"2013",資料!$J:$J,"4") -> 0 | L58: =J58/AVERAGE(E58,F58) -> 0 | M58: =K58/AVERAGE(E58,F58) -> 0 | N58: =(G58+K58)/AVERAGE(E58,F58) -> 0
D59: 台中水湳站 | E59: 4 | F59: 4 | G59: =COUNTIFS(資料!$C:$C,D59,資料!$G:$G,"2013",資料!$H:$H,"4") -> 0 | J59: =COUNTIFS(資料!$C:$C,D59,資料!$I:$I,"2013",資料!$J:$J,"4",資料!$O:$O,"V") -> 0 | K59: =COUNTIFS(資料!$C:$C,D59,資料!$I:$I,"2013",資料!$J:$J,"4") -> 0 | L59: =J59/AVERAGE(E59,F59) -> 0 | M59: =K59/AVERAGE(E59,F59) -> 0 | N59: =(G59+K59)/AVERAGE(E59,F59) -> 0
B60: 南區營運中心 | D60: 斗六保長站 | E60: 11 | F60: 11 | G60: =COUNTIFS(資料!$C:$C,D60,資料!$G:$G,"2013",資料!$H:$H,"4") -> 0 | J60: =COUNTIFS(資料!$C:$C,D60,資料!$I:$I,"2013",資料!$J:$J,"4",資料!$O:$O,"V") -> 0 | K60: =COUNTIFS(資料!$C:$C,D60,資料!$I:$I,"2013",資料!$J:$J,"4") -> 0 | L60: =J60/AVERAGE(E60,F60) -> 0 | M60: =K60/AVERAGE(E60,F60) -> 0 | N60: =(G60+K60)/AVERAGE(E60,F60) -> 0
D61: 台南站 | E61: 7 | F61: 8 | G61: =COUNTIFS(資料!$C:$C,D61,資料!$G:$G,"2013",資料!$H:$H,"4") -> 2 | J61: =COUNTIFS(資料!$C:$C,D61,資料!$I:$I,"2013",資料!$J:$J,"4",資料!$O:$O,"V") -> 1 | K61: =COUNTIFS(資料!$C:$C,D61,資料!$I:$I,"2013",資料!$J:$J,"4") -> 1 | L61: =J61/AVERAGE(E61,F61) -> 0.13333333 | M61: =K61/AVERAGE(E61,F61) -> 0.13333333 | N61: =(G61+K61)/AVERAGE(E61,F61) -> 0.4
A62: 國際事業處 | B62: =A62 -> 國際事業處 | D62: 國際事業處 | E62: 3 | F62: 4 | G62: =COUNTIFS(資料!$C:$C,B62,資料!$G:$G,"2013",資料!$H:$H,"4") -> 2 | J62: =COUNTIFS(資料!$C:$C,D62,資料!$I:$I,"2013",資料!$J:$J,"4",資料!$O:$O,"V") -> 0 | K62: =COUNTIFS(資料!$C:$C,B62,資料!$I:$I,"2013",資料!$J:$J,"4") -> 0 | L62: =J62/AVERAGE(E62,F62) -> 0 | M62: =K62/AVERAGE(E62,F62) -> 0 | N62: =(G62+K62)/AVERAGE(E62,F62) -> 0.57142857
A63: 再生處理處 | B63: 再生處理處 | D63: 再生-行政室 | E63: 5 | F63: 5 | G63: =COUNTIFS(資料!$C:$C,D63,資料!$G:$G,"2013",資料!$H:$H,"4") -> 0 | J63: =COUNTIFS(資料!$C:$C,D63,資料!$I:$I,"2013",資料!$J:$J,"4",資料!$O:$O,"V") -> 0 | K63: =COUNTIFS(資料!$C:$C,D63,資料!$I:$I,"2013",資料!$J:$J,"4") -> 0 | L63: =J63/AVERAGE(E63,F63) -> 0 | M63: =K63/AVERAGE(E63,F63) -> 0 | N63: =(G63+K63)/AVERAGE(E63,F63) -> 0
D64: 研發中心 | E64: 4 | F64: 4 | G64: =COUNTIFS(資料!$C:$C,D64,資料!$G:$G,"2013",資料!$H:$H,"4") -> 0 | J64: =COUNTIFS(資料!$C:$C,D64,資料!$I:$I,"2013",資料!$J:$J,"4",資料!$O:$O,"V") -> 0 | K64: =COUNTIFS(資料!$C:$C,D64,資料!$I:$I,"2013",資料!$J:$J,"4") -> 0 | L64: =J64/AVERAGE(E64,F64) -> 0 | M64: =K64/AVERAGE(E64,F64) -> 0 | N64: =(G64+K64)/AVERAGE(E64,F64) -> 0
D65: 分選課 | E65: 20 | F65: 21 | G65: =COUNTIFS(資料!$C:$C,D65,資料!$G:$G,"2013",資料!$H:$H,"4") -> 1 | J65: =COUNTIFS(資料!$C:$C,D65,資料!$I:$I,"2013",資料!$J:$J,"4",資料!$O:$O,"V") -> 0 | K65: =COUNTIFS(資料!$C:$C,D65,資料!$I:$I,"2013",資料!$J:$J,"4") -> 0 | L65: =J65/AVERAGE(E65,F65) -> 0 | M65: =K65/AVERAGE(E65,F65) -> 0 | N65: =(G65+K65)/AVERAGE(E65,F65) -> 0.048780488
D66: 處理課 | E66: 17 | F66: 17 | G66: =COUNTIFS(資料!$C:$C,D66,資料!$G:$G,"2013",資料!$H:$H,"4") -> 0 | J66: =COUNTIFS(資料!$C:$C,D66,資料!$I:$I,"2013",資料!$J:$J,"4",資料!$O:$O,"V") -> 0 | K66: =COUNTIFS(資料!$C:$C,D66,資料!$I:$I,"2013",資料!$J:$J,"4") -> 0 | L66: =J66/AVERAGE(E66,F66) -> 0 | M66: =K66/AVERAGE(E66,F66) -> 0 | N66: =(G66+K66)/AVERAGE(E66,F66) -> 0
D67: 造粒課 | E67: 9 | F67: 9 | G67: =COUNTIFS(資料!$C:$C,D67,資料!$G:$G,"2013",資料!$H:$H,"4") -> 0 | J67: =COUNTIFS(資料!$C:$C,D67,資料!$I:$I,"2013",資料!$J:$J,"4",資料!$O:$O,"V") -> 0 | K67: =COUNTIFS(資料!$C:$C,D67,資料!$I:$I,"2013",資料!$J:$J,"4") -> 0 | L67: =J67/AVERAGE(E67,F67) -> 0 | M67: =K67/AVERAGE(E67,F67) -> 0 | N67: =(G67+K67)/AVERAGE(E67,F67) -> 0
D68: 喬翔分選課 | E68: 8 | F68: 9 | G68: =COUNTIFS(資料!$C:$C,D68,資料!$G:$G,"2013",資料!$H:$H,"4") -> 6 | J68: =COUNTIFS(資料!$C:$C,D68,資料!$I:$I,"2013",資料!$J:$J,"4",資料!$O:$O,"V") -> 3 | K68: =COUNTIFS(資料!$C:$C,D68,資料!$I:$I,"2013",資料!$J:$J,"4") -> 3 | L68: =J68/AVERAGE(E68,F68) -> 0.35294118 | M68: =K68/AVERAGE(E68,F68) -> 0.35294118 | N68: =(G68+K68)/AVERAGE(E68,F68) -> 1.0588235
A69: 便利通路事業處 | B69: =A69 -> 便利通路事業處 | D69: =B69 -> 便利通路事業處 | E69: 9 | F69: 9 | G69: =COUNTIFS(資料!$C:$C,B69,資料!$G:$G,"2013",資料!$H:$H,"4") -> 0 | J69: =COUNTIFS(資料!$C:$C,D69,資料!$I:$I,"2013",資料!$J:$J,"4",資料!$O:$O,"V") -> 0 | K69: =COUNTIFS(資料!$C:$C,D69,資料!$I:$I,"2013",資料!$J:$J,"4") -> 0 | L69: =J69/AVERAGE(E69,F69) -> 0 | M69: =K69/AVERAGE(E69,F69) -> 0 | N69: =(G69+K69)/AVERAGE(E69,F69) -> 0
A70: 合計 | E70: =SUM(E6:E69) -> 411 | F70: =SUM(F6:F69) -> 420 | G70: =SUM(G6:G69) -> 29 | H70: =SUM(H6:H69) -> 1 | I70: =SUM(I6:I69) -> 1 | J70: =SUM(J6:J69) -> 16 | K70: =SUM(K6:K69) -> 19 | L70: =AVERAGE(L6:L69) -> 0.0515401 | M70: =AVERAGE(M6:M69) -> 0.061140714 | N70: =AVERAGE(N6:N69) -> 0.21364927

Sheet 到職
B1: 部門 | C1: 工號 | D1: 姓名 | E1: 職位 | F1: 到職日 | G1: 勞健保 | H1: 備註
B2: 網管工程課 | C2: 04303 | D2: 蔡孟儒 | E2: 工程師 | F2: 45663 | G2: 01/06加保
B3: 中區業務一課(金馬站) | C3: 04304 | D3: 邱滿堂 | E3: 作業員 | F3: 45659 | G3: 01/02加保
B4: 中區業務一課(中三) | C4: 04305 | D4: 高博文 | E4: 拖車司機 | F4: 45672 | G4: 01/15加保
B6: 加盟部 | C6: 04306 | D6: 滕芸 | E6: 管理師 | F6: 45691 | G6: 2/3加保 | H6: 加保於青心
B7: 行銷部 | C7: 04307 | D7: 許湘琦 | E7: 副管理師 | F7: 2025/2/3 | G7: 2/3加保
B8: 財務部 | C8: 04310 | D8: 謝旻哲 | E8: 工讀生 | F8: 45691 | G8: 2/3加保
B9: 廢車客服課 | C9: 04308 | D9: 劉思欣 | E9: 助理管理師 | F9: 45693 | G9: 2/5加保
B10: 廢車客服課 | C10: 04309 | D10: 李品慈 | E10: 助理管理師 | F10: 45693 | G10: 2/5加保
B11: 企業客服課 | C11: 04311 | D11: 蘇子堯 | E11: 助理管理師 | F11: 45698 | G11: 2/10加保
B12: 人資課 | C12: 04312 | D12: 陳資蓉 | E12: 副管理師 | F12: 45705 | G12: 2/17加保
B13: 全興造粒課 | C13: 04313 | D13: 王士駿 | E13: 外場人員 | F13: 45705 | G13: 2/17加保
B14: 南區業務一課 | C14: 04314 | D14: 田瑋群 | E14: 夾子車司機 | F14: 45705 | G14: 2/17加保
B15: 全興造粒課 | C15: 04315 | D15: 書帕差 | E15: 移工 | F15: 45712 | G15: 2/24加保
B17: 草屯站 | C17: 04322 | D17: 陳繼華 | E17: 顧問 | F17: 45717 | G17: 3/1加保
B18: 營運部 | C18: 04316 | D18: 林庭鋐 | E18: 管理師 | F18: 45719 | G18: 3/3加保
B19: 北區業務三課 | C19: 04318 | D19: 江柏寰 | E19: 工讀生 | F19: 45719 | G19: 3/3加保
B20: 中區業務一課(沙鹿倉) | C20: 04320 | D20: 王子珉 | E20: 儲備夾子車司機 | F20: 45721 | G20: 3/5加保
... B25: 南區業務一課 | C25: 04324 | D25: 林于翔 | E25: 夾子車司機 | F25: 45728 | G25: 3/12加保
B26: 全興處理一課 | C26: 04325 | D26: 書拉財 | E26: 移工 | F26: 45733 | G26: 3/16加保 | H26: 3/16入境，3/17上班
B27: 員林站 | C27: 04326 | D27: 詹偉賢 | E27: 外場人員 | F27: 45735 | G27: 3/19加保
B28: 北區業務一課 | C28: 04327 | D28: 陳基展 | E28: 作業員(駐博智電子) | F28: 45740 | G28: 3/24加保
B29: 和美站 | C29: 04328 | D29: 張鴻祥 | E29: 拖車司機 | F29: 45740 | G29: 3/24加保
B31: 拆除工程課 | C31: 04330 | D31: 陳俊緯 | E31: 夾子車司機 | F31: 45754 | G31: 4/7加保
B32: 神岡站 | C32: 04331 | D32: 林縉佑 | E32: 儲備拖車司機 | F32: 45754 | G32: 4/7加保
B33: 南區業務一課 | C33: 04332 | D33: 李世昌 | E33: 儲備夾子車司機 | F33: 45754 | G33: 4/7加保
B34: 法務及環安課 | C34: 04329 | D34: 陳俊成 | E34: 管理師 | F34: 45755 | G34: 4/8加保
B35: 北區業務一課 | C35: 04333 | D35: 呂鵬 | E35: 3.5T小車司機 | F35: 45763 | G35: 4/16加保
B36: 金馬站 | C36: 04334 | D36: 鄭錫堯 | E36: 3.5T小車司機 | F36: 45770 | G36: 4/23加保
B37: 北區業務三課 | C37: 04335 | D37: 許正學 | E37: 作業員(晚班) | F37: 45771 | G37: 4/24加保
B39: 北區業務二課 | D39: 葉科旻 | E39: 作業員 | F39: 45782 | G39: 5/5加保 | H39: 加保 3合1、團保
B40: 北區業務二課 | C40: 04336 | D40: 鍾雲青 | E40: 作業員 | F40: 45782 | G40: 5/5加保
B41: 全興處理二課 | C41: 04337 | D41: 薩拉育 | E41: 移工 | F41: 2025/5/5 (5/4入境) | G41: 5/4加保
B42: 神岡站 | C42: 04338 | D42: 陳建勳 | E42: 拖車司機 | F42: 45782 | G42: 5/5加保
B43: 全興處理二課 | C43: 04339 | D43: 納他吳 | E43: 移工 | F43: 45789 | G43: 5/11加保
B44: 中區業務一課 | C44: 04340 | D44: 黃培源 | E44: 作業員(駐矽品中山) | F44: 45796 | G44: 5/19加保
B45: 北區業務二課 | C45: 04341 | D45: 江盛州 | E45: 作業員(駐廠矽品) | F45: 45796 | G45: 5/19加保
B46: 全興造粒課 | C46: 04342 | D46: 班查 | E46: 移工 | F46: 45799 | G46: 5/22加保
B47: 南區業務一課 | C47: 04343 | D47: 方亞庭 | E47: 副管理師(駐美光) | F47: 45803 | G47: 5/26加保
B48: 中區業務一課 | C48: 04344 | D48: 張永興 | E48: 作業員(駐矽品大豐) | F48: 45803 | G48: 5/26加保
B49: 中區業務一課 | C49: 04345 | D49: 張慧君 | E49: 作業員(駐矽品大豐) | F49: 45803 | G49: 5/26加保
B50: 中區業務一課 | C50: 04346 | D50: 何政風 | E50: 拖車司機 | F50: 45803 | G50: 5/26加保
B52: 員林站 | C52: 04349 | D52: 鄭志勝 | E52: 外場人員 | F52: 45810 | G52: 6/2加保
B53: 國際事業部業務課 | C53: 04347 | D53: 陳睿婕 | E53: 業務高級專員 | F53: 45810 | G53: 6/2加保
B54: 北區業務三課 | C54: 04348 | D54: 侯兆謙 | E54: 副管理師 | F54: 45813 | G54: 6/5加保
... B78: 南區業務一課 | C78: 04372 | D78: 賴疆允 | E78: 夾子車司機 | F78: 45859 | G78: 7/21加保
B80: 國際部業務課 | C80: 04376 | D80: Theo. Mavros | E80: 業務高級專員 | F80: 45883 | H80: 尚未收到任何資料
B81: 行銷部 | C81: 04373 | D81: 楊淳羽 | E81: 高級管理師 | F81: 45873 | G81: 8/4加保
B82: 總經理室 | C82: 04374 | D82: 李香儂 | E82: 管理師 | F82: 45873 | G82: 8/4加保
B83: 總經理室 | C83: 04375 | D83: 林慎彥 | E83: 高級管理師 | F83: 45873 | G83: 8/4加保
B84: 企業客服課 | C84: 04377 | D84: 陳威錡 | E84: 工讀生 | F84: 45873 | G84: 8/4加保
B85: 中區業務一課 | C85: 04378 | D85: 林廣銘 | E85: 作業員(駐竹南京元) | F85: 45873 | G85: 8/4加保
B86: 中區業務一課 | C86: 04379 | D86: 傅文吉 | E86: 作業員(駐中山矽品) | F86: 45873 | G86: 8/4加保
B87: 中區業務一課 | C87: 04380 | D87: 林品如 | E87: 作業員 | F87: 45873 | G87: 8/4加保
B88: 南區業務二課 | C88: 04381 | D88: 李全再 | E88: 夾子車司機 | F88: 45873 | G88: 8/4加保
B89: 南區業務一課 | C89: 04382 | D89: 潘偉誌 | E89: 夾子車司機 | F89: 45873 | G89: 8/4加保
B90: 新竹站 | C90: 04383 | D90: 詹益煥 | E90: 3.5頓司機 | F90: 45873 | G90: 8/4加保
B91: 北區業務一課 | C91: 04384 | D91: 黃聖媛 | E91: 專員 | F91: 45880 | G91: 8/11加保
B92: 南區業務二課 | C92: 04386 | D92: 黃善德 | E92: 作業員 | F92: 45880 | G92: 8/11加保
... B104: 南區業務二課 | C104: 04398 | D104: 陳宏憲 | E104: 夾子車司機 | F104: 45915 | G104: 9/15加保
B105: 國際部業務課 | C105: 04392 | D105: Yogesh Kumar | E105: 專案襄理 | F105: 45917 | G105: 9/17加保 | I105: 姓氏：Kumar、名：Yogesh
B106: 中區業務一課 | C106: 04400 | D106: 張皓盛 | E106: 夾子車司機 | F106: 45922 | G106: 9/22加保
B107: 國際事業部 | C107: 04391 | D107: 林妤庭 | E107: 副理 | F107: 45901 | G107: 9/1加保
B108: 廢車客服課 | C108: 03350 | D108: 李湘蘋 | E108: 助理管理師 | F108: 45911 | G108: 9/11加保
B110: 中區業務一課 | C110: 04401 | D110: 許竣捷 | E110: 儲備夾子車司機 | F110: 45931 | G110: 10/1加保
B111: 五股分選課 | C111: 04402 | D111: 簡士峰 | E111: 作業員 | F111: 45931 | G111: 10/1加保
B112: 企業客服課 | C112: 04403 | D112: 邱冠霖 | E112: 工讀生 | F112: 45931 | G112: 10/1加保
B113: 企業客服課 | C113: 04404 | D113: 胡欣柔 | E113: 工讀生 | F113: 45931 | G113: 10/1加保
B114: 拆除工程課 | C114: 04405 | D114: 陳震宏 | E114: 夾子車司機 | F114: 45938 | G114: 10/8加保
B115: 南區業務二課 | C115: 04406 | D115: 張玉峰 | E115: 作業員 | F115: 45938 | G115: 10/8加保
B116: 中區業務一課 | C116: 04407 | D116: 林國勳 | E116: 作業員(駐竹南京元) | F116: 45938 | G116: 10/8加保
B117: 中區業務一課 | C117: 04399 | D117: 王雅姿 | E117: 倉儲物流專員 | F117: 45943 | G117: 10/13加保
B118: 企業客服課 | C118: 04409 | D118: 蔡亞伸 | E118: 工讀生 | F118: 45943 | G118: 10/13加保
... B127: 北區業務二課 | C127: 04417 | D127: 羅士瑋 | E127: 作業員 | F127: 45966 | G127: 11/5加保
B128: 南區業務二課 | C128: 04418 | D128: 施宏霖 | E128: 作業員 | F128: 2025/11/10 | G128: 11/10加保
B129: 全興造粒課 | C129: 04419 | D129: 李豐舟 | E129: 外場人員 | F129: 45974 | G129: 11/13加保
B130: 再生紡織設計部 | C130: 04414 | D130: Putri Sonia | E130: 管理師 | F130: 45981 | G130: 11/20加保
B132: 中區業務一課 | C132: 04420 | D132: 官協志 | E132: 壓縮車司機 | F132: 45994 | G132: 12/3加保
B133: 管理課 | C133: 04421 | D133: 韓俊龍 | E133: 副管理師 | F133: 46013 | G133: 12/22加保
B134: 南區業務二課 | C134: 04422 | D134: 楊翠玉 | E134: 作業員 | F134: 46013 | G134: 12/22加保
B135: 人資課 | C135: 04423 | D135: 謝旻哲 | E135: 工讀生
B137: 總經理室 | C137: 04424 | D137: 周耕毅 | E137: 資深高級管理師 | F137: 46027 | G137: 1/5加保
B138: 企業客服課 | C138: 04425 | D138: 朱子癸 | E138: 工讀生 | F138: 46027 | G138: 1/5加保
B139: 北區業務二課 | C139: 04426 | D139: 龔盟方 | E139: 作業員 | F139: 46027 | G139: 1/5加保
B140: 南區業務一課 | C140: 04427 | D140: 陳威濟 | E140: 夾子車司機 | F140: 46027 | G140: 1/5加保
B141: 中區業務一課 | C141: 04428 | D141: 林裕盛 | E141: 作業員 | F141: 46027 | G141: 1/5加保
B142: 中區業務一課 | C142: 04429 | D142: 蔡佑祿 | E142: 夾子車司機 | F142: 46027 | G142: 1/5加保
B143: 南區業務二課 | C143: 04430 | D143: 陳信宏 | E143: 作業員 | F143: 46029 | G143: 1/7加保
B144: 南區業務一課 | C144: 04431 | D144: 郭俊岑 | E144: 夾子車司機 | F144: 46041 | G144: 1/19加保
B145: 五股分選課 | C145: 03911 | D145: 黃暄育 | E145: 工讀生 | F145: 46023 | G145: 1/1加保
B146: 廢車客服課 | C146: 03281 | D146: 陳靜姿 | E146: 助理管理師 | F146: 46036 | G146: 1/14加保
B147: 預計報到者 | D147: 姓名 | E147: 職位 | F147: 到職日 | G147: 駕照 | H147: 證照

Sheet checkin4月 
A1: 4月新進
A3: 序 | B3: 薪 | C3: 部門名稱 | D3: 工號 | E3: 姓名 | F3: 職位 | G3: 等 | H3: 穩 | I3: 投 | J3: 勞 | K3: 健 | L3: 職 | M3: 退 | N3: 銀 | O3: 類 | P3: 到職日 | Q3: 加保日 | R3: 備註
A4: 1 | C4: 拆除工程課 | D4: 04330 | E4: 陳俊緯 | F4: 夾子車司機 | P4: 45754 | Q4: 4/7加保
A5: 2 | C5: 神岡站 | D5: 04331 | E5: 林縉佑 | F5: 儲備拖車司機 | P5: 45754 | Q5: 4/7加保
A6: 3 | C6: 南區業務一課 | D6: 04332 | E6: 李世昌 | F6: 儲備夾子車司機 | P6: 45754 | Q6: 4/7加保
A7: 4 | C7: 法務及環安課 | D7: 04329 | E7: 陳俊成 | F7: 管理師 | P7: 45755 | Q7: 4/8加保
A8: 5 | C8: 北區業務三課 | D8: 04008 | E8: 葉衣琪 | F8: 助理會計 | P8: 45758 | Q8: 4/11富保
A9: 6 | C9: 北區業務一課 | D9: 04333 | E9: 呂鵬 | F9: 3.5T小車司機 | P9: 45763 | Q9: 4/16加保
A10: 7 | C10: 金馬站 | D10: 04334 | E10: 鄭錫堯 | F10: 3.5T小車司機 | P10: 45770 | Q10: 4/23加保
A11: 8 | C11: 北區業務三課 | D11: 04335 | E11: 許正學 | F11: 作業員(晚班) | P11: 45771 | Q11: 4/24加保

Sheet checkin1月
A1: 1 | B1: 月新進
A3: 序 | B3: 薪 | H3: 等 | I3: 穩 | J3: 投 | K3: 勞 | L3: 健 | M3: 職 | N3: 退 | O3: 銀 | P3: 類 | T3: B
A4: 1 | C4: 網管工程課 | D4: 04303 | E4: 蔡孟儒 | F4: 工程師 | Q4: 45663 | R4: 01/06加保
A5: 2 | C5: 中區業務一課 | D5: 04304 | E5: 邱滿堂 | F5: 作業員 | Q5: 45659 | R5: 01/02加保
A6: 3 | C6: 中區業務一課(中三) | D6: 04305 | E6: 高博文 | F6: 拖車司機 | Q6: 45672 | R6: 01/15加保
A7: 4
A8: 5
A9: 6
A10: 7
A11: 8
A12: 9
A13: 10
A14: 11
A15: 12
A16: 13
A17: 14
A18: 15
... A23: 20

Sheet 每月離職率
A1: 2013年每月員工人數及每月流動率
A2: 月份 | B2: 月初人數 | C2: 月底人數 | D2: 平均人數 | E2: 新進人數 | F2: 離職人數 | G2: 每月 流動率
A3: 1 | G3: =(F3+E3)/D3 -> #DIV/0!
A4: 2 | G4: =(F4+E4)/D4 -> #DIV/0!
A5: 3 | G5: =(F5+E5)/D5 -> #DIV/0!
A6: 4 | G6: =(F6+E6)/D6 -> #DIV/0!
A7: 5 | G7: =(F7+E7)/D7 -> #DIV/0!
A8: 6 | G8: =(F8+E8)/D8 -> #DIV/0!
A9: 7 | G9: =(F9+E9)/D9 -> #DIV/0!
A10: 8 | G10: =(F10+E10)/D10 -> #DIV/0!
A11: 9 | G11: =(F11+E11)/D11 -> #DIV/0!
A12: 10 | G12: =(F12+E12)/D12 -> #DIV/0!
A13: 11 | G13: =(F13+E13)/D13 -> #DIV/0!
A14: 12 | G14: =(F14+E14)/D14 -> #DIV/0!
G15: =AVERAGE(G3:G14) -> #DIV/0!
A20: 2012年每月員工人數及每月流動率
A21: 月份 | B21: 月初人數 | C21: 月底人數 | D21: 平均人數 | E21: 新進人數 | F21: 離職人數 | G21: 每月 流動率
A22: 1 | G22: =(F22+E22)/D22 -> #DIV/0!
A23: 2 | G23: =(F23+E23)/D23 -> #DIV/0!
A24: 3 | G24: =(F24+E24)/D24 -> #DIV/0!
A25: 4 | G25: =(F25+E25)/D25 -> #DIV/0!
A26: 5 | G26: =(F26+E26)/D26 -> #DIV/0!
A27: 6 | G27: =(F27+E27)/D27 -> #DIV/0!
A28: 7 | G28: =(F28+E28)/D28 -> #DIV/0!
A29: 8 | G29: =(F29+E29)/D29 -> #DIV/0!
A30: 9 | G30: =(F30+E30)/D30 -> #DIV/0!
A31: 10 | G31: =(F31+E31)/D31 -> #DIV/0!
A32: 11 | G32: =(F32+E32)/D32 -> #DIV/0!
A33: 12 | G33: =(F33+E33)/D33 -> #DIV/0!
G34: =AVERAGE(G22:G33) -> #DIV/0!

Sheet checkout1月
A1: 1 | B1: 月離職
A3: 序 | B3: 薪 | G3: 作 | H3: 特 | I3: 小時 | J3: 加
A4: 1 | C4: 南區業務一課 | D4: 03863 | E4: 蔡建傑 | F4: 儲備夾子車司機 | M4: 44748 | N4: 45663 | O4: 育嬰留停2025/01/06-2025/06/30
A5: 2 | C5: 中區業務三課 | D5: 03348 | E5: 卓巧宜 | F5: 副管理師 | M5: 43423 | N5: 45663 | O5: 育嬰留停2025/01/06-2025/07/31
A6: 3 | C6: 宏偉處理課 | D6: H0027 | E6: 胡國慶 | F6: 外場人員 | M6: 45635 | N6: 45659
A7: 4 | C7: 中區業務一課 | D7: 02603 | E7: 李武憲 | F7: 作業員 | M7: 42002 | N7: 45679
A8: 5 | C8: 南區業務一課 | D8: 03526 | E8: 張玲翔 | F8: 作業員 | M8: 43808 | N8: 45688
A9: 6 | C9: 全興造粒課 | D9: 04297 | E9: 黃鴻文 | F9: 外場人員 | M9: 45614 | N9: 45688 | O9: 資遣
A10: 7
A11: 8
A12: 9
A13: 10
A14: 11
A15: 12
A16: 13
A17: 14
A18: 15
A19: 16
A20: 17
A21: 18
... A26: 23

Sheet checkin2月
A1: 2 | B1: 月新進
A3: 序 | B3: 薪 | H3: 等 | I3: 穩 | J3: 投 | K3: 勞 | L3: 健 | M3: 職 | N3: 退 | O3: 銀 | P3: 類 | T3: B
A4: 1 | C4: 加盟部 | D4: 04306 | E4: 滕芸 | F4: 管理師 | Q4: 45691 | R4: 2/3加保 | S4: 加保於青心
A5: 2 | C5: 行銷部 | D5: 04307 | E5: 許湘琦 | F5: 副管理師 | Q5: 2025/2/3 | R5: 2/3加保
A6: 3 | C6: 財務部 | D6: 04310 | E6: 謝旻哲 | F6: 工讀生 | Q6: 45691 | R6: 2/3加保
A7: 4 | C7: 廢車客服課 | D7: 04308 | E7: 劉思欣 | F7: 助理管理師 | Q7: 45693 | R7: 2/5加保
A8: 5 | C8: 廢車客服課 | D8: 04309 | E8: 李品慈 | F8: 助理管理師 | Q8: 45693 | R8: 2/5加保
A9: 6 | C9: 企業客服課 | D9: 04311 | E9: 蘇子堯 | F9: 助理管理師 | Q9: 45698 | R9: 2/10加保
A10: 7 | C10: 人資課 | D10: 04312 | E10: 陳資蓉 | F10: 副管理師 | Q10: 45705 | R10: 2/17加保
A11: 8 | C11: 全興造粒課 | D11: 04313 | E11: 王士駿 | F11: 外場人員 | Q11: 45705 | R11: 2/17加保
A12: 9 | C12: 南區業務一課 | D12: 04314 | E12: 田瑋群 | F12: 夾子車司機 | Q12: 45705 | R12: 2/17加保
A13: 10 | C13: 全興造粒課 | D13: 04315 | E13: 書帕差 | F13: 移工 | Q13: 45712 | R13: 2/24加保
A14: 11
A15: 12
A16: 13
A17: 14
A18: 15
A19: 16
A20: 17
A21: 18
A22: 19
A23: 20

Sheet checkout 2月
A1: 2 | B1: 月離職
A3: 序 | B3: 薪 | G3: 作 | H3: 特 | I3: 小時 | J3: 加
A4: 1 | C4: 人資課 | D4: 04238 | E4: 劉以汝 | F4: 副管理師 | M4: 45474 | N4: 45691
A5: 2 | C5: 廢車客服課 | D5: 03377 | E5: 廖芷嵐 | F5: 助理管理師 | M5: 43480 | N5: 45693
A6: 3 | C6: 和美站 | D6: 02335 | E6: 蔡政德 | F6: 拖車司機 | M6: 41463 | N6: 45701
A7: 4 | C7: 中區業務一課 | D7: 04276 | E7: 劉羽程 | F7: 作業員 | M7: 45551 | N7: 45705
A8: 5 | C8: 管理課 | D8: 04182 | E8: 林佳瑩 | F8: 助理管理師 | M8: 45355 | N8: 45709
A9: 6 | C9: 北區業務三課 | D9: 03911 | E9: 黃暄育 | F9: 助理會計 | M9: 44858 | N9: 45688
A10: 7 | C10: 業務部行政管理課 | D10: 03017 | E10: 林玉婷 | F10: 專員 | M10: 42870 | N10: 45713
A11: 8 | C11: 北區業務二課 | D11: 03593 | E11: 鍾雲青 | F11: 班長 | M11: 44048 | N11: 45716
A12: 9 | C12: 北區業務二課 | D12: 03464 | E12: 蔡孟蓉 | F12: 分選員 | M12: 43682 | N12: 45716
A13: 10 | C13: 北區業務二課 | D13: 03591 | E13: 楊逸棋 | F13: 作業員 | M13: 44046 | N13: 45716
A14: 11 | C14: 財務部 | D14: 04310 | E14: 謝旻哲 | F14: 工讀生 | M14: 45691 | N14: 45716
A15: 12 | C15: 全興造粒課 | D15: 03915 | E15: 楊宗達 | F15: 班長 | M15: 44866 | N15: 45716
A16: 14
A17: 15
A18: 16
A19: 17
A20: 18
A21: 19
A22: 20
A23: 21
A24: 22
A25: 23

Sheet checkout 4月
A1: 4月離職
A3: 序 | B3: 薪 | C3: 部門名稱 | D3: 工號 | E3: 姓名 | F3: 職位 | G3: 作 | H3: 特 | I3: 小時 | J3: 加 | K3: 到職日 | L3: 離職日 | M3: 備註
A4: 1 | C4: 中區業務一課 | D4: 04305 | E4: 高博文 | F4: 拖車司機 | K4: 45672 | L4: 45751 | M4: 資遣
A5: 2 | C5: 全興處理二課 | D5: 03822 | E5: 阿恩 | F5: 移工 | K5: 44667 | L5: 45755 | M5: 4/8最後工作日，4/10離境退保(結算)
A6: 3 | C6: 和美站 | D6: 04328 | E6: 張鴻祥 | F6: 拖車司機 | K6: 45740 | L6: 45760 | M6: 退保日4/15
A7: 4 | C7: 法務及環安課 | D7: 04329 | E7: 陳俊成 | F7: 管理師 | K7: 45755 | L7: 45761
A8: 5 | C8: 家電客服課 | D8: 04015 | E8: 林金燕 | F8: 助理管理師 | K8: 44991 | L8: 45765
A9: 6 | C9: 法務及環安課 | D9: 03810 | E9: 蔡雅雯 | F9: 管理師 | K9: 44634 | L9: 45765 | M9: 4/19~10/18育嬰留停(4月薪資需補發2月因請假扣款的費用)
A10: 7 | C10: 青心-加盟課 | D10: 04306 | E10: 滕芸 | F10: 管理師 | K10: 45691 | L10: 45769 | M10: 資遣 5/2退保(薪資算到4/22)
A11: 8 | C11: 神岡站 | D11: 04331 | E11: 林縉佑 | F11: 儲備拖車司機 | K11: 45754 | L11: 45772
A12: 9 | C12: 員林站 | D12: 02683 | E12: 朱振隆 | F12: 外場人員 | K12: 42177 | L12: 45777
A13: 10 | C13: 全興造粒課 | D13: 02533 | E13: 彼查 | F13: 移工 | K13: 41834 | L13: 45777 | M13: 4/30最後工作日，5/3離境退保(結算)
A14: 11 | C14: 北區業務三課 | D14: 04258 | E14: 吳慧萍 | F14: 工讀生 | K14: 45516 | L14: 45777
A15: 12 | C15: 中區業務一課 | D15: 04266 | E15: 許新育 | F15: 3.5噸司機 | K15: 45530 | L15: 45777
A16: 13 | C16: 全興處理二課 | D16: 04137 | E16: 帕他拉功 | F16: 移工 | K16: 45187 | L16: 45777 | M16: 4/30最後工作日，5/6離境退保(結算)
A17: 14 | C17: 北區業務三課 | D17: 03961 | E17: 顏士婷 | F17: 班長 | K17: 44917 | L17: 45777

Sheet 離職
A1: EIP表單編碼 | B1: 月份 | C1: 部門 | D1: 工號 | E1: 姓名 | F1: 職稱 | G1: 到職日期 | H1: 離職日 | I1: 退保 | J1: 申請日期 | K1: 年 | L1: 月 | M1: 日 | N1: 天數 | O1: 服務年資 | P1: 細分類 | Q1: 詳細原因 | R1: 歸檔確認 | S1: 離職單 | T1: 離職證明 | U1: 薪資單 | V1: mail發出
A2: 114080001 | B2: 08月 | C2: 行銷部 | D2: 03321 | E2: 陳姿穎 | F2: 管理師 | G2: 43376 | H2: 45879 | I2: 8/10退保 | J2: 45821 | K2: =DATEDIF(G2,H2,"y") -> 6 | L2: =DATEDIF(G2,H2,"ym") -> 10 | M2: =DATEDIF(G2,H2,"MD") -> 7 | N2: =DATEDIF(G2,H2,"d") -> 2503 | O2: =IF(N2<=92,"3個月以下",IF(N2<=365,"3個月至1年",IF(N2<=1095,"1年至3年",IF(N2>1096,"3年以上")))) -> 3年以上 | P2: 個人問題 | R2: □已完成歸檔 □___月生效 □其他： | S2: OK | T2: 需要 | U2: 需要 | V2: 台中市西屯區市政北三路113號10樓之5
A3: 招募 | B3: 08月 | C3: 人資課 | D3: 04312 | E3: 陳資蓉 | F3: 副管理師 | G3: 45705 | H3: 45877 | I3: 8/8退保 | J3: 45846 | K3: =DATEDIF(G3,H3,"y") -> 0 | L3: =DATEDIF(G3,H3,"ym") -> 5 | M3: =DATEDIF(G3,H3,"MD") -> 22 | N3: =DATEDIF(G3,H3,"d") -> 172 | O3: =IF(N3<=92,"3個月以下",IF(N3<=365,"3個月至1年",IF(N3<=1095,"1年至3年",IF(N3>1096,"3年以上")))) -> 3個月至1年 | P3: 個人問題 | R3: □已完成歸檔 □___月生效 □其他： | S3: OK | T3: 需要，8/12寄 | U3: NO | V3: 台中市新社區協成里華豐三街60號
A4: 114080003 | B4: 08月 | C4: 草屯站 | D4: 00033 | E4: 李志仁 | F4: 主任 | G4: 37712 | H4: 45900 | I4: 9/1退保 | J4: 45870 | K4: =DATEDIF(G4,H4,"y") -> 22 | L4: =DATEDIF(G4,H4,"ym") -> 4 | M4: =DATEDIF(G4,H4,"MD") -> 30 | N4: =DATEDIF(G4,H4,"d") -> 8188 | O4: =IF(N4<=92,"3個月以下",IF(N4<=365,"3個月至1年",IF(N4<=1095,"1年至3年",IF(N4>1096,"3年以上")))) -> 3年以上 | P4: 資遣 | R4: □已完成歸檔 □___月生效 □其他： | S4: X | T4: 非自願OK
A5: 114080004 | B5: 08月 | C5: 五股分選課 | D5: 03538 | E5: 呂軍億 | F5: 組長 | G5: 43864 | H5: 45900 | I5: 9/1退保 | J5: 45874 | K5: =DATEDIF(G5,H5,"y") -> 5 | L5: =DATEDIF(G5,H5,"ym") -> 6 | M5: =DATEDIF(G5,H5,"MD") -> 28 | N5: =DATEDIF(G5,H5,"d") -> 2036 | O5: =IF(N5<=92,"3個月以下",IF(N5<=365,"3個月至1年",IF(N5<=1095,"1年至3年",IF(N5>1096,"3年以上")))) -> 3年以上 | P5: 個人問題 | R5: □已完成歸檔 □___月生效 □其他： | S5: OK | T5: 需要 | U5: 需要 | V5: 新北市八里區龍米路二段228-22號2樓
A6: 114080005 | B6: 08月 | C6: 中區業務一課 | D6: 04379 | E6: 傅文吉 | F6: 作業員 | G6: 45873 | H6: 45874 | I6: 8/6退保 | J6: 45875 | K6: =DATEDIF(G6,H6,"y") -> 0 | L6: =DATEDIF(G6,H6,"ym") -> 0 | M6: =DATEDIF(G6,H6,"MD") -> 1 | N6: =DATEDIF(G6,H6,"d") -> 1 | O6: =IF(N6<=92,"3個月以下",IF(N6<=365,"3個月至1年",IF(N6<=1095,"1年至3年",IF(N6>1096,"3年以上")))) -> 3個月以下 | P6: 個人問題 | R6: □已完成歸檔 □___月生效 □其他： | S6: OK | T6: NO | U6: NO
A7: 114080006 | B7: 08月 | C7: 中區業務一課 | D7: 04360 | E7: 楊琪伊 | F7: 物流專員 | G7: 45854 | H7: 45877 | I7: 8/8退保 | J7: 45877 | K7: =DATEDIF(G7,H7,"y") -> 0 | L7: =DATEDIF(G7,H7,"ym") -> 0 | M7: =DATEDIF(G7,H7,"MD") -> 23 | N7: =DATEDIF(G7,H7,"d") -> 23 | O7: =IF(N7<=92,"3個月以下",IF(N7<=365,"3個月至1年",IF(N7<=1095,"1年至3年",IF(N7>1096,"3年以上")))) -> 3個月以下 | P7: 個人問題 | Q7: 太長加班 | R7: □已完成歸檔 □___月生效 □其他： | S7: OK | T7: 需要 | U7: 需要 | V7: 台中市清水區港都路163號5樓之6
A8: 114080007 | B8: 08月 | C8: 軟體開發課 | D8: 04287 | E8: 陳鈺燻 | F8: 副工程師 | G8: 45586 | H8: 45879 | I8: 8/10退保 | J8: 45880 | K8: =DATEDIF(G8,H8,"y") -> 0 | L8: =DATEDIF(G8,H8,"ym") -> 9 | M8: =DATEDIF(G8,H8,"MD") -> 20 | N8: =DATEDIF(G8,H8,"d") -> 293 | O8: =IF(N8<=92,"3個月以下",IF(N8<=365,"3個月至1年",IF(N8<=1095,"1年至3年",IF(N8>1096,"3年以上")))) -> 3個月至1年 | P8: 資遣 | R8: □已完成歸檔 □___月生效 □其他： | S8: OK | T8: 非自願OK
A9: 114080008 | B9: 08月 | C9: 網管工程課 | D9: 03490 | E9: 石培瀚 | F9: 副工程師 | G9: 43724 | H9: 45878 | I9: 8/9退保 | J9: 45880 | K9: =DATEDIF(G9,H9,"y") -> 5 | L9: =DATEDIF(G9,H9,"ym") -> 10 | M9: =DATEDIF(G9,H9,"MD") -> 24 | N9: =DATEDIF(G9,H9,"d") -> 2154 | O9: =IF(N9<=92,"3個月以下",IF(N9<=365,"3個月至1年",IF(N9<=1095,"1年至3年",IF(N9>1096,"3年以上")))) -> 3年以上 | P9: 資遣 | R9: □已完成歸檔 □___月生效 □其他： | S9: OK | T9: 非自願OK
A10: 114080009 | B10: 08月 | C10: 五股分選課 | D10: 04387 | E10: 黃詔熙 | F10: 作業員 | G10: 45880 | H10: 45880 | I10: 8/11退保 | J10: 45880 | K10: =DATEDIF(G10,H10,"y") -> 0 | L10: =DATEDIF(G10,H10,"ym") -> 0 | M10: =DATEDIF(G10,H10,"MD") -> 0 | N10: =DATEDIF(G10,H10,"d") -> 0 | O10: =IF(N10<=92,"3個月以下",IF(N10<=365,"3個月至1年",IF(N10<=1095,"1年至3年",IF(N10>1096,"3年以上")))) -> 3個月以下 | P10: 個人問題 | R10: □已完成歸檔 □___月生效 □其他： | S10: OK | T10: NO | U10: NO
A11: 114080010 | B11: 08月 | C11: 中區業務一課 | D11: 04378 | E11: 林廣銘 | F11: 作業員 | G11: 45873 | H11: 45884 | I11: 8/15退保 | J11: 45881 | K11: =DATEDIF(G11,H11,"y") -> 0 | L11: =DATEDIF(G11,H11,"ym") -> 0 | M11: =DATEDIF(G11,H11,"MD") -> 11 | N11: =DATEDIF(G11,H11,"d") -> 11 | O11: =IF(N11<=92,"3個月以下",IF(N11<=365,"3個月至1年",IF(N11<=1095,"1年至3年",IF(N11>1096,"3年以上")))) -> 3個月以下 | P11: 個人問題 | R11: □已完成歸檔 □___月生效 □其他： | S11: OK | T11: NO | U11: NO
A12: 114080011 | B12: 08月 | C12: 業務課 | D12: 03335 | E12: 徐筠棋 | F12: 高級業務專員 | G12: 43405 | H12: 45892 | I12: 8/23退保 | J12: 45882 | K12: =DATEDIF(G12,H12,"y") -> 6 | L12: =DATEDIF(G12,H12,"ym") -> 9 | M12: =DATEDIF(G12,H12,"MD") -> 22 | N12: =DATEDIF(G12,H12,"d") -> 2487 | O12: =IF(N12<=92,"3個月以下",IF(N12<=365,"3個月至1年",IF(N12<=1095,"1年至3年",IF(N12>1096,"3年以上")))) -> 3年以上 | P12: 資遣 | R12: □已完成歸檔 □___月生效 □其他： | S12: X
A13: 114080012 | B13: 08月 | C13: 南區業務二課 | D13: 04381 | E13: 李全再 | F13: 夾子車司機 | G13: 45873 | H13: 45884 | I13: 8/15退保 | J13: 45884 | K13: =DATEDIF(G13,H13,"y") -> 0 | L13: =DATEDIF(G13,H13,"ym") -> 0 | M13: =DATEDIF(G13,H13,"MD") -> 11 | N13: =DATEDIF(G13,H13,"d") -> 11 | O13: =IF(N13<=92,"3個月以下",IF(N13<=365,"3個月至1年",IF(N13<=1095,"1年至3年",IF(N13>1096,"3年以上")))) -> 3個月以下 | P13: 身體因素 | R13: □已完成歸檔 □___月生效 □其他： | S13: OK | T13: 需要 | U13: 需要 | V13: 高雄市小港區孔宅里孔宅街4號
A14: 114080013 | B14: 08月 | C14: 中區業務一課 | D14: 04380 | E14: 林品如 | F14: 作業員 | G14: 45873 | H14: 45884 | I14: 8/15退保 | J14: 45884 | K14: =DATEDIF(G14,H14,"y") -> 0 | L14: =DATEDIF(G14,H14,"ym") -> 0 | M14: =DATEDIF(G14,H14,"MD") -> 11 | N14: =DATEDIF(G14,H14,"d") -> 11 | O14: =IF(N14<=92,"3個月以下",IF(N14<=365,"3個月至1年",IF(N14<=1095,"1年至3年",IF(N14>1096,"3年以上")))) -> 3個月以下 | P14: 個人問題 | R14: □已完成歸檔 □___月生效 □其他： | S14: OK | T14: NO | U14: 需要 連同體檢報告一起寄回 | V14: 台中市清水區橋頭里民有路260巷2號
A15: 114080014 | B15: 08月 | C15: 中區業務一課 | D15: 04346 | E15: 何政風 | F15: 拖車司機 | G15: 45803 | H15: 45897 | I15: 8/28退保 | J15: 45888 | K15: =DATEDIF(G15,H15,"y") -> 0 | L15: =DATEDIF(G15,H15,"ym") -> 3 | M15: =DATEDIF(G15,H15,"MD") -> 2 | N15: =DATEDIF(G15,H15,"d") -> 94 | O15: =IF(N15<=92,"3個月以下",IF(N15<=365,"3個月至1年",IF(N15<=1095,"1年至3年",IF(N15>1096,"3年以上")))) -> 3個月至1年 | P15: 資遣 | R15: □已完成歸檔 □___月生效 □其他： | S15: X
A16: 114080015 | B16: 08月 | C16: 中區業務一課 | D16: 04355 | E16: 彭志翔 | F16: 作業員 | G16: 45826 | H16: 45898 | I16: 8/29退保 | J16: 45889 | K16: =DATEDIF(G16,H16,"y") -> 0 | L16: =DATEDIF(G16,H16,"ym") -> 2 | M16: =DATEDIF(G16,H16,"MD") -> 11 | N16: =DATEDIF(G16,H16,"d") -> 72 | O16: =IF(N16<=92,"3個月以下",IF(N16<=365,"3個月至1年",IF(N16<=1095,"1年至3年",IF(N16>1096,"3年以上")))) -> 3個月以下 | P16: 資遣 | R16: □已完成歸檔 □___月生效 □其他： | S16: X
A17: 114080016 | B17: 08月 | C17: 南區業務一課 | D17: 04070 | E17: 陳賢鈺 | F17: 夾子車司機 | G17: 45054 | H17: 45891 | I17: 8/22退保 | J17: 45889 | K17: =DATEDIF(G17,H17,"y") -> 2 | L17: =DATEDIF(G17,H17,"ym") -> 3 | M17: =DATEDIF(G17,H17,"MD") -> 14 | N17: =DATEDIF(G17,H17,"d") -> 837 | O17: =IF(N17<=92,"3個月以下",IF(N17<=365,"3個月至1年",IF(N17<=1095,"1年至3年",IF(N17>1096,"3年以上")))) -> 1年至3年 | P17: 身體因素 | R17: □已完成歸檔 □___月生效 □其他： | S17: OK | T17: 需要 | U17: 需要 | V17: 台南市安定區港口里港口241-12號
A18: 114080017 | B18: 08月 | C18: 南區業務一課 | D18: 04389 | E18: 黃瑞堂 | F18: 作業員 | G18: 45889 | H18: 45890 | I18: 8/21退保 | J18: 45890 | K18: =DATEDIF(G18,H18,"y") -> 0 | L18: =DATEDIF(G18,H18,"ym") -> 0 | M18: =DATEDIF(G18,H18,"MD") -> 1 | N18: =DATEDIF(G18,H18,"d") -> 1 | O18: =IF(N18<=92,"3個月以下",IF(N18<=365,"3個月至1年",IF(N18<=1095,"1年至3年",IF(N18>1096,"3年以上")))) -> 3個月以下 | P18: 個人問題 | R18: □已完成歸檔 □___月生效 □其他： | S18: OK | T18: NO | U18: NO
A19: 114080018 | B19: 08月 | C19: 員林站 | D19: 04349 | E19: 鄭志勝 | F19: 外場人員 | G19: 45810 | H19: 45896 | I19: 8/27退保 | J19: 45891 | K19: =DATEDIF(G19,H19,"y") -> 0 | L19: =DATEDIF(G19,H19,"ym") -> 2 | M19: =DATEDIF(G19,H19,"MD") -> 25 | N19: =DATEDIF(G19,H19,"d") -> 86 | O19: =IF(N19<=92,"3個月以下",IF(N19<=365,"3個月至1年",IF(N19<=1095,"1年至3年",IF(N19>1096,"3年以上")))) -> 3個月以下 | P19: 個人問題 | Q19: 原訂8/31離職,因身體因素調整離職日為8/27 | R19: □已完成歸檔 □___月生效 □其他： | S19: OK | T19: 需要 | U19: 需要 | V19: 彰化縣二水鄉合興村英義路32號
A20: 114080019 | B20: 08月 | C20: 北區業務二課 | D20: 03555 | E20: 劉春保 | F20: 作業員 | G20: 43906 | H20: 45900 | J20: 45895 | K20: =DATEDIF(G20,H20,"y") -> 5 | L20: =DATEDIF(G20,H20,"ym") -> 5 | M20: =DATEDIF(G20,H20,"MD") -> 15 | N20: =DATEDIF(G20,H20,"d") -> 1994 | O20: =IF(N20<=92,"3個月以下",IF(N20<=365,"3個月至1年",IF(N20<=1095,"1年至3年",IF(N20>1096,"3年以上")))) -> 3年以上 | P20: 家庭因素 | R20: □已完成歸檔 □___月生效 □其他： | S20: OK | T20: NO | U20: 需要 | V20: 新竹縣竹北市福德里18鄰三民路494巷1號
A21: 114080020 | B21: 08月 | C21: 再生紡織設計部 | D21: 04259 | E21: 趙建豪 | F21: 高級工程師 | G21: 45516 | H21: 45900 | I21: 9/1退保 | J21: 45897 | K21: =DATEDIF(G21,H21,"y") -> 1 | L21: =DATEDIF(G21,H21,"ym") -> 0 | M21: =DATEDIF(G21,H21,"MD") -> 19 | N21: =DATEDIF(G21,H21,"d") -> 384 | O21: =IF(N21<=92,"3個月以下",IF(N21<=365,"3個月至1年",IF(N21<=1095,"1年至3年",IF(N21>1096,"3年以上")))) -> 1年至3年 | P21: 資遣 | R21: □已完成歸檔 □___月生效 □其他： | S21: X | T21: 需要 | U21: 需要 | V21: 台中市北區漢口路三段78號4F之7
A22: 114080021 | B22: 08月 | C22: 企業客服課 | D22: 04377 | E22: 陳威錡 | F22: 工讀生 | G22: 45873 | H22: 45900 | I22: 9/1退保 | J22: 45898 | K22: =DATEDIF(G22,H22,"y") -> 0 | L22: =DATEDIF(G22,H22,"ym") -> 0 | M22: =DATEDIF(G22,H22,"MD") -> 27 | N22: =DATEDIF(G22,H22,"d") -> 27 | O22: =IF(N22<=92,"3個月以下",IF(N22<=365,"3個月至1年",IF(N22<=1095,"1年至3年",IF(N22>1096,"3年以上")))) -> 3個月以下 | P22: 個人問題 | Q22: 學校開學 | R22: □已完成歸檔 □___月生效 □其他： | T22: NO | U22: NO
A23: 114080022 | B23: 08月 | C23: 企業客服課 | D23: 04362 | E23: 車延信 | F23: 工讀生 | G23: 45847 | H23: 45900 | I23: 9/1退保 | J23: 45898 | K23: =DATEDIF(G23,H23,"y") -> 0 | L23: =DATEDIF(G23,H23,"ym") -> 1 | M23: =DATEDIF(G23,H23,"MD") -> 22 | N23: =DATEDIF(G23,H23,"d") -> 53 | O23: =IF(N23<=92,"3個月以下",IF(N23<=365,"3個月至1年",IF(N23<=1095,"1年至3年",IF(N23>1096,"3年以上")))) -> 3個月以下 | P23: 個人問題 | Q23: 學校開學 | R23: □已完成歸檔 □___月生效 □其他： | T23: NO | U23: NO
A24: 114080023 | B24: 08月 | C24: 中區業務一課 | D24: 03700 | E24: 吳思維 | F24: 拖車司機 | G24: 44396 | H24: 45900 | J24: 45903 | K24: =DATEDIF(G24,H24,"y") -> 4 | L24: =DATEDIF(G24,H24,"ym") -> 1 | M24: =DATEDIF(G24,H24,"MD") -> 12 | N24: =DATEDIF(G24,H24,"d") -> 1504 | O24: =IF(N24<=92,"3個月以下",IF(N24<=365,"3個月至1年",IF(N24<=1095,"1年至3年",IF(N24>1096,"3年以上")))) -> 3年以上 | P24: 育嬰留停 | Q24: 留停期間9/1~9/30 | R24: □已完成歸檔 □___月生效 □其他：
A26: 114090001 | B26: 09月 | C26: 五股分選課 | D26: 04008 | E26: 葉衣琪 | F26: 助理會計 | G26: 44977 | H26: 45915 | I26: 9/15退保 | J26: 45884 | K26: =DATEDIF(G26,H26,"y") -> 2 | L26: =DATEDIF(G26,H26,"ym") -> 6 | M26: =DATEDIF(G26,H26,"MD") -> 26 | N26: =DATEDIF(G26,H26,"d") -> 938 | O26: =IF(N26<=92,"3個月以下",IF(N26<=365,"3個月至1年",IF(N26<=1095,"1年至3年",IF(N26>1096,"3年以上")))) -> 1年至3年 | P26: 家庭因素 | Q26: 原訂9/30離職,個人因素調整為9/15 | R26: □已完成歸檔 □___月生效 □其他： | S26: V | T26: V | U26: V | V26: 新北市蘆洲區中正路174巷36號4樓
A27: 114090002 | B27: 09月 | C27: 企業客服課 | D27: 04361 | E27: 謝榮家 | F27: 工讀生 | G27: 45847 | H27: 45905 | I27: 9/5退保 | J27: 45897 | K27: =DATEDIF(G27,H27,"y") -> 0 | L27: =DATEDIF(G27,H27,"ym") -> 1 | M27: =DATEDIF(G27,H27,"MD") -> 27 | N27: =DATEDIF(G27,H27,"d") -> 58 | O27: =IF(N27<=92,"3個月以下",IF(N27<=365,"3個月至1年",IF(N27<=1095,"1年至3年",IF(N27>1096,"3年以上")))) -> 3個月以下 | P27: 個人問題 | Q27: 學校開學 | R27: □已完成歸檔 □___月生效 □其他： | T27: X | U27: X
A28: 114090003 | B28: 09月 | C28: 企業客服課 | D28: 04363 | E28: 王君泰 | F28: 工讀生 | G28: 45847 | H28: 45902 | I28: 9/2退保 | J28: 45897 | K28: =DATEDIF(G28,H28,"y") -> 0 | L28: =DATEDIF(G28,H28,"ym") -> 1 | M28: =DATEDIF(G28,H28,"MD") -> 24 | N28: =DATEDIF(G28,H28,"d") -> 55 | O28: =IF(N28<=92,"3個月以下",IF(N28<=365,"3個月至1年",IF(N28<=1095,"1年至3年",IF(N28>1096,"3年以上")))) -> 3個月以下 | P28: 個人問題 | Q28: 學校開學 | R28: □已完成歸檔 □___月生效 □其他： | T28: X | U28: X
A29: 114090004 | B29: 09月 | C29: 行銷部 | D29: 04357 | E29: 黃詩庭 | F29: 工讀生 | G29: 45839 | H29: 45912 | I29: 9/12退保 | J29: 45897 | K29: =DATEDIF(G29,H29,"y") -> 0 | L29: =DATEDIF(G29,H29,"ym") -> 2 | M29: =DATEDIF(G29,H29,"MD") -> 11 | N29: =DATEDIF(G29,H29,"d") -> 73 | O29: =IF(N29<=92,"3個月以下",IF(N29<=365,"3個月至1年",IF(N29<=1095,"1年至3年",IF(N29>1096,"3年以上")))) -> 3個月以下 | P29: 個人問題 | Q29: 合約到期 | R29: □已完成歸檔 □___月生效 □其他： | S29: V | T29: V | U29: V | V29: 台中市清水區中社裡22鄰建國路122號14樓之一
A30: 114090005 | B30: 09月 | C30: 拆除工程課 | D30: 04330 | E30: 陳俊緯 | F30: 夾子車司機 | G30: 45754 | H30: 45912 | I30: 9/12退保 | J30: 45902 | K30: =DATEDIF(G30,H30,"y") -> 0 | L30: =DATEDIF(G30,H30,"ym") -> 5 | M30: =DATEDIF(G30,H30,"MD") -> 5 | N30: =DATEDIF(G30,H30,"d") -> 158 | O30: =IF(N30<=92,"3個月以下",IF(N30<=365,"3個月至1年",IF(N30<=1095,"1年至3年",IF(N30>1096,"3年以上")))) -> 3個月至1年 | P30: 個人問題 | R30: □已完成歸檔 □___月生效 □其他： | S30: V | T30: X | U30: V | V30: 台中市東勢區文新街278巷17號3樓
A31: 114090006 | B31: 09月 | C31: 全興造粒課 | D31: 03928 | E31: 李暘陞 | F31: 作業員 | G31: 44879 | H31: 45912 | I31: 9/12退保 | J31: 45903 | K31: =DATEDIF(G31,H31,"y") -> 2 | L31: =DATEDIF(G31,H31,"ym") -> 9 | M31: =DATEDIF(G31,H31,"MD") -> 29 | N31: =DATEDIF(G31,H31,"d") -> 1033 | O31: =IF(N31<=92,"3個月以下",IF(N31<=365,"3個月至1年",IF(N31<=1095,"1年至3年",IF(N31>1096,"3年以上")))) -> 1年至3年 | P31: 個人問題 | R31: □已完成歸檔 □___月生效 □其他： | S31: V | T31: X | U31: X
A32: 114090007 | B32: 09月 | C32: 宏偉處理課 | D32: 03657 | E32: 劉祥志 | F32: 組長 | G32: 44270 | H32: 45930 | I32: 9/30退保 | J32: 45903 | K32: =DATEDIF(G32,H32,"y") -> 4 | L32: =DATEDIF(G32,H32,"ym") -> 6 | M32: =DATEDIF(G32,H32,"MD") -> 15 | N32: =DATEDIF(G32,H32,"d") -> 1660 | O32: =IF(N32<=92,"3個月以下",IF(N32<=365,"3個月至1年",IF(N32<=1095,"1年至3年",IF(N32>1096,"3年以上")))) -> 3年以上 | P32: 資遣 | R32: □已完成歸檔 □___月生效 □其他： | S32: X
A33: 114090008 | B33: 09月 | C33: 宏偉營業課 | D33: H0001 | E33: 李曉琪 | F33: 主辦會計 | G33: 42334 | H33: 45930 | I33: 9/30退保 | J33: 45903 | K33: =DATEDIF(G33,H33,"y") -> 9 | L33: =DATEDIF(G33,H33,"ym") -> 10 | M33: =DATEDIF(G33,H33,"MD") -> 4 | N33: =DATEDIF(G33,H33,"d") -> 3596 | O33: =IF(N33<=92,"3個月以下",IF(N33<=365,"3個月至1年",IF(N33<=1095,"1年至3年",IF(N33>1096,"3年以上")))) -> 3年以上 | P33: 資遣 | R33: □已完成歸檔 □___月生效 □其他： | S33: X
A34: 114090009 | B34: 09月 | C34: 宏偉營業課 | D34: H0002 | E34: 陳靖宜 | F34: 主辦會計 | G34: 41061 | H34: 45930 | J34: 45903 | K34: =DATEDIF(G34,H34,"y") -> 13 | L34: =DATEDIF(G34,H34,"ym") -> 3 | M34: =DATEDIF(G34,H34,"MD") -> 29 | N34: =DATEDIF(G34,H34,"d") -> 4869 | O34: =IF(N34<=92,"3個月以下",IF(N34<=365,"3個月至1年",IF(N34<=1095,"1年至3年",IF(N34>1096,"3年以上")))) -> 3年以上 | P34: 資遣 | R34: □已完成歸檔 □___月生效 □其他： | S34: X
A35: 114090010 | B35: 09月 | C35: 宏偉處理課 | D35: H0004 | E35: 張秋媚 | F35: 作業員 | G35: 39356 | H35: 45930 | J35: 45903 | K35: =DATEDIF(G35,H35,"y") -> 17 | L35: =DATEDIF(G35,H35,"ym") -> 11 | M35: =DATEDIF(G35,H35,"MD") -> 29 | N35: =DATEDIF(G35,H35,"d") -> 6574 | O35: =IF(N35<=92,"3個月以下",IF(N35<=365,"3個月至1年",IF(N35<=1095,"1年至3年",IF(N35>1096,"3年以上")))) -> 3年以上 | P35: 資遣 | R35: □已完成歸檔 □___月生效 □其他： | S35: X
A36: 114090011 | B36: 09月 | C36: 宏偉處理課 | D36: H0005 | E36: 古莉達 | F36: 作業員 | G36: 40078 | H36: 45930 | J36: 45903 | K36: =DATEDIF(G36,H36,"y") -> 16 | L36: =DATEDIF(G36,H36,"ym") -> 0 | M36: =DATEDIF(G36,H36,"MD") -> 8 | N36: =DATEDIF(G36,H36,"d") -> 5852 | O36: =IF(N36<=92,"3個月以下",IF(N36<=365,"3個月至1年",IF(N36<=1095,"1年至3年",IF(N36>1096,"3年以上")))) -> 3年以上 | P36: 資遣 | R36: □已完成歸檔 □___月生效 □其他： | S36: X
A37: 114090012 | B37: 09月 | C37: 宏偉處理課 | D37: H0007 | E37: 林秋呈 | F37: 作業員 | G37: 40284 | H37: 45930 | I37: 9/30退保 | J37: 45903 | K37: =DATEDIF(G37,H37,"y") -> 15 | L37: =DATEDIF(G37,H37,"ym") -> 5 | M37: =DATEDIF(G37,H37,"MD") -> 14 | N37: =DATEDIF(G37,H37,"d") -> 5646 | O37: =IF(N37<=92,"3個月以下",IF(N37<=365,"3個月至1年",IF(N37<=1095,"1年至3年",IF(N37>1096,"3年以上")))) -> 3年以上 | P37: 資遣 | R37: □已完成歸檔 □___月生效 □其他： | S37: X
A38: 114090013 | B38: 09月 | C38: 宏偉處理課 | D38: H0012 | E38: 杜文長 | F38: 移工 | G38: 43739 | H38: 45930 | I38: 9/30退保 | J38: 45903 | K38: =DATEDIF(G38,H38,"y") -> 5 | L38: =DATEDIF(G38,H38,"ym") -> 11 | M38: =DATEDIF(G38,H38,"MD") -> 29 | N38: =DATEDIF(G38,H38,"d") -> 2191 | O38: =IF(N38<=92,"3個月以下",IF(N38<=365,"3個月至1年",IF(N38<=1095,"1年至3年",IF(N38>1096,"3年以上")))) -> 3年以上 | P38: 資遣 | R38: □已完成歸檔 □___月生效 □其他： | S38: X
A39: 114090014 | B39: 09月 | C39: 宏偉處理課 | D39: H0016 | E39: 張宗義 | F39: 資深外場人員 | G39: 42508 | H39: 45930 | I39: 9/30退保 | J39: 45903 | K39: =DATEDIF(G39,H39,"y") -> 9 | L39: =DATEDIF(G39,H39,"ym") -> 4 | M39: =DATEDIF(G39,H39,"MD") -> 12 | N39: =DATEDIF(G39,H39,"d") -> 3422 | O39: =IF(N39<=92,"3個月以下",IF(N39<=365,"3個月至1年",IF(N39<=1095,"1年至3年",IF(N39>1096,"3年以上")))) -> 3年以上 | P39: 資遣 | R39: □已完成歸檔 □___月生效 □其他： | S39: X
A40: 114090015 | B40: 09月 | C40: 宏偉處理課 | D40: H0021 | E40: 杜文強 | F40: 移工 | G40: 43335 | H40: 45930 | I40: 9/30退保 | J40: 45903 | K40: =DATEDIF(G40,H40,"y") -> 7 | L40: =DATEDIF(G40,H40,"ym") -> 1 | M40: =DATEDIF(G40,H40,"MD") -> 7 | N40: =DATEDIF(G40,H40,"d") -> 2595 | O40: =IF(N40<=92,"3個月以下",IF(N40<=365,"3個月至1年",IF(N40<=1095,"1年至3年",IF(N40>1096,"3年以上")))) -> 3年以上 | P40: 資遣 | R40: □已完成歸檔 □___月生效 □其他： | S40: X
A41: 114090016 | B41: 09月 | C41: 宏偉處理課 | D41: H0023 | E41: 范文雄 | F41: 移工 | G41: 43528 | H41: 45930 | I41: 9/30退保 | J41: 45903 | K41: =DATEDIF(G41,H41,"y") -> 6 | L41: =DATEDIF(G41,H41,"ym") -> 6 | M41: =DATEDIF(G41,H41,"MD") -> 26 | N41: =DATEDIF(G41,H41,"d") -> 2402 | O41: =IF(N41<=92,"3個月以下",IF(N41<=365,"3個月至1年",IF(N41<=1095,"1年至3年",IF(N41>1096,"3年以上")))) -> 3年以上 | P41: 資遣 | R41: □已完成歸檔 □___月生效 □其他： | S41: X
A42: 114090017 | B42: 09月 | C42: 宏偉處理課 | D42: H0024 | E42: 丁功正 | F42: 移工 | G42: 43530 | H42: 45930 | I42: 10/1退保 | J42: 45903 | K42: =DATEDIF(G42,H42,"y") -> 6 | L42: =DATEDIF(G42,H42,"ym") -> 6 | M42: =DATEDIF(G42,H42,"MD") -> 24 | N42: =DATEDIF(G42,H42,"d") -> 2400 | O42: =IF(N42<=92,"3個月以下",IF(N42<=365,"3個月至1年",IF(N42<=1095,"1年至3年",IF(N42>1096,"3年以上")))) -> 3年以上 | P42: 資遣 | R42: □已完成歸檔 □___月生效 □其他： | S42: X
A43: 114090018 | B43: 09月 | C43: 業務課 | D43: 04347 | E43: 陳睿婕 | F43: 業務高級專員 | G43: 45810 | H43: 45905 | I43: 9/5退保 | J43: 45904 | K43: =DATEDIF(G43,H43,"y") -> 0 | L43: =DATEDIF(G43,H43,"ym") -> 3 | M43: =DATEDIF(G43,H43,"MD") -> 3 | N43: =DATEDIF(G43,H43,"d") -> 95 | O43: =IF(N43<=92,"3個月以下",IF(N43<=365,"3個月至1年",IF(N43<=1095,"1年至3年",IF(N43>1096,"3年以上")))) -> 3個月至1年 | P43: 工作性質 | Q43: 因工作階段性任務完成,協調轉調其他部門,但人員無意願,自請離職 | R43: □已完成歸檔 □___月生效 □其他： | S43: V | T43: V | U43: V | V43: 台中市南屯區向上路二段340號
A44: 114090019 | B44: 09月 | C44: 南區業務一課 | D44: 03570 | E44: 林永裕 | F44: 夾子車司機 | G44: 43955 | H44: 45912 | I44: 9/12退保 | J44: 45903 | K44: =DATEDIF(G44,H44,"y") -> 5 | L44: =DATEDIF(G44,H44,"ym") -> 4 | M44: =DATEDIF(G44,H44,"MD") -> 8 | N44: =DATEDIF(G44,H44,"d") -> 1957 | O44: =IF(N44<=92,"3個月以下",IF(N44<=365,"3個月至1年",IF(N44<=1095,"1年至3年",IF(N44>1096,"3年以上")))) -> 3年以上 | P44: 個人問題 | R44: □已完成歸檔 □___月生效 □其他： | S44: V | T44: X | U44: X
A45: 114090020 | B45: 09月 | C45: 全興造粒課 | D45: 03845 | E45: 李玟潔 | F45: 助理會計 | G45: 44718 | H45: 45930 | I45: 已申請 | J45: 45918 | K45: =DATEDIF(G45,H45,"y") -> 3 | L45: =DATEDIF(G45,H45,"ym") -> 3 | M45: =DATEDIF(G45,H45,"MD") -> 24 | N45: =DATEDIF(G45,H45,"d") -> 1212 | O45: =IF(N45<=92,"3個月以下",IF(N45<=365,"3個月至1年",IF(N45<=1095,"1年至3年",IF(N45>1096,"3年以上")))) -> 3年以上 | P45: 育嬰留停 | Q45: 留停區間:10/1~12/31 | R45: □已完成歸檔 □___月生效 □其他：
A46: 114090021 | B46: 09月 | C46: 中區業務一課 | D46: 04358 | E46: 賴炎輝 | F46: 作業員 | G46: 45839 | H46: 45909 | I46: 9/11退保 | J46: 45911 | K46: =DATEDIF(G46,H46,"y") -> 0 | L46: =DATEDIF(G46,H46,"ym") -> 2 | M46: =DATEDIF(G46,H46,"MD") -> 8 | N46: =DATEDIF(G46,H46,"d") -> 70 | O46: =IF(N46<=92,"3個月以下",IF(N46<=365,"3個月至1年",IF(N46<=1095,"1年至3年",IF(N46>1096,"3年以上")))) -> 3個月以下 | P46: 個人問題 | R46: □已完成歸檔 □___月生效 □其他： | S46: V離職訊息 | T46: V | U46: X | V46: 苗栗縣頭屋鄉鳴鳳村6鄰三湖27號
A47: 114090022 | B47: 09月 | C47: 國際事業部 | D47: 04257 | E47: 林佳蓉 | F47: 副管理師 | G47: 45516 | H47: 45930 | I47: 9/30退保 | J47: 45915 | K47: =DATEDIF(G47,H47,"y") -> 1 | L47: =DATEDIF(G47,H47,"ym") -> 1 | M47: =DATEDIF(G47,H47,"MD") -> 18 | N47: =DATEDIF(G47,H47,"d") -> 414 | O47: =IF(N47<=92,"3個月以下",IF(N47<=365,"3個月至1年",IF(N47<=1095,"1年至3年",IF(N47>1096,"3年以上")))) -> 1年至3年 | P47: 另謀高就 | R47: □已完成歸檔 □___月生效 □其他： | S47: V | T47: V | U47: V | V47: 台中市東區建成路336巷1-1號3樓
A48: 114090023 | B48: 09月 | C48: 斗六站 | D48: 03855 | E48: 翁佳得 | F48: 夾子車司機 | G48: 44732 | H48: 45930 | I48: 9/30退保 | J48: 45916 | K48: =DATEDIF(G48,H48,"y") -> 3 | L48: =DATEDIF(G48,H48,"ym") -> 3 | M48: =DATEDIF(G48,H48,"MD") -> 10 | N48: =DATEDIF(G48,H48,"d") -> 1198 | O48: =IF(N48<=92,"3個月以下",IF(N48<=365,"3個月至1年",IF(N48<=1095,"1年至3年",IF(N48>1096,"3年以上")))) -> 3年以上 | P48: 另謀高就 | R48: □已完成歸檔 □___月生效 □其他： | S48: V | T48: V | U48: V | V48: 雲林縣斗六市保長路41號
A49: 114090024 | B49: 09月 | C49: 全興造粒課 | D49: 01747 | E49: 李俊弘 | F49: 組長 | G49: 40595 | H49: 45930 | I49: 9/30退保 | J49: 45918 | K49: =DATEDIF(G49,H49,"y") -> 14 | L49: =DATEDIF(G49,H49,"ym") -> 7 | M49: =DATEDIF(G49,H49,"MD") -> 9 | N49: =DATEDIF(G49,H49,"d") -> 5335 | O49: =IF(N49<=92,"3個月以下",IF(N49<=365,"3個月至1年",IF(N49<=1095,"1年至3年",IF(N49>1096,"3年以上")))) -> 3年以上 | P49: 另謀高就 | R49: □已完成歸檔 □___月生效 □其他： | S49: V | T49: V | U49: X | V49: 彰化市彰南路二段512巷19號
A50: 114090025 | B50: 09月 | C50: 北區業務二課 | D50: 03555 | E50: 劉春保 | F50: 作業員 | G50: 43906 | H50: 45930 | I50: 9/30退保 | J50: 45922 | K50: =DATEDIF(G50,H50,"y") -> 5 | L50: =DATEDIF(G50,H50,"ym") -> 6 | M50: =DATEDIF(G50,H50,"MD") -> 14 | N50: =DATEDIF(G50,H50,"d") -> 2024 | O50: =IF(N50<=92,"3個月以下",IF(N50<=365,"3個月至1年",IF(N50<=1095,"1年至3年",IF(N50>1096,"3年以上")))) -> 3年以上 | P50: 身體因素 | Q50: 因身體因素需要開刀並長期休養 | R50: □已完成歸檔 □___月生效 □其他： | S50: V | T50: X | U50: V | V50: 新竹縣竹北市福德里18鄰三民路494巷1號
A51: 114090026 | B51: 09月 | C51: 中區業務一課 | D51: 04356 | E51: 劉正偉 | F51: 夾子車司機 | G51: 45826 | H51: 45930 | I51: 9/30退保 | J51: 45924 | K51: =DATEDIF(G51,H51,"y") -> 0 | L51: =DATEDIF(G51,H51,"ym") -> 3 | M51: =DATEDIF(G51,H51,"MD") -> 12 | N51: =DATEDIF(G51,H51,"d") -> 104 | O51: =IF(N51<=92,"3個月以下",IF(N51<=365,"3個月至1年",IF(N51<=1095,"1年至3年",IF(N51>1096,"3年以上")))) -> 3個月至1年 | P51: 個人問題 | R51: □已完成歸檔 □___月生效 □其他： | S51: V | T51: X | U51: V | V51: 台中市沙鹿區清泉路176巷6號
A53: 114100001 | B53: 10月 | C53: 宏偉營業課 | D53: H0002 | E53: 陳靖宜 | F53: 主辦會計 | G53: 41061 | H53: 45961 | I53: 10/31退保 | J53: 45903 | K53: =DATEDIF(G53,H53,"y") -> 13 | L53: =DATEDIF(G53,H53,"ym") -> 4 | M53: =DATEDIF(G53,H53,"MD") -> 30 | N53: =DATEDIF(G53,H53,"d") -> 4900 | O53: =IF(N53<=92,"3個月以下",IF(N53<=365,"3個月至1年",IF(N53<=1095,"1年至3年",IF(N53>1096,"3年以上")))) -> 3年以上 | P53: 資遣 | R53: □已完成歸檔 □___月生效 □其他： | S53: X
A54: 114100002 | B54: 10月 | C54: 宏偉處理課 | D54: H0004 | E54: 張秋媚 | F54: 作業員 | G54: 39356 | H54: 45961 | I54: 10/31退保 | J54: 45903 | K54: =DATEDIF(G54,H54,"y") -> 18 | L54: =DATEDIF(G54,H54,"ym") -> 0 | M54: =DATEDIF(G54,H54,"MD") -> 30 | N54: =DATEDIF(G54,H54,"d") -> 6605 | O54: =IF(N54<=92,"3個月以下",IF(N54<=365,"3個月至1年",IF(N54<=1095,"1年至3年",IF(N54>1096,"3年以上")))) -> 3年以上 | P54: 資遣 | R54: □已完成歸檔 □___月生效 □其他： | S54: X
A55: 114100003 | B55: 10月 | C55: 宏偉處理課 | D55: H0005 | E55: 古莉達 | F55: 作業員 | G55: 40078 | H55: 45961 | I55: 10/31退保 | J55: 45903 | K55: =DATEDIF(G55,H55,"y") -> 16 | L55: =DATEDIF(G55,H55,"ym") -> 1 | M55: =DATEDIF(G55,H55,"MD") -> 9 | N55: =DATEDIF(G55,H55,"d") -> 5883 | O55: =IF(N55<=92,"3個月以下",IF(N55<=365,"3個月至1年",IF(N55<=1095,"1年至3年",IF(N55>1096,"3年以上")))) -> 3年以上 | P55: 資遣 | R55: □已完成歸檔 □___月生效 □其他： | S55: X
A56: 114100004 | B56: 10月 | C56: 管理課 | D56: 02820 | E56: 謝佩伶 | F56: 副管理師 | G56: 42466 | H56: 45961 | I56: 10/31退保 | J56: 45924 | K56: =DATEDIF(G56,H56,"y") -> 9 | L56: =DATEDIF(G56,H56,"ym") -> 6 | M56: =DATEDIF(G56,H56,"MD") -> 25 | N56: =DATEDIF(G56,H56,"d") -> 3495 | O56: =IF(N56<=92,"3個月以下",IF(N56<=365,"3個月至1年",IF(N56<=1095,"1年至3年",IF(N56>1096,"3年以上")))) -> 3年以上 | P56: 個人問題 | R56: □已完成歸檔 □___月生效 □其他：
A57: 114100005 | B57: 10月 | C57: 中區業務一課 | D57: 04401 | E57: 許竣捷 | F57: 儲備夾子車司機 | G57: 45931 | H57: 45935 | I57: 10/05退保 | J57: 45937 | K57: =DATEDIF(G57,H57,"y") -> 0 | L57: =DATEDIF(G57,H57,"ym") -> 0 | M57: =DATEDIF(G57,H57,"MD") -> 4 | N57: =DATEDIF(G57,H57,"d") -> 4 | O57: =IF(N57<=92,"3個月以下",IF(N57<=365,"3個月至1年",IF(N57<=1095,"1年至3年",IF(N57>1096,"3年以上")))) -> 3個月以下 | P57: 個人問題 | R57: □已完成歸檔 □___月生效 □其他： | S57: V | T57: X | U57: X
A58: 114100006 | B58: 10月 | C58: 家電客服課 | D58: 04271 | E58: 陳信廷 | F58: 3.5噸司機 | G58: 45544 | H58: 45961 | I58: 10/31退保 | J58: 45931 | K58: =DATEDIF(G58,H58,"y") -> 1 | L58: =DATEDIF(G58,H58,"ym") -> 1 | M58: =DATEDIF(G58,H58,"MD") -> 22 | N58: =DATEDIF(G58,H58,"d") -> 417 | O58: =IF(N58<=92,"3個月以下",IF(N58<=365,"3個月至1年",IF(N58<=1095,"1年至3年",IF(N58>1096,"3年以上")))) -> 1年至3年 | P58: 資遣 | R58: □已完成歸檔 □___月生效 □其他： | S58: X
A59: 114100007 | B59: 10月 | C59: 家電客服課 | D59: 03497 | E59: 張珈菱 | F59: 助理管理師 | G59: 43731 | H59: 45961 | I59: 10/31退保 | J59: 45931 | K59: =DATEDIF(G59,H59,"y") -> 6 | L59: =DATEDIF(G59,H59,"ym") -> 1 | M59: =DATEDIF(G59,H59,"MD") -> 8 | N59: =DATEDIF(G59,H59,"d") -> 2230 | O59: =IF(N59<=92,"3個月以下",IF(N59<=365,"3個月至1年",IF(N59<=1095,"1年至3年",IF(N59>1096,"3年以上")))) -> 3年以上 | P59: 資遣 | R59: □已完成歸檔 □___月生效 □其他： | S59: X
A60: 114100008 | B60: 10月 | C60: 電商部行政管理課 | D60: 03920 | E60: 杜昀芳 | F60: 副管理師 | G60: 44872 | H60: 45961 | I60: 10/31退保 | J60: 45931 | K60: =DATEDIF(G60,H60,"y") -> 2 | L60: =DATEDIF(G60,H60,"ym") -> 11 | M60: =DATEDIF(G60,H60,"MD") -> 24 | N60: =DATEDIF(G60,H60,"d") -> 1089 | O60: =IF(N60<=92,"3個月以下",IF(N60<=365,"3個月至1年",IF(N60<=1095,"1年至3年",IF(N60>1096,"3年以上")))) -> 1年至3年 | P60: 資遣 | R60: □已完成歸檔 □___月生效 □其他： | S60: X
A61: 114100009 | B61: 10月 | C61: 電商部行政管理課 | D61: 03615 | E61: 楊依綺 | F61: 組長 | G61: 44123 | H61: 45961 | I61: 10/31退保 | J61: 45931 | K61: =DATEDIF(G61,H61,"y") -> 5 | L61: =DATEDIF(G61,H61,"ym") -> 0 | M61: =DATEDIF(G61,H61,"MD") -> 12 | N61: =DATEDIF(G61,H61,"d") -> 1838 | O61: =IF(N61<=92,"3個月以下",IF(N61<=365,"3個月至1年",IF(N61<=1095,"1年至3年",IF(N61>1096,"3年以上")))) -> 3年以上 | P61: 資遣 | R61: □已完成歸檔 □___月生效 □其他： | S61: X
A62: 114100010 | B62: 10月 | C62: 北區業務二課 | D62: 04279 | E62: 施詠覺 | F62: 作業員 | G62: 45558 | H62: 45930 | J62: 45945 | K62: =DATEDIF(G62,H62,"y") -> 1 | L62: =DATEDIF(G62,H62,"ym") -> 0 | M62: =DATEDIF(G62,H62,"MD") -> 7 | N62: =DATEDIF(G62,H62,"d") -> 372 | O62: =IF(N62<=92,"3個月以下",IF(N62<=365,"3個月至1年",IF(N62<=1095,"1年至3年",IF(N62>1096,"3年以上")))) -> 1年至3年 | P62: 留職停薪 | Q62: 留停區間(暫定):10/1~10/31 | R62: □已完成歸檔 □___月生效 □其他： | S62: X
A63: 114100011 | B63: 10月 | D63: 04412 | E63: 李翊滐 | F63: 夾子車司機 | G63: 45943 | H63: 45953 | I63: 10/23退保 | J63: 45952 | K63: =DATEDIF(G63,H63,"y") -> 0 | L63: =DATEDIF(G63,H63,"ym") -> 0 | M63: =DATEDIF(G63,H63,"MD") -> 10 | N63: =DATEDIF(G63,H63,"d") -> 10 | O63: =IF(N63<=92,"3個月以下",IF(N63<=365,"3個月至1年",IF(N63<=1095,"1年至3年",IF(N63>1096,"3年以上")))) -> 3個月以下 | P63: 個人問題 | R63: □已完成歸檔 □___月生效 □其他： | S63: V | T63: X | U63: X
A64: 114100012 | B64: 10月 | C64: 中區業務一課 | D64: 04365 | E64: 何衡譽 | F64: 作業員 | G64: 45847 | H64: 45953 | I64: 10/23退保 | J64: 45958 | K64: =DATEDIF(G64,H64,"y") -> 0 | L64: =DATEDIF(G64,H64,"ym") -> 3 | M64: =DATEDIF(G64,H64,"MD") -> 14 | N64: =DATEDIF(G64,H64,"d") -> 106 | O64: =IF(N64<=92,"3個月以下",IF(N64<=365,"3個月至1年",IF(N64<=1095,"1年至3年",IF(N64>1096,"3年以上")))) -> 3個月至1年 | P64: 個人問題 | R64: □已完成歸檔 □___月生效 □其他： | S64: V | T64: V | U64: V | V64: 台中市潭子區大富路3段33巷120弄2號
A65: 114100013 | B65: 10月 | C65: 南區業務一課 | D65: 04280 | E65: 黃亦聖 | F65: 作業員 | G65: 45558 | H65: 45961 | I65: 10/31退保 | J65: 45957 | K65: =DATEDIF(G65,H65,"y") -> 1 | L65: =DATEDIF(G65,H65,"ym") -> 1 | M65: =DATEDIF(G65,H65,"MD") -> 8 | N65: =DATEDIF(G65,H65,"d") -> 403 | O65: =IF(N65<=92,"3個月以下",IF(N65<=365,"3個月至1年",IF(N65<=1095,"1年至3年",IF(N65>1096,"3年以上")))) -> 1年至3年 | P65: 個人問題 | R65: □已完成歸檔 □___月生效 □其他： | S65: V
A67: 114110001 | B67: 11月 | C67: 北區業務二課 | D67: 03633 | E67: 鄭紹烽 | F67: 作業員 | G67: 44179 | H67: 45975 | I67: 11/14退保 | J67: 45966 | K67: =DATEDIF(G67,H67,"y") -> 4 | L67: =DATEDIF(G67,H67,"ym") -> 11 | M67: =DATEDIF(G67,H67,"MD") -> 0 | N67: =DATEDIF(G67,H67,"d") -> 1796 | O67: =IF(N67<=92,"3個月以下",IF(N67<=365,"3個月至1年",IF(N67<=1095,"1年至3年",IF(N67>1096,"3年以上")))) -> 3年以上 | P67: 個人問題 | R67: □已完成歸檔 □___月生效 □其他： | S67: V | T67: V | U67: V | V67: 桃園市楊梅區高新街206巷9號
A68: 114110002 | B68: 11月 | C68: 中區業務一課 | D68: 04399 | E68: 王雅姿 | F68: 倉儲物流專員 | G68: 45943 | H68: 45967 | I68: 11/6退保 | J68: 45967 | K68: =DATEDIF(G68,H68,"y") -> 0 | L68: =DATEDIF(G68,H68,"ym") -> 0 | M68: =DATEDIF(G68,H68,"MD") -> 24 | N68: =DATEDIF(G68,H68,"d") -> 24 | O68: =IF(N68<=92,"3個月以下",IF(N68<=365,"3個月至1年",IF(N68<=1095,"1年至3年",IF(N68>1096,"3年以上")))) -> 3個月以下 | P68: 個人問題 | R68: □已完成歸檔 □___月生效 □其他： | S68: V
A69: 114110003 | B69: 11月 | C69: 中區業務一課 | D69: 00285 | E69: 吳侯進 | F69: 作業員 | G69: 39083 | H69: 45971 | I69: 11/10退保 | J69: 45971 | K69: =DATEDIF(G69,H69,"y") -> 18 | L69: =DATEDIF(G69,H69,"ym") -> 10 | M69: =DATEDIF(G69,H69,"MD") -> 9 | N69: =DATEDIF(G69,H69,"d") -> 6888 | O69: =IF(N69<=92,"3個月以下",IF(N69<=365,"3個月至1年",IF(N69<=1095,"1年至3年",IF(N69>1096,"3年以上")))) -> 3年以上 | P69: 解雇 | R69: □已完成歸檔 □___月生效 □其他：
A70: 114110004 | B70: 11月 | C70: 中區業務一課 | D70: 01879 | E70: 阮氏金成 | F70: 作業員 | G70: 40787 | H70: 45971 | I70: 11/10退保 | J70: 45971 | K70: =DATEDIF(G70,H70,"y") -> 14 | L70: =DATEDIF(G70,H70,"ym") -> 2 | M70: =DATEDIF(G70,H70,"MD") -> 9 | N70: =DATEDIF(G70,H70,"d") -> 5184 | O70: =IF(N70<=92,"3個月以下",IF(N70<=365,"3個月至1年",IF(N70<=1095,"1年至3年",IF(N70>1096,"3年以上")))) -> 3年以上 | P70: 解雇 | R70: □已完成歸檔 □___月生效 □其他：
A71: 114110005 | B71: 11月 | C71: 南區業務一課 | D71: 04372 | E71: 賴疆允 | F71: 夾子車司機 | G71: 45859 | H71: 45971 | I71: 11/10退保 | J71: 45971 | K71: =DATEDIF(G71,H71,"y") -> 0 | L71: =DATEDIF(G71,H71,"ym") -> 3 | M71: =DATEDIF(G71,H71,"MD") -> 20 | N71: =DATEDIF(G71,H71,"d") -> 112 | O71: =IF(N71<=92,"3個月以下",IF(N71<=365,"3個月至1年",IF(N71<=1095,"1年至3年",IF(N71>1096,"3年以上")))) -> 3個月至1年 | P71: 個人問題 | Q71: 交通違規 | R71: □已完成歸檔 □___月生效 □其他： | S71: V | T71: X | U71: V | V71: 台南市官田區官田里官田182-27號
A72: 114110006 | B72: 11月 | C72: 企業客服課 | D72: 04403 | E72: 邱冠霖 | F72: 工讀生 | G72: 45931 | H72: 45979 | I72: 11/18退保 | J72: 45968 | K72: =DATEDIF(G72,H72,"y") -> 0 | L72: =DATEDIF(G72,H72,"ym") -> 1 | M72: =DATEDIF(G72,H72,"MD") -> 17 | N72: =DATEDIF(G72,H72,"d") -> 48 | O72: =IF(N72<=92,"3個月以下",IF(N72<=365,"3個月至1年",IF(N72<=1095,"1年至3年",IF(N72>1096,"3年以上")))) -> 3個月以下 | P72: 個人問題 | Q72: 合約期滿 | R72: □已完成歸檔 □___月生效 □其他：
A73: 114110007 | B73: 11月 | C73: 全興造粒課 | D73: 03948 | E73: 安塔空 | F73: 移工 | G73: 44899 | H73: 45987 | I73: 11/29退保 | J73: 45968 | K73: =DATEDIF(G73,H73,"y") -> 2 | L73: =DATEDIF(G73,H73,"ym") -> 11 | M73: =DATEDIF(G73,H73,"MD") -> 22 | N73: =DATEDIF(G73,H73,"d") -> 1088 | O73: =IF(N73<=92,"3個月以下",IF(N73<=365,"3個月至1年",IF(N73<=1095,"1年至3年",IF(N73>1096,"3年以上")))) -> 1年至3年 | P73: 個人問題 | R73: □已完成歸檔 □___月生效 □其他：
A74: 114110008 | B74: 11月 | C74: 行銷部 | D74: 04390 | E74: 王意涵 | F74: 管理師 | G74: 45901 | H74: 45989 | I74: 11/28退保 | J74: 45985 | K74: =DATEDIF(G74,H74,"y") -> 0 | L74: =DATEDIF(G74,H74,"ym") -> 2 | M74: =DATEDIF(G74,H74,"MD") -> 27 | N74: =DATEDIF(G74,H74,"d") -> 88 | O74: =IF(N74<=92,"3個月以下",IF(N74<=365,"3個月至1年",IF(N74<=1095,"1年至3年",IF(N74>1096,"3年以上")))) -> 3個月以下 | P74: 個人問題 | R74: □已完成歸檔 □___月生效 □其他：
A76: 114120001 | B76: 12月 | C76: 資訊部專案管理課 | D76: 04299 | E76: 黃筠倫 | F76: 副工程師 | G76: 45628 | H76: 45992 | I76: 12/1退保 | J76: 45992 | K76: =DATEDIF(G76,H76,"y") -> 0 | L76: =DATEDIF(G76,H76,"ym") -> 11 | M76: =DATEDIF(G76,H76,"MD") -> 29 | N76: =DATEDIF(G76,H76,"d") -> 364 | O76: =IF(N76<=92,"3個月以下",IF(N76<=365,"3個月至1年",IF(N76<=1095,"1年至3年",IF(N76>1096,"3年以上")))) -> 3個月至1年 | P76: 資遣 | R76: □已完成歸檔 □___月生效 □其他：
A77: 114120002 | B77: 12月 | C77: 北區業務二課 | D77: 04279 | E77: 施詠覺 | F77: 作業員 | G77: 45558 | H77: 45930 | I77: 12/5退保 | J77: 45945 | K77: =DATEDIF(G77,H77,"y") -> 1 | L77: =DATEDIF(G77,H77,"ym") -> 0 | M77: =DATEDIF(G77,H77,"MD") -> 7 | N77: =DATEDIF(G77,H77,"d") -> 372 | O77: =IF(N77<=92,"3個月以下",IF(N77<=365,"3個月至1年",IF(N77<=1095,"1年至3年",IF(N77>1096,"3年以上")))) -> 1年至3年 | P77: 解雇 | R77: □已完成歸檔 □___月生效 □其他：
A78: 114120003 | B78: 12月 | C78: 管理課 | D78: 04283 | E78: 宋承憲 | F78: 代主管 | G78: 46013 | H78: 46022 | I78: 12/31退保 | J78: 46010 | K78: =DATEDIF(G78,H78,"y") -> 0 | L78: =DATEDIF(G78,H78,"ym") -> 0 | M78: =DATEDIF(G78,H78,"MD") -> 9 | N78: =DATEDIF(G78,H78,"d") -> 9 | O78: =IF(N78<=92,"3個月以下",IF(N78<=365,"3個月至1年",IF(N78<=1095,"1年至3年",IF(N78>1096,"3年以上")))) -> 3個月以下 | P78: 個人問題 | R78: □已完成歸檔 □___月生效 □其他： | T78: V | U78: X | V78: 台中市大雅區三和里建興路201巷2號
A79: 114120004 | B79: 12月 | C79: 行政管理課 | D79: 03898 | E79: 陳怡樺 | F79: 高級管理師 | G79: 44830 | H79: 46022 | J79: 46010 | K79: =DATEDIF(G79,H79,"y") -> 3 | L79: =DATEDIF(G79,H79,"ym") -> 3 | M79: =DATEDIF(G79,H79,"MD") -> 5 | N79: =DATEDIF(G79,H79,"d") -> 1192 | O79: =IF(N79<=92,"3個月以下",IF(N79<=365,"3個月至1年",IF(N79<=1095,"1年至3年",IF(N79>1096,"3年以上")))) -> 3年以上 | P79: 職務異動 | Q79: 異動至行銷部 暫緩 | R79: □已完成歸檔 □___月生效 □其他：
A80: 114120005 | B80: 12月 | C80: 行政管理課 | D80: 04181 | E80: 廖尉君 | F80: 高級管理師 | G80: 45355 | H80: 46022 | J80: 46010 | K80: =DATEDIF(G80,H80,"y") -> 1 | L80: =DATEDIF(G80,H80,"ym") -> 9 | M80: =DATEDIF(G80,H80,"MD") -> 27 | N80: =DATEDIF(G80,H80,"d") -> 667 | O80: =IF(N80<=92,"3個月以下",IF(N80<=365,"3個月至1年",IF(N80<=1095,"1年至3年",IF(N80>1096,"3年以上")))) -> 1年至3年 | P80: 職務異動 | Q80: 異動至行銷部 暫緩 | R80: □已完成歸檔 □___月生效 □其他：
A81: 114120006 | B81: 12月 | C81: 網管工程課 | D81: 04303 | E81: 蔡孟儒 | F81: 工程師 | G81: 45663 | H81: 46022 | I81: 12/31退保 | J81: 45982 | K81: =DATEDIF(G81,H81,"y") -> 0 | L81: =DATEDIF(G81,H81,"ym") -> 11 | M81: =DATEDIF(G81,H81,"MD") -> 25 | N81: =DATEDIF(G81,H81,"d") -> 359 | O81: =IF(N81<=92,"3個月以下",IF(N81<=365,"3個月至1年",IF(N81<=1095,"1年至3年",IF(N81>1096,"3年以上")))) -> 3個月至1年 | P81: 個人問題 | R81: □已完成歸檔 □___月生效 □其他： | T81: V | U81: V | V81: 台中市沙鹿區西勢里18鄰和睦路三段481巷112號
A82: 114120007 | B82: 12月 | C82: 北區業務一課 | D82: 04327 | E82: 陳基展 | F82: 作業員 | G82: 45740 | H82: 46022 | I82: 12/31退保 | J82: 46010 | K82: =DATEDIF(G82,H82,"y") -> 0 | L82: =DATEDIF(G82,H82,"ym") -> 9 | M82: =DATEDIF(G82,H82,"MD") -> 7 | N82: =DATEDIF(G82,H82,"d") -> 282 | O82: =IF(N82<=92,"3個月以下",IF(N82<=365,"3個月至1年",IF(N82<=1095,"1年至3年",IF(N82>1096,"3年以上")))) -> 3個月至1年 | P82: 資遣 | R82: □已完成歸檔 □___月生效 □其他：
A83: 114120008 | B83: 12月 | C83: 宏偉廠(大豐) | D83: 00009 | E83: 曾石雄 | F83: 經理 | G83: 37316 | H83: 46022 | I83: 12/31退保 | J83: 46010 | K83: =DATEDIF(G83,H83,"y") -> 23 | L83: =DATEDIF(G83,H83,"ym") -> 9 | M83: =DATEDIF(G83,H83,"MD") -> 30 | N83: =DATEDIF(G83,H83,"d") -> 8706 | O83: =IF(N83<=92,"3個月以下",IF(N83<=365,"3個月至1年",IF(N83<=1095,"1年至3年",IF(N83>1096,"3年以上")))) -> 3年以上 | P83: 資遣 | R83: □已完成歸檔 □___月生效 □其他：
A84: 114120009 | B84: 12月 | C84: 法務及環安課 | D84: 04282 | E84: 李勝裕 | F84: 高級管理師 | G84: 45566 | H84: 46007 | J84: 46003 | K84: =DATEDIF(G84,H84,"y") -> 1 | L84: =DATEDIF(G84,H84,"ym") -> 2 | M84: =DATEDIF(G84,H84,"MD") -> 15 | N84: =DATEDIF(G84,H84,"d") -> 441 | O84: =IF(N84<=92,"3個月以下",IF(N84<=365,"3個月至1年",IF(N84<=1095,"1年至3年",IF(N84>1096,"3年以上")))) -> 1年至3年 | P84: 育嬰留停 | Q84: 留停區間:114/12/17~115/6/16 | R84: □已完成歸檔 □___月生效 □其他：
A85: 114120010 | B85: 12月 | C85: 營運管理部 | D85: 04316 | E85: 林庭鋐 | F85: 管理師 | G85: 45719 | H85: 46022 | I85: 12/31退保 | J85: 46013 | K85: =DATEDIF(G85,H85,"y") -> 0 | L85: =DATEDIF(G85,H85,"ym") -> 9 | M85: =DATEDIF(G85,H85,"MD") -> 28 | N85: =DATEDIF(G85,H85,"d") -> 303 | O85: =IF(N85<=92,"3個月以下",IF(N85<=365,"3個月至1年",IF(N85<=1095,"1年至3年",IF(N85>1096,"3年以上")))) -> 3個月至1年 | P85: 個人問題 | R85: □已完成歸檔 □___月生效 □其他： | T85: V | U85: V | V85: 台中市太平區新平路一段138巷57號
A87: 115010001 | B87: 1月 | C87: 法務及環安課 | D87: 03810 | E87: 蔡雅雯 | F87: 管理師 | G87: 44634 | H87: 46038 | I87: 1/16退保 | J87: 46015 | K87: =DATEDIF(G87,H87,"y") -> 3 | L87: =DATEDIF(G87,H87,"ym") -> 10 | M87: =DATEDIF(G87,H87,"MD") -> 2 | N87: =DATEDIF(G87,H87,"d") -> 1404 | O87: =IF(N87<=92,"3個月以下",IF(N87<=365,"3個月至1年",IF(N87<=1095,"1年至3年",IF(N87>1096,"3年以上")))) -> 3年以上 | P87: 個人問題 | R87: □已完成歸檔 □___月生效 □其他： | T87: V | V87: 台中市龍井區忠和里工業路89巷3號
A88: 115010002 | B88: 1月 | C88: 國際事業部 | D88: 02768 | E88: 林茹雯 | F88: 資深經理 | G88: 46027 | H88: 46037 | I88: 1/15退保 | J88: 46027 | K88: =DATEDIF(G88,H88,"y") -> 0 | L88: =DATEDIF(G88,H88,"ym") -> 0 | M88: =DATEDIF(G88,H88,"MD") -> 10 | N88: =DATEDIF(G88,H88,"d") -> 10 | O88: =IF(N88<=92,"3個月以下",IF(N88<=365,"3個月至1年",IF(N88<=1095,"1年至3年",IF(N88>1096,"3年以上")))) -> 3個月以下 | P88: 個人問題 | R88: □已完成歸檔 □___月生效 □其他： | T88: V | U88: V | V88: 中英文
A89: 115010003 | B89: 1月 | C89: 電子商務部 | D89: 04408 | E89: 曾喜煌 | F89: 工讀生 | G89: 45943 | H89: 46031 | I89: 1/9退保 | J89: 46027 | K89: =DATEDIF(G89,H89,"y") -> 0 | L89: =DATEDIF(G89,H89,"ym") -> 2 | M89: =DATEDIF(G89,H89,"MD") -> 27 | N89: =DATEDIF(G89,H89,"d") -> 88 | O89: =IF(N89<=92,"3個月以下",IF(N89<=365,"3個月至1年",IF(N89<=1095,"1年至3年",IF(N89>1096,"3年以上")))) -> 3個月以下 | P89: 其他原因 | Q89: 合約期滿 | R89: □已完成歸檔 □___月生效 □其他：
A90: 115010004 | B90: 1月 | C90: 全興造粒課 | D90: 02954 | E90: 丹多 | F90: 移工 | G90: 42775 | H90: 46053 | J90: 46034 | K90: =DATEDIF(G90,H90,"y") -> 8 | L90: =DATEDIF(G90,H90,"ym") -> 11 | M90: =DATEDIF(G90,H90,"MD") -> 22 | N90: =DATEDIF(G90,H90,"d") -> 3278 | O90: =IF(N90<=92,"3個月以下",IF(N90<=365,"3個月至1年",IF(N90<=1095,"1年至3年",IF(N90>1096,"3年以上")))) -> 3年以上 | P90: 其他原因 | Q90: 合約期滿 最後工作日：1/31(六) 結算日：2/6(五)上午09:00 離境日：2/7(六) | R90: □已完成歸檔 □___月生效 □其他：
A91: 115010005 | B91: 1月 | C91: 全興造粒課 | D91: 03548 | E91: 阿努查 | F91: 移工 | G91: 43894 | H91: 46053 | J91: 46034 | K91: =DATEDIF(G91,H91,"y") -> 5 | L91: =DATEDIF(G91,H91,"ym") -> 10 | M91: =DATEDIF(G91,H91,"MD") -> 27 | N91: =DATEDIF(G91,H91,"d") -> 2159 | O91: =IF(N91<=92,"3個月以下",IF(N91<=365,"3個月至1年",IF(N91<=1095,"1年至3年",IF(N91>1096,"3年以上")))) -> 3年以上 | P91: 其他原因 | Q91: 合約期滿 最後工作日：1/31(六) 結算日：2/6(五)上午09:00 離境日：2/8(日) | R91: □已完成歸檔 □___月生效 □其他：
A92: 115010006 | B92: 1月 | C92: 全興造粒課 | D92: 04352 | E92: 書拉財 | F92: 移工 | G92: 45723 | H92: 46030 | I92: 1/15退保 | J92: 46034 | K92: =DATEDIF(G92,H92,"y") -> 0 | L92: =DATEDIF(G92,H92,"ym") -> 10 | M92: =DATEDIF(G92,H92,"MD") -> 1 | N92: =DATEDIF(G92,H92,"d") -> 307 | O92: =IF(N92<=92,"3個月以下",IF(N92<=365,"3個月至1年",IF(N92<=1095,"1年至3年",IF(N92>1096,"3年以上")))) -> 3個月至1年 | P92: 個人問題 | Q92: 自請離職 最後工作日：1/8(四) 結算日：1/16(五)上午09:00 *廢聘日：1/13(二)* | R92: □已完成歸檔 □___月生效 □其他：
A93: 115010007 | B93: 1月 | C93: 全興造粒課 | D93: 04084 | E93: 朋吉 | F93: 移工 | G93: 45075 | H93: 46030 | I93: 1/17退保 | J93: 46034 | K93: =DATEDIF(G93,H93,"y") -> 2 | L93: =DATEDIF(G93,H93,"ym") -> 7 | M93: =DATEDIF(G93,H93,"MD") -> 10 | N93: =DATEDIF(G93,H93,"d") -> 955 | O93: =IF(N93<=92,"3個月以下",IF(N93<=365,"3個月至1年",IF(N93<=1095,"1年至3年",IF(N93>1096,"3年以上")))) -> 1年至3年 | P93: 個人問題 | Q93: 自請離職 最後工作日：1/8(四) 結算+驗證日：1/16(五)上午09:00 *離境日：1/17(六)* | R93: □已完成歸檔 □___月生效 □其他：
A94: 115010008 | B94: 1月 | C94: 北區業務二課 | D94: 04426 | E94: 龔盟方 | F94: 作業員 | G94: 46027 | H94: 46034 | I94: 1/12退保 | J94: 46034 | K94: =DATEDIF(G94,H94,"y") -> 0 | L94: =DATEDIF(G94,H94,"ym") -> 0 | M94: =DATEDIF(G94,H94,"MD") -> 7 | N94: =DATEDIF(G94,H94,"d") -> 7 | O94: =IF(N94<=92,"3個月以下",IF(N94<=365,"3個月至1年",IF(N94<=1095,"1年至3年",IF(N94>1096,"3年以上")))) -> 3個月以下 | P94: 個人問題 | R94: □已完成歸檔 □___月生效 □其他：
A95: 115010009 | B95: 1月 | C95: 北區業務一課 | D95: 03421 | E95: 黃家欣 | F95: 作業員 | G95: 43579 | H95: 46053 | I95: 1/31退保 | J95: 46034 | K95: =DATEDIF(G95,H95,"y") -> 6 | L95: =DATEDIF(G95,H95,"ym") -> 9 | M95: =DATEDIF(G95,H95,"MD") -> 7 | N95: =DATEDIF(G95,H95,"d") -> 2474 | O95: =IF(N95<=92,"3個月以下",IF(N95<=365,"3個月至1年",IF(N95<=1095,"1年至3年",IF(N95>1096,"3年以上")))) -> 3年以上 | P95: 資遣 | R95: □已完成歸檔 □___月生效 □其他：
A96: 115010010 | B96: 1月 | C96: 業務部行政管理課 | D96: 03898 | E96: 陳怡樺 | F96: 高級管理師 | G96: 44830 | H96: 46053 | I96: 1/31退保 | J96: 46034 | K96: =DATEDIF(G96,H96,"y") -> 3 | L96: =DATEDIF(G96,H96,"ym") -> 4 | M96: =DATEDIF(G96,H96,"MD") -> 5 | N96: =DATEDIF(G96,H96,"d") -> 1223 | O96: =IF(N96<=92,"3個月以下",IF(N96<=365,"3個月至1年",IF(N96<=1095,"1年至3年",IF(N96>1096,"3年以上")))) -> 3年以上 | P96: 資遣 | R96: □已完成歸檔 □___月生效 □其他： | T96: V
A97: 115010011 | B97: 1月 | C97: 業務部行政管理課 | D97: 04181 | E97: 廖尉君 | F97: 高級管理師 | G97: 45355 | H97: 46053 | I97: 1/31退保 | J97: 46034 | K97: =DATEDIF(G97,H97,"y") -> 1 | L97: =DATEDIF(G97,H97,"ym") -> 10 | M97: =DATEDIF(G97,H97,"MD") -> 27 | N97: =DATEDIF(G97,H97,"d") -> 698 | O97: =IF(N97<=92,"3個月以下",IF(N97<=365,"3個月至1年",IF(N97<=1095,"1年至3年",IF(N97>1096,"3年以上")))) -> 1年至3年 | P97: 資遣 | R97: □已完成歸檔 □___月生效 □其他： | T97: V
A98: 115010012 | B98: 1月 | C98: 廢車客服課 | D98: 04308 | E98: 劉思欣 | F98: 助理管理師 | G98: 45693 | H98: 46053 | I98: 1/31退保 | J98: 46051 | K98: =DATEDIF(G98,H98,"y") -> 0 | L98: =DATEDIF(G98,H98,"ym") -> 11 | M98: =DATEDIF(G98,H98,"MD") -> 26 | N98: =DATEDIF(G98,H98,"d") -> 360 | O98: =IF(N98<=92,"3個月以下",IF(N98<=365,"3個月至1年",IF(N98<=1095,"1年至3年",IF(N98>1096,"3年以上")))) -> 3個月至1年 | P98: 資遣 | Q98: 尚未起單 | R98: □已完成歸檔 □___月生效 □其他： | T98: V
A99: 115010013 | B99: 1月 | C99: 全興處理二課 | D99: 00067 | E99: 許明田 | F99: 主任 | G99: 38287 | H99: 46053 | I99: 1/31退保 | J99: 46043 | K99: =DATEDIF(G99,H99,"y") -> 21 | L99: =DATEDIF(G99,H99,"ym") -> 3 | M99: =DATEDIF(G99,H99,"MD") -> 4 | N99: =DATEDIF(G99,H99,"d") -> 7766 | O99: =IF(N99<=92,"3個月以下",IF(N99<=365,"3個月至1年",IF(N99<=1095,"1年至3年",IF(N99>1096,"3年以上")))) -> 3年以上 | P99: 資遣 | R99: □已完成歸檔 □___月生效 □其他： | T99: V
A100: 115010014 | B100: 1月 | C100: 全興處理二課 | D100: 01514 | E100: 黃美玉 | F100: 分選員 | G100: 40275 | H100: 46053 | I100: 1/31退保 | J100: 46043 | K100: =DATEDIF(G100,H100,"y") -> 15 | L100: =DATEDIF(G100,H100,"ym") -> 9 | M100: =DATEDIF(G100,H100,"MD") -> 24 | N100: =DATEDIF(G100,H100,"d") -> 5778 | O100: =IF(N100<=92,"3個月以下",IF(N100<=365,"3個月至1年",IF(N100<=1095,"1年至3年",IF(N100>1096,"3年以上")))) -> 3年以上 | P100: 資遣 | R100: □已完成歸檔 □___月生效 □其他： | T100: V
A101: 115010015 | B101: 1月 | C101: 全興造粒課 | D101: 03814 | E101: 孫阿諾 | F101: 移工 | G101: 44652 | H101: 46053 | J101: 46043 | K101: =DATEDIF(G101,H101,"y") -> 3 | L101: =DATEDIF(G101,H101,"ym") -> 9 | M101: =DATEDIF(G101,H101,"MD") -> 30 | N101: =DATEDIF(G101,H101,"d") -> 1401 | O101: =IF(N101<=92,"3個月以下",IF(N101<=365,"3個月至1年",IF(N101<=1095,"1年至3年",IF(N101>1096,"3年以上")))) -> 3年以上 | P101: 資遣 | R101: □已完成歸檔 □___月生效 □其他：
A102: 115010016 | B102: 1月 | C102: 全興造粒課 | D102: 03842 | E102: 艾格 | F102: 移工 | G102: 44709 | H102: 46053 | J102: 46043 | K102: =DATEDIF(G102,H102,"y") -> 3 | L102: =DATEDIF(G102,H102,"ym") -> 8 | M102: =DATEDIF(G102,H102,"MD") -> 3 | N102: =DATEDIF(G102,H102,"d") -> 1344 | O102: =IF(N102<=92,"3個月以下",IF(N102<=365,"3個月至1年",IF(N102<=1095,"1年至3年",IF(N102>1096,"3年以上")))) -> 3年以上 | P102: 資遣 | R102: □已完成歸檔 □___月生效 □其他：
A103: 115010017 | B103: 1月 | C103: 全興造粒課 | D103: 04209 | E103: 阿替 | F103: 移工 | G103: 45414 | H103: 46053 | J103: 46043 | K103: =DATEDIF(G103,H103,"y") -> 1 | L103: =DATEDIF(G103,H103,"ym") -> 8 | M103: =DATEDIF(G103,H103,"MD") -> 29 | N103: =DATEDIF(G103,H103,"d") -> 639 | O103: =IF(N103<=92,"3個月以下",IF(N103<=365,"3個月至1年",IF(N103<=1095,"1年至3年",IF(N103>1096,"3年以上")))) -> 1年至3年 | P103: 資遣 | R103: □已完成歸檔 □___月生效 □其他：
A104: 115010018 | B104: 1月 | C104: 全興造粒課 | D104: 03772 | E104: 查尼 | F104: 移工 | G104: 44512 | H104: 46053 | J104: 46043 | K104: =DATEDIF(G104,H104,"y") -> 4 | L104: =DATEDIF(G104,H104,"ym") -> 2 | M104: =DATEDIF(G104,H104,"MD") -> 19 | N104: =DATEDIF(G104,H104,"d") -> 1541 | O104: =IF(N104<=92,"3個月以下",IF(N104<=365,"3個月至1年",IF(N104<=1095,"1年至3年",IF(N104>1096,"3年以上")))) -> 3年以上 | P104: 資遣 | R104: □已完成歸檔 □___月生效 □其他：
A105: 115010019 | B105: 1月 | C105: 全興造粒課 | D105: 04342 | E105: 班查 | F105: 移工 | G105: 45799 | H105: 46053 | J105: 46043 | K105: =DATEDIF(G105,H105,"y") -> 0 | L105: =DATEDIF(G105,H105,"ym") -> 8 | M105: =DATEDIF(G105,H105,"MD") -> 9 | N105: =DATEDIF(G105,H105,"d") -> 254 | O105: =IF(N105<=92,"3個月以下",IF(N105<=365,"3個月至1年",IF(N105<=1095,"1年至3年",IF(N105>1096,"3年以上")))) -> 3個月至1年 | P105: 資遣 | R105: □已完成歸檔 □___月生效 □其他：
...

Sheet checkin 
A1: 2月新進
A3: 序 | B3: 薪 | C3: 部門名稱 | D3: 工號 | E3: 姓名 | F3: 職位 | G3: 到職日 | H3: 加保日 | I3: 司 | J3: 計 | K3: 等 | L3: 穩 | M3: 投 | N3: 勞 | O3: 健 | P3: 職 | Q3: 退 | R3: 銀 | S3: 類 | T3: 備註
A4: 1 | C4: 營運部 | D4: 04433 | E4: 游宗霖 | F4: 管理師 | G4: 46055 | H4: 2/2加保
A5: 2 | C5: 全興造粒課 | D5: 04434 | E5: 魏豪民 | F5: 夾子車司機 | G5: 46055 | H5: 2/2加保
A6: 3
A7: 4
A8: 5
A9: 6
A10: 7
A11: 8
A12: 9
A13: 10
A14: 11
A15: 12
A16: 13
A17: 14
A18: 15
C20: 部門 | D20: 工號 | E20: 被推薦人 | F20: 到職日 | G20: 推薦人 | H20: 獎金發放月
C21: 中區業務一課 | D21: 04416 | E21: 黃世偉 | F21: 45964 | G21: 04396陳明杰 | H21: 115.02、05
C22: 南區業務一課 | D22: 04422 | E22: 楊翠玉 | F22: 46013 | G22: 04406張玉峰 | H22: 115.03、06
C23: 中區業務一課 | D23: 04437 | E23: 吳政憲 | F23: 46076 | G23: 04153張志偉 | H23: 115.05、08

Sheet checkout 
A1: 2月離職
A3: 序 | B3: 薪 | C3: 部門名稱 | D3: 工號 | E3: 姓名 | F3: 職位 | G3: 到職日 | H3: 離職日 | I3: HRM | J3: 司 | K3: 保計 | L3: 薪計 | M3: 作 | N3: 特 | O3: 小時 | P3: 加 | Q3: 備註
A4: 1 | C4: 會計課 | D4: 01900 | E4: 蕭秀玲 | F4: 副管理師 | G4: 40848 | H4: 46066
A5: 2 | C5: 專案拓展部 | D5: 04290 | E5: 詹涴喻 | F5: 高級管理師 | G5: 45600 | H5: 46066
A6: 3 | C6: 北區業務一課 | D6: 04384 | E6: 黃聖媛 | F6: 專員 | G6: 45880 | H6: 46066
A7: 4 | C7: 企業客服課 | D7: 04425 | E7: 朱子癸 | F7: 工讀生 | G7: 46027 | H7: 46066
A8: 5 | C8: 企業客服課 | D8: 04409 | E8: 蔡亞伸 | F8: 工讀生 | G8: 45943 | H8: 46066
A9: 6 | C9: 北區業務二課 | D9: 03830 | E9: 劉家男 | F9: 3.5噸司機 | G9: 44684 | H9: 46079
A10: 7 | C10: 全興造粒課 | D10: 04260 | E10: 鄭權瀚 | F10: 組長 | G10: 45516 | H10: 46081
A11: 8 | C11: 品保課 | D11: 03558 | E11: 張家倫 | F11: 主任 | G11: 43927 | H11: 46081
A12: 9 | C12: 資訊部專案管理課 | D12: 03611 | E12: 徐銘駿 | F12: 高級工程師 | G12: 44109 | H12: 46081
A13: 10 | C13: 資訊部專案管理課 | D13: 02567 | E13: 廖欣怡 | F13: 高級工程師 | G13: 41935 | H13: 46081
A14: 11 | C14: 品保課 | D14: 03812 | E14: 黃鈺婷 | F14: 副工程師 | G14: 44657 | H14: 46081
A15: 12 | C15: 加盟管理課 | D15: 04116 | E15: 談靜柔 | F15: 管理師 | G15: 45139 | H15: 46081
A16: 13
A17: 14
A18: 15
A19: 16
A20: 17
A21: 18
A22: 19
A23: 20

Sheet 給工安(每月)
A1: 部門 | B1: 工號 | C1: 姓名 | D1: 性別 | E1: 職稱 | F1: 到職日期 | G1: 離職日 | H1: 備註
A2: 營運管理部 | B2: 03334 | C2: 吳宗勳 | D2: 男 | E2: 3.5噸小車司機 | F2: 43395 | G2: 45792
A3: 營運管理部 | B3: 04306 | C3: 滕芸 | D3: 女 | E3: 管理師 | F3: 45691 | G3: 45779
A4: 業務開發部 | B4: 03736 | C4: 蔡玉茹 | D4: 女 | E4: 助理會計 | F4: 44461 | G4: 45786
A5: 再生紡織設計部 | B5: 04178 | C5: 胡嘉容 | D5: 女 | E5: 副管理師 | F5: 45341 | G5: 45808
A6: 業務開發部 | B6: 04332 | C6: 李世昌 | D6: 男 | E6: 儲備夾子車司機 | F6: 45754 | G6: 45793
A7: 營運管理部 | B7: 03616 | C7: 林福基 | D7: 男 | E7: 3.5噸小車司機 | F7: 44118 | G7: 45808
A8: 業務開發部 | B8: 03644 | C8: 高健棠 | D8: 男 | E8: 作業員 | F8: 44216 | G8: 45808
A9: 行銷部 | B9: 04307 | C9: 許湘琦 | D9: 女 | E9: 副管理師 | F9: 45691 | G9: 45808
A10: 業務開發部 | B10: 04320 | C10: 王子珉 | D10: 男 | E10: 大貨車司機 | F10: 45721 | G10: 45808
A11: 業務開發部 | B11: 04343 | C11: 方亞庭 | D11: 女 | E11: 副管理師 | F11: 45803 | G11: 45806
A13: 部門 | B13: 工號 | C13: 姓名 | D13: 職位 | E13: 到職日 | F13: 備註
A14: 全興處理二課 | B14: 04339 | C14: 納他吳 | D14: 移工 | E14: 45789
A15: 中區業務一課 | B15: 04340 | C15: 黃培源 | D15: 作業員 | E15: 45796
A16: 中區業務一課 | B16: 04344 | C16: 張永興 | D16: 作業員 | E16: 45803
A17: 中區業務一課 | B17: 04346 | C17: 何政風 | D17: 拖車司機 | E17: 45803
A18: 中區業務一課 | B18: 04345 | C18: 張慧君 | D18: 作業員 | E18: 45803
A19: 北區業務二課 | B19: 04341 | C19: 江盛州 | D19: 作業員 | E19: 45796
A20: 全興造粒課 | B20: 04342 | C20: 班查 | D20: 移工 | E20: 45799

Sheet 原因細分類
A2: 家庭因素
A3: 搬家結婚
A4: 個人問題
A5: 身體因素
A6: 繼續升學 | B6: 含服兵役
A7: 交通問題
A8: 環境問題
A9: 工作性質
A10: 工時問題
A11: 休假制度
A12: 班次制度
A13: 另謀高就
A14: 管理制度
A15: 福利制度
A16: 主管問題
A17: 教育訓練
A18: 薪資問題
... A30: 環境因素

Sheet 離職資料夾命名用
A1: 序號 | B1: 離職申請單 | C1: - | D1: 工號 | E1: 姓名 | F1: 結果
A2: 1. | B2: 離職申請單 | C2: - | D2: 04299 | E2: 黃筠倫 | F2: =IF(D2="","",A2&B2&C2&D2&E2) -> 1.離職申請單-04299黃筠倫
A3: 2. | B3: 離職申請單 | C3: - | D3: 04279 | E3: 施詠覺 | F3: =IF(D3="","",A3&B3&C3&D3&E3) -> 2.離職申請單-04279施詠覺
A4: 3. | B4: 離職申請單 | C4: - | D4: 04283 | E4: 宋承憲 | F4: =IF(D4="","",A4&B4&C4&D4&E4) -> 3.離職申請單-04283宋承憲
A5: 4. | B5: 離職申請單 | C5: - | D5: 03898 | E5: 陳怡樺 | F5: =IF(D5="","",A5&B5&C5&D5&E5) -> 4.離職申請單-03898陳怡樺
A6: 5. | B6: 離職申請單 | C6: - | D6: 04181 | E6: 廖尉君 | F6: =IF(D6="","",A6&B6&C6&D6&E6) -> 5.離職申請單-04181廖尉君
A7: 6. | B7: 離職申請單 | C7: - | D7: 04303 | E7: 蔡孟儒 | F7: =IF(D7="","",A7&B7&C7&D7&E7) -> 6.離職申請單-04303蔡孟儒
A8: 7. | B8: 離職申請單 | C8: - | D8: 04327 | E8: 陳基展 | F8: =IF(D8="","",A8&B8&C8&D8&E8) -> 7.離職申請單-04327陳基展
A9: 8. | B9: 離職申請單 | C9: - | D9: 00009 | E9: 曾石雄 | F9: =IF(D9="","",A9&B9&C9&D9&E9) -> 8.離職申請單-00009曾石雄
A10: 9. | B10: 離職申請單 | C10: - | D10: 04282 | E10: 李勝裕 | F10: =IF(D10="","",A10&B10&C10&D10&E10) -> 9.離職申請單-04282李勝裕
A11: 10. | B11: 離職申請單 | C11: - | D11: 04316 | E11: 林庭鋐 | F11: =IF(D11="","",A11&B11&C11&D11&E11) -> 10.離職申請單-04316林庭鋐
A12: 11. | B12: 離職申請單 | C12: - | F12: =IF(D12="","",A12&B12&C12&D12&E12)
A13: 12. | B13: 離職申請單 | C13: - | F13: =IF(D13="","",A13&B13&C13&D13&E13)
A14: 13. | B14: 離職申請單 | C14: - | F14: =IF(D14="","",A14&B14&C14&D14&E14)
A15: 14. | B15: 離職申請單 | C15: - | F15: =IF(D15="","",A15&B15&C15&D15&E15)
A16: 15. | B16: 離職申請單 | C16: - | F16: =IF(D16="","",A16&B16&C16&D16&E16)
A17: 16. | B17: 離職申請單 | C17: - | F17: =IF(D17="","",A17&B17&C17&D17&E17)
A18: 17. | B18: 離職申請單 | C18: - | F18: =IF(D18="","",A18&B18&C18&D18&E18)
A19: 18. | B19: 離職申請單 | C19: - | F19: =IF(D19="","",A19&B19&C19&D19&E19)
A20: 19. | B20: 離職申請單 | C20: - | F20: =IF(D20="","",A20&B20&C20&D20&E20)
A21: 20. | B21: 離職申請單 | C21: - | F21: =IF(D21="","",A21&B21&C21&D21&E21)
A22: 21. | B22: 離職申請單 | C22: - | F22: =IF(D22="","",A22&B22&C22&D22&E22)
A23: 22. | B23: 離職申請單 | C23: - | F23: =IF(D23="","",A23&B23&C23&D23&E23)
... A34: 33. | B34: 離職申請單 | C34: - | F34: =IF(D34="","",A34&B34&C34&D34&E34)

Sheet 到職(舊)
B1: 部門 | C1: 工號 | D1: 姓名 | E1: 職位 | F1: 成本中心 | G1: 到職日 | H1: 勞健保 | I1: 備註
B2: 台中分公司 | D2: 吳春嬌 | E2: 業務助理 | G2: 39136 | AG2: 外勞稅
B3: 台南站 | D3: 楊鎮愷 | E3: 司機 | G3: 39139 | W3: 4000
B4: 台南站 | D4: 李智銘 | E4: 司機 | G4: 39139 | H4: 理賠金額
B5: 董事長室 | D5: 黃冀如 | E5: 高專 | G5: 39139
B6: 業務處 | D6: 陳蓉茱 | E6: 業務助理 | G6: 39139
B7: 香山站 | C7: 0900311 | D7: 袁金華 | E7: 基層作業員 | G7: 39140 | H7: 隔離1萬
B8: 香山站 | D8: 龍雲生 | E8: 基層作業員 | G8: 39141
B9: 香山站 | D9: 張瑞珍 | E9: 基層作業員 | G9: 39141
B10: 管理部 | D10: 李惠茹 | E10: 總務助理 | G10: 39142
B11: 董事長室 | D11: 徐忠義 | E11: 高專 | G11: 39142
B12: 02674 | D12: 蕭幸伃 | E12: 營運部助理 | G12: 39142
B13: 業務處 | D13: 林沐蓉 | E13: 二手商店助理 | G13: 39142
B14: 旺利站 | D14: 柯益成 | E14: 外場人員 | G14: 39142 | O14: =SUM(O4:O13) -> 0
B15: 旺利站 | D15: 周秉宏 | G15: 39142
B16: 旺利站 | D16: 楊克明 | E16: 外場人員 | G16: 39142
D17: 湯金鳳 | E17: 基層作業員 | G17: 39146
B18: 台南站 | D18: 朱啟東 | E18: 司機 | G18: 39146
B19: 台南站 | D19: 蘇薇薇 | E19: 晚班會計助理 | G19: 39146
B20: 總公司 | D20: 葉莉婷 | E20: 清潔工 | G20: 39146
B21: 香山站 | D21: 李愛玉 | E21: 基層作業員 | G21: 39147
D22: 王瑜君 | E22: 基層作業員 | G22: 39149
B23: 土城站 | D23: 陳玉勳 | E23: 會計助理 | G23: 39149
D24: 陳金進 | E24: 堆高機司機 | G24: 39150
B25: 台中分公司 | D25: 李志遠 | E25: 司機 | G25: 39150
B26: 台南站 | D26: 葉榮霖 | E26: 司機 | G26: 39153
B27: 台南站 | D27: 吳益勤 | G27: 39155
B28: 桃園站 | D28: 楊肇嘉 | E28: 儲備幹部 | G28: 39155
B29: 總公司 | D29: 林雅倫 | E29: 行政人員 | G29: 39157
D30: 陳輝和 | E30: 堆高機司機 | G30: 39157
D31: 邱徐秀 | G31: 39157
B32: 土城站 | D32: 黃宜達 | E32: 外場人員 | G32: 39160
B33: 和美站 | D33: 廖國棟 | E33: 外場人員 | G33: 39160
B34: 總公司 | D34: 張永豪 | E34: 行政人員 | G34: 39160
D35: 黃瓊嬅 | E35: 基層作業員 | G35: 39161
D36: 葉秀卿 | E36: 基層作業員 | G36: 39161
D37: 黃子洛 | E37: 基層作業員 | G37: 39161
B38: 桃園站 | D38: 黃玉林 | E38: 司機 | G38: 39163
B39: 土城站 | D39: 吳志明 | E39: 外場人員 | G39: 39163
B40: 土城站 | D40: 黎永君 | E40: 儲備幹部 | G40: 39164
B41: 總公司 | D41: 鄭韻如 | E41: 行政助理 | G41: 39164
B42: 土城站 | D42: 謝其樺 | E42: 外場人員 | G42: 39167
B43: 和美站 | D43: 黃朧友 | E43: 外場人員 | G43: 39167
B44: 總公司 | D44: 許雅嵐 | E44: 財務助理 | G44: 39167
B45: 全興廠 | D45: 陳宗堯 | E45: 副理 | G45: 39167
B46: 太平站 | D46: 林傑茵 | E46: 窗口會計助理 | G46: 39167
B47: 台南站 | D47: 陳品榛 | E47: 窗口會計助理 | G47: 39168
B48: 和美站 | D48: 黃志鴻 | E48: 外場人員 | G48: 39171
B49: 總公司 | D49: 呂佩璇 | E49: 教育訓練師 | G49: 39171
... B53: 台中環保局 | D53: 劉宜榛 | E53: 會計助理 | G53: 39178
D54: 黃亞李 | E54: 基層作業員 | G54: 39178
B55: 桃園站 | D55: 淩敏傑 | E55: 儲備幹部 | G55: 39178
B56: 香山站 | D56: 廖上榕 | E56: 窗口會計助理 | G56: 39182
B57: 文山環保 | D57: 許秀敏 | G57: 39182
B58: 文山環保 | D58: 黃麗足 | G58: 39182
B59: 文山環保 | D59: 謝順慶 | G59: 39182
B60: 文山環保 | D60: 陳美吟 | G60: 39182
B61: 文山環保 | D61: 林粉 | G61: 39182
B62: 文山環保 | D62: 何金峰 | G62: 39182
B63: 文山環保 | D63: 張瑋鍾 | G63: 39182
B64: 文山環保 | D64: 張瑋航 | G64: 39182
B65: 文山環保 | D65: 李春茹 | G65: 39182
B66: 文山環保 | D66: 陳力浩 | G66: 39182
B67: 文山環保 | D67: 謝遠彰 | G67: 39182
B68: 文山環保 | D68: 廖國清 | G68: 39182
... B73: 文山環保 | D73: 張詩筠 | G73: 39182
D74: 曾麗雲 | E74: 基層作業員 | G74: 39182
B75: 文山環保 | D75: 嚴瑞嬌 | G75: 39183
B76: 文山環保 | D76: 白馨佩 | G76: 39183
B77: 文山環保 | D77: 松家琪 | G77: 39183
B78: 文山環保 | D78: 陳秀娟 | G78: 39183
B79: 文山環保 | D79: 尤聖道 | G79: 39184
D80: 莊創銘 | E80: 司機 | G80: 39185
B81: 文山環保 | D81: 鄭舒瑜 | E81: 窗口會計助理 | G81: 39185
B82: 文山環保 | D82: 陳榮裕 | E82: 外場人員 | G82: 39185
B83: 太平站 | D83: 林育弘 | E83: 外場人員 | G83: 39155
B84: 香山站 | D84: 陳巧雲 | E84: 基層作業員 | G84: 39155
B85: 香山站 | D85: 鍾國良 | E85: 基層作業員 | G85: 39155
B86: 員林站 | D86: 盧月玲 | E86: 窗口會計助理 | G86: 39188
B87: 總公司 | D87: 張政嘉 | E87: 程式設計師 | G87: 39188
B88: 文山環保 | D88: 王正雄 | G88: 39188
B89: 總公司 | D89: 許俶菁 | E89: 行政人員 | G89: 39188
B90: 總公司 | D90: 王寶郎 | E90: 帳務組長 | G90: 39188
B91: 香山站 | D91: 楊清城 | G91: 39188
D92: 周彩珠 | E92: 基層作業員 | G92: 39188
D93: 趙彩鑾 | G93: 39185
D94: 陳秀滿 | G94: 39185
D95: 陳金賜 | G95: 39189
B96: 文山環保 | D96: 黃柏榕 | E96: 外場人員 | G96: 39189
B97: 文山環保 | D97: 施家閔 | E97: 外場人員 | G97: 39189
B98: 文山環保 | D98: 王儀婕 | E98: 窗口會計助理 | G98: 39189
B99: 文山環保 | D99: 陳坤桔 | G99: 39190
B100: 文山環保 | D100: 陳志雄 | G100: 39190
B101: 香山站 | D101: 胡秋娥 | G101: 39190
B102: 大廈站 | D102: 古豐豪 | G102: 39190
B103: 文山環保 | D103: 官桂美 | G103: 39191
B104: 太平站 | D104: 顏谷賓 | E104: 外場人員 | G104: 39192
B105: 業務處 | D105: 吳至鎔 | E105: 司機 | G105: 39190
B106: 業務處 | D106: 廖冠富 | E106: 司機 | G106: 39190
B107: 業務處 | D107: 吳政道 | E107: 司機 | G107: 39192
...

Sheet 離職(舊)
A1: 通知日 | B1: 站別 | C1: 工號 | D1: 姓名 | E1: 職位 | F1: 到職日 | G1: 離職日 | H1: 備註 | I1: 離職單 | J1: 離職證明 | K1: 薪資單 | L1: mail發出
B2: 香山站 | D2: 林政禕 | E2: 寒假工讀生 | G2: 39136 | H2: 聘僱期間到期
B3: 香山站 | D3: 陳貴勇 | E3: 寒假工讀生 | G3: 39136 | H3: 聘僱期間到期
B4: 香山站 | D4: 吳治翰 | E4: 寒假工讀生 | G4: 39139 | H4: 聘僱期間到期
B5: 全興站 | D5: 葉盈蘭 | E5: 基層作業員 | G5: 39139
B6: 台南站 | D6: 柯美月 | E6: 臨時工 | G6: 39139 | H6: 聘僱期間到期
B7: 台南站 | D7: 吳國銘 | E7: 臨時工 | G7: 39139 | H7: 聘僱期間到期
B8: 台南站 | D8: 楊財發 | E8: 臨時工 | G8: 39139 | H8: 聘僱期間到期
B9: 台南站 | D9: 蔡志偉 | E9: 臨時工 | G9: 39139 | H9: 聘僱期間到期
B10: 全興站 | D10: 阮翠雲 | E10: 中班作業員 | G10: 39140
B11: 業務處 | D11: 何致慧 | E11: 業務 | G11: 39141
B12: 台南站 | D12: 楊鎮愷 | E12: 司機 | G12: 39141
B13: 台南站 | D13: 李智銘 | E13: 司機 | G13: 39141
B14: 香山站 | D14: 楊淑女 | E14: 基層作業員 | G14: 39141
B15: 香山站 | D15: 張瑞珍 | E15: 基層作業員 | G15: 39141
B16: 旺利站 | D16: 江嘉峰 | E16: 寒假工讀生 | G16: =SUM(G2:G14) -> 508810 | H16: 聘僱期間到期
B17: 香山站 | D17: 龍雲生 | E17: 計時人員 | G17: 39142
B18: 香山站 | D18: 鄧景秀 | E18: 計時人員 | G18: 39142
B19: 台南站 | D19: 劉寶蓮 | E19: 計時人員 | G19: 39142
B20: 旺利站 | D20: 簡瑞益 | E20: 外場人員 | G20: 39147
B21: 台南站 | D21: 蘇薇薇 | E21: 會計助理 | G21: 39147
B22: 台南站 | D22: 朱啟東 | E22: 司機 | G22: 39148
B23: 台南站 | D23: 林淙安 | E23: 基層作業員 | G23: 39149
B24: 總公司 | D24: 葉莉婷 | E24: 清潔工 | G24: 39150
B25: 業務處 | D25: 鄭昌峻 | E25: 業務 | G25: 39144
B26: 業務處 | D26: 劉建國 | E26: 司機 | G26: 39153
B27: 總公司 | D27: 黃朝陽 | E27: 總務專員 | G27: 39153
B28: 業務處 | D28: 葉嘉琳 | E28: 業務助理 | G28: 39153
B29: 總公司 | D29: 李惠茹 | E29: 總務助理 | G29: 39155 | H29: 免職 | L29: 資訊財部
B30: 台南站 | D30: 李金魚 | E30: 基層作業員 | G30: 39156 | U30: 育生日
B31: 全興站 | D31: 黃梅蘭 | E31: 基層作業員 | G31: 39156
B32: 台南站 | D32: 盧詩武 | E32: 外場人員 | G32: 39160
B33: 喬翔站 | D33: 邱泓澍 | E33: 司機 | G33: 39160
B34: 總公司 | D34: 葉子君 | E34: 程式設計師 | G34: 39160
D35: 黃瓊嬅 | E35: 基層作業員 | G35: 39163
D36: 葉秀卿 | E36: 基層作業員 | G36: 39163
B37: 和美站 | D37: 陳永龍 | E37: 外場人員 | G37: 39163
B38: 總公司 | D38: 林雅倫 | E38: 行政助理 | G38: 39163
B39: 總公司 | D39: 張永豪 | E39: 行政助理 | G39: 39164
B40: 旺利站 | D40: 陳裕文 | E40: 司機 | G40: 39167
B41: 土城站 | D41: 黎永君 | E41: 儲備幹部 | G41: 39261
B42: 台南站 | D42: 陳品榛 | E42: 窗口會計 | G42: 39169
B43: 和美站 | D43: 黃朧友 | E43: 外場人員 | G43: 39170
B44: 草屯站 | D44: 洪立信 | E44: 外場人員 | G44: 39172
B45: 桃園站 | D45: 郭志恒 | E45: 司機 | G45: 39172
B46: 南屯站 | D46: 呂若蘭 | E46: 窗口會計 | G46: 39174
B47: 和美站 | D47: 廖國棟 | E47: 外場人員 | G47: 39174
B48: 和美站 | D48: 黃志鴻 | E48: 外場人員 | G48: 39174
... B50: 文山環保 | D50: 劉宜榛 | E50: 會計助理 | G50: 39178
D51: 黃亞李 | E51: 基層作業員 | G51: 39178
B52: 大廈站 | D52: 張文良 | E52: 司機 | G52: 39181 | H52: 免職
B53: 文山環保 | D53: 謝順慶 | E53: 計時人員 | G53: 39182
B54: 香山站 | D54: 廖上榕 | E54: 窗口會計 | G54: 39182
B55: 文山環保 | D55: 白馨佩 | G55: 39183
B56: 文山環保 | D56: 松家琪 | G56: 39183
B57: 文山環保 | D57: 陳秀娟 | G57: 39183
B58: 資部 | D58: 曾麗雲 | E58: 基層作業員 | G58: 2007/04//12
B59: 資部 | D59: 姚月霞 | E59: 基層作業員 | G59: 39184
B60: 資部 | D60: 鄭玉玲 | E60: 基層作業員 | G60: 39184
B61: 文山環保 | D61: 陳榮裕 | E61: 外場人員 | G61: 39186
B62: 文山環保 | D62: 鄭舒瑜 | E62: 會計助理 | G62: 39186
B63: 台南站 | D63: 黃基憶 | E63: 基層作業員 | G63: 39186
B64: 太平站 | D64: 林育弘 | E64: 外場人員 | G64: 39186
B65: 土城站 | D65: 謝慶樺 | E65: 外場人員 | G65: 39186 | H65: 免職
B66: 香山站 | D66: 陳巧雲 | G66: 39186
B67: 香山站 | D67: 鐘國良 | G67: 39188
B68: 香山站 | D68: 詹春妹 | G68: 39188
B69: 文山環保 | D69: 林秋香 | G69: 39188
B70: 資部 | D70: 梁氏垂玲 | E70: 基層作業員 | G70: 39189
B71: 文山環保 | D71: 黃柏榕 | E71: 外場人員 | G71: 39189
B72: 文山環保 | D72: 施家閔 | E72: 外場人員 | G72: 39189
B73: 香山站 | D73: 楊清城 | G73: 39191
D74: 陳金賜 | G74: 39191
B75: 文山環保 | D75: 陳坤桔 | G75: 39192
B76: 文山環保 | D76: 張詩筠 | G76: 39195
B77: 文山環保 | D77: 嚴瑞嬌 | G77: 39195
B78: 文山環保 | D78: 尤聖道 | G78: 39195
B79: 文山環保 | D79: 王正雄 | G79: 39195
B80: 文山環保 | D80: 陳碧珍 | G80: 39195
B81: 文山環保 | D81: 陳素月 | G81: 39195
B82: 文山環保 | D82: 陳力浩 | G82: 39195
B83: 文山環保 | D83: 張瑋航 | G83: 39195
B84: 文山環保 | D84: 張瑋鐘 | G84: 39195
B85: 文山環保 | D85: 柯金峰 | G85: 39195
B86: 文山環保 | D86: 林粉 | G86: 39195
... B88: 文山環保 | D88: 黃麗足 | G88: 39195
B89: 輔祥專案 | D89: 徐煲堂 | E89: 外場人員 | G89: 39195
B90: 文山環保 | D90: 吳明佳 | G90: 39195
B91: 香山站 | D91: 胡秋娥 | G91: 39197 | H91: 免職
D92: 柯綠鄉 | E92: 基層作業員 | G92: 39196
B93: 文山環保 | D93: 林芳杰 | G93: 39197
B94: 香山站 | D94: 黃詩穎 | G94: 39198
B95: 香山站 | D95: 楊清城 | G95: 39199
D96: 白慧貞 | E96: 基層作業員 | G96: 39198
B97: 香山站 | D97: 陳瑞英 | E97: 窗口會計助理 | G97: 39202
B98: 香山站 | D98: 孫萬榮 | G98: 39202 | H98: 免職
B99: 香山站 | D99: 李愛玉 | G99: 39202 | H99: 免職
B100: 神岡站 | D100: 張瑋昀 | E100: 窗口會計助理 | G100: 39199
B101: 總公司 | D101: 許俶菁 | E101: 行政助理 | G101: 39202
D102: 阮氏嫺 | E102: 基層作業員 | G102: 39202
...

Sheet 工作表1
A1: 大豐科 | B1: 云想 | C1: 和東 | D1: 青心 | E1: 保長 | F1: 員信 | G1: 神林 | H1: 草屯 | I1: 新竹

Sheet checkin6月 
A1: 6月新進
A3: 序 | B3: 薪 | C3: 部門名稱 | D3: 工號 | E3: 姓名 | F3: 職位 | G3: 等 | H3: 穩 | I3: 投 | J3: 勞 | K3: 健 | L3: 職 | M3: 退 | N3: 銀 | O3: 類 | P3: 到職日 | Q3: 加保日 | R3: 備註
A4: 1 | C4: 員林站 | D4: 04349 | E4: 鄭志勝 | F4: 外場人員 | P4: 45810 | Q4: 6/2加保
A5: 2 | C5: 國際事業部業務課 | D5: 04347 | E5: 陳睿婕 | F5: 業務高級專員 | P5: 45810 | Q5: 6/2加保
A6: 3 | C6: 北區業務三課 | D6: 04348 | E6: 侯兆謙 | F6: 副管理師 | P6: 45813 | Q6: 6/5加保
A7: 4 | C7: 和美站 | D7: 04350 | E7: 吳承澤 | F7: 拖車司機 | P7: 45817 | Q7: 6/9加保
A8: 5 | C8: 中區業務一課 | D8: 04352 | E8: 蔣文寶 | F8: 3.5噸小車司機 | P8: 45817 | Q8: 6/9加保
A9: 6 | C9: 中區業務一課 | D9: 04351 | E9: 王佩君 | F9: 物流專員 | P9: 45817 | Q9: 6/9加保
A10: 7 | C10: 南區業務一課 | D10: 04353 | E10: 曾榮煌 | F10: 駐廠工安人員 | P10: 45819 | Q10: 6/11加保
A11: 8 | C11: 中區業務一課 | D11: 04354 | E11: 陳詠銘 | F11: 作業員(駐彰化矽品) | P11: 45824 | Q11: 6/16加保
A12: 9 | C12: 中區業務一課 | D12: 04355 | E12: 彭志翔 | F12: 作業員(駐后里矽品) | P12: 45826 | Q12: 6/18加保
A13: 10 | C13: 中區業務一課 | D13: 04356 | E13: 劉正偉 | F13: 夾子車司機 | P13: 45826 | Q13: 6/18加保

Sheet checkout 6月 
A1: 6月離職
A3: 序 | B3: 薪 | C3: 部門名稱 | D3: 工號 | E3: 姓名 | F3: 職位 | G3: 作 | H3: 特 | I3: 小時 | J3: 加 | K3: 到職日 | L3: 離職日 | M3: 備註
A4: 1 | C4: 全興造粒課 | D4: 03896 | E4: 卿那芃 | F4: 移工 | K4: 44818 | L4: 45811
A5: 2 | C5: 再生紡織設計部 | D5: 04179 | E5: 林軒妤 | F5: 副管理師 | K5: 45341 | L5: 45818
A6: 3 | C6: 全興造粒課 | D6: 04313 | E6: 王士駿 | F6: 外場人員 | K6: 45705 | L6: 45813
A7: 4 | C7: 中區業務一課 | D7: 04351 | E7: 王佩君 | F7: 倉儲物流專員 | K7: 45817 | L7: 45818
A8: 5 | C8: 南區業務二課 | D8: 03834 | E8: 羅景立 | F8: 作業員 | K8: 44685 | L8: 45822
A9: 6 | C9: 家電課服課 | D9: 04202 | E9: 洪藝禎 | F9: 助理管理師 | K9: 45404 | L9: 45828
A10: 7 | C10: 南區業務二課 | D10: 04224 | E10: 傅漢源 | F10: 夾子車司機 | K10: 45446 | L10: 45833
A11: 8 | C11: 中區業務一課 | D11: 04246 | E11: 李承軒 | F11: 作業員 | K11: 45488 | L11: 45838
A12: 9 | C12: 全興處理二課 | D12: 01352 | E12: 劉月鳳 | F12: 分選員 | K12: 40071 | L12: 45838
A13: 10 | C13: 再生紡織設計部 | D13: 04177 | E13: 廖均淳 | F13: 管理師 | K13: 45341 | L13: 45838
A14: 11 | C14: 中區業務一課 | D14: 04340 | E14: 黃培源 | F14: 作業員 | K14: 45796 | L14: 45838
A15: 12 | C15: 中區業務一課 | D15: 03792 | E15: 甘霖憲 | F15: 班長 | K15: 44553 | L15: 45838

Sheet checkin5月
A1: 5月新進
A3: 序 | B3: 薪 | C3: 部門名稱 | D3: 工號 | E3: 姓名 | F3: 職位 | G3: 等 | H3: 穩 | I3: 投 | J3: 勞 | K3: 健 | L3: 職 | M3: 退 | N3: 銀 | O3: 類 | P3: 到職日 | Q3: 加保日 | R3: 備註
A4: 1 | C4: 北區業務二課 | E4: 葉科旻 | F4: 作業員 | P4: 45782 | Q4: 5/5加保
A5: 2 | C5: 北區業務二課 | D5: 04336 | E5: 鍾雲青 | F5: 作業員 | P5: 45782 | Q5: 5/5加保
A6: 3 | C6: 全興處理二課 | D6: 04337 | E6: 薩拉育 | F6: 移工 | P6: 45782 | Q6: 5/4加保 | R6: 5/4入境
A7: 4 | C7: 神岡站 | D7: 04338 | E7: 陳建勳 | F7: 拖車司機 | P7: 45782 | Q7: 5/5加保
A8: 5 | C8: 全興處理二課 | D8: 04339 | E8: 納他吳 | F8: 移工 | P8: 45789 | Q8: 5/11加保
A9: 6 | C9: 中區業務一課 | D9: 04340 | E9: 黃培源 | F9: 作業員(駐矽品中山) | P9: 45796 | Q9: 5/19加保
A10: 7 | C10: 北區業務二課 | D10: 04341 | E10: 江盛州 | F10: 作業員(駐廠矽品) | P10: 45796 | Q10: 5/19加保
A11: 8 | C11: 全興造粒課 | D11: 04342 | E11: 班查 | F11: 移工 | P11: 45799 | Q11: 5/22加保
A12: 9 | C12: 南區業務一課 | E12: 方亞庭 | F12: 副管理師(駐美光) | P12: 2025/5/26
A13: 10 | C13: 中區業務一課 | E13: 張永興 | F13: 作業員(駐矽品大豐) | P13: 2025/5/26
A14: 11 | C14: 中區業務一課 | E14: 張慧君 | F14: 作業員(駐矽品大豐) | P14: 2025/5/26

Sheet checkout 5月
A1: 5月離職
A3: 序 | B3: 薪 | C3: 部門名稱 | D3: 工號 | E3: 姓名 | F3: 職位 | G3: 作 | H3: 特 | I3: 小時 | J3: 加 | K3: 到職日 | L3: 離職日 | M3: 備註
A4: 1 | C4: 北區業務二課 | E4: 葉科旻 | F4: 作業員 | K4: 45782 | L4: 45786 | M4: 連曠三日
A5: 2 | C5: 中區業務一課 | D5: 03736 | E5: 蔡玉茹 | F5: 助理會計 | K5: 44461 | L5: 45786
A6: 3 | C6: 金馬站 | D6: 03334 | E6: 吳宗勳 | F6: 3.5噸司機 | K6: 43395 | L6: 45792
A7: 4 | C7: 南區業務一課 | D7: 04332 | E7: 李世昌 | F7: 儲備夾子車司機 | K7: 45754 | L7: 45793
A8: 5 | C8: 新竹站 | D8: 03616 | E8: 林福基 | F8: 3.5噸司機 | K8: 2020/10/14 | L8: 45808
A9: 6 | C9: 南區業務一課 | D9: 03760 | E9: 阮志安 | F9: 夾子車司機 | K9: 2021/11/01 | L9: 45808 | M9: 原育嬰留停期限:113/7/31-114/7/31，14/5/31退保(資遣)
A10: 7 | C10: 南區業務一課 | D10: 03664 | E10: 高健棠 | F10: 作業員 | K10: 44216 | L10: 45808
A11: 8 | C11: 再生紡織設計部 | D11: 04178 | E11: 胡嘉容 | F11: 副管理師 | K11: 45341 | L11: 45808
A12: 9 | C12: 行銷部 | D12: 04307 | E12: 許湘琦 | F12: 副管理師 | K12: 45691 | L12: 45808
A13: 10
A14: 11
A15: 12
A16: 13
A17: 14

Sheet 加盟主
A1: 姓名 | B1: 計畫別 | C1: 加保日 | D1: 預計退保日 | E1: 退保日 | F1: ID | G1: 出生年月日 | H1: 備註
A2: 林芃宏 | B2: 300 | C2: 107/1/3 | D2: 43192 | E2: 43192
A3: 林雍智 | B3: 100 | C3: 107/1/16 | D3: 43205 | E3: 43206 | F3: P122933887 | G3: 0711122
A4: 楊昌權 | B4: 100 | C4: 107/2/21 | D4: 43240 | E4: 43241 | F4: F128248111 | G4: 0680921
A5: 張智銘 | B5: 100 | C5: 107/6/11 | D5: 43353 | E5: 43353 | F5: F124014682 | G5: 0661202
A6: 楊能全 | B6: 100 | C6: 107/6/11 | D6: 43353 | E6: 43353 | F6: O100087092 | G6: 0760730
A7: 張坤男 | B7: 100 | C7: 107/7/3 | D7: 43375 | E7: 43375 | F7: N123857849 | G7: 0710623
A8: 許峻榕 | B8: 100 | C8: 107/12/1 | D8: 43524 | E8: 43567 | F8: P123133416 | G8: 0760810

Sheet 仲介
A1: 站別 | B1: 投保單位 | C1: 姓名 | D1: 職位 | E1: 到職日 | F1: 加保日 | G1: 離職日 | H1: 退保日 | I1: ID | J1: 出生年月日 | K1: 備註
A2: 金馬組 | B2: 金馬 | C2: 鄭旗財 | D2: 臨時工 | E2: 42858 | F2: 5/3加保(不加健保) | G2: 42861 | H2: 5/6退保 | I2: K120201325 | J2: 48.05.01
A3: 金馬組 | B3: 金馬 | C3: 張丙 | D3: 臨時工 | E3: 42858 | F3: 5/3加保(不加健保) | G3: 42861 | H3: 5/6退保 | I3: Q121685507 | J3: 49.03.25
A4: 金馬組 | B4: 金馬 | C4: 楊鴻鈞 | D4: 臨時工 | E4: 42865 | F4: 5/10加保(不加健保) | G4: 42877 | H4: 5/22退保 | I4: P122820509 | J4: 74.10.27
A5: 金馬組 | B5: 金馬 | C5: 張仁才 | D5: 臨時工 | E5: 42872 | F5: 5/17加保(不加健保) | G5: 42882 | H5: 5/27退保 | I5: N122903708 | J5: 64.10.25
A6: 金馬組 | B6: 金馬 | C6: 卓嘉軒 | D6: 臨時工 | E6: 42877 | F6: 5/22加保(不加健保) | G6: 42895 | H6: 6/14退保 | I6: M122302497 | J6: 77.1.21
A7: 中部倉庫 | B7: 金馬 | C7: 陳炯旭 | D7: 臨時工 | E7: 42884 | F7: 5/29加保(不加健保) | G7: 42885 | H7: 5/30退保 | I7: L120727486 | J7: 058 年 07 月 06 日
A8: 中部倉庫 | B8: 金馬 | C8: 吳俊潾 | D8: 臨時工 | E8: 42884 | F8: 5/29加保(不加健保) | G8: 42885 | H8: 5/30退保 | I8: L125612408 | J8: 087 年 11 月 15 日
A9: 中部倉庫 | B9: 金馬 | C9: 王俊傑 | D9: 臨時工 | E9: 42884 | F9: 5/29加保(不加健保) | G9: 42885 | H9: 5/30退保 | I9: F125731155 | J9: 072 年 01 月 17 日
A10: 中部倉庫 | B10: 金馬 | C10: 陳文政 | D10: 臨時工 | E10: 42884 | F10: 5/29加保(不加健保) | G10: 42885 | H10: 5/30退保 | I10: B122949544 | J10: 081 年 08 月 08 日
A11: 金馬組 | B11: 金馬 | C11: 謝耀中 | D11: 臨時工 | E11: 42887 | F11: 6/1加保(不加健保) | G11: 42887 | H11: 6/2退保 | I11: N123125762 | J11: 65.05.14
A12: 金馬組 | B12: 金馬 | C12: 黃駿騰 | D12: 臨時工 | E12: 42891 | F12: 6/5加保(不加健保) | G12: 42895 | H12: 6/14退保 | I12: N124144930 | J12: 71.7.29
A13: 中部倉庫 | B13: 金馬 | C13: 王俊傑 | D13: 臨時工 | E13: 42893 | F13: 6/7加保(不加健保) | G13: 42895 | H13: 6/9退保 | I13: F125731155 | J13: 72.01.17
... A21: 中部倉庫 | B21: 金馬 | C21: 白松軒 | D21: 臨時工 | E21: 42914 | F21: 6/28加保(不加健保) | G21: 42915 | H21: 6/29退保 | I21: L123795557 | J21: 60.03.28
